Workbook

Sheet Control Sheet
A1: Hakim Group | Payroll Reconciliation Tool
B4: Monthly Control Panel
B5: Tolerance - HG practices (%) | C5: 0.2
B6: Tolerance - HO2 practice (%) | C6: 0.05
B7: Minimum £ to flag | C7: 50
B8: Prior period label | C8: June 2026
B9: Current period label | C9: July 2026
B10: Rule: practices whose name contains 'Head Office' use the HO2 tolerance; all others use the HG tolerance. Edit only the gold cells above.
B12: Monthly steps
B13: 1. Export the six iTrent reports below for the current payroll run.
B14: 2. Check the prior-month Payment Breakdown export for an EXTRA leading 'Reference No' column (see warning below). Delete it if present so both months line up.
B15: 3. Clear old data from each paste tab (keep the header row) and paste the new export starting at the header row shown in 'Expected report layout' below.
B16: 4. Update the Prior/Current period labels above.
B17: 5. Open Summary, Exceptions, Zero Hours and Drilldown - they recalculate automatically.
B18: 6. Work through Exceptions top to bottom; use Drilldown to inspect any payroll number.
B19: 7. Agree totals on the Summary tab to BACS and to the payroll submissions.
B22: Expected report layout
B23: Report | C23: Paste tab | D23: Header row | E23: Data starts | F23: Key columns
B24: NPV Comparison (Net Pay) | C24: NPV Comparison | D24: 14 | E24: 15 | F24: D Payroll No, E Prior Net, F Current Net
B25: Payment Breakdown - current month | C25: Payment Breakdown Current | D25: 14 | E25: 15 | F25: D Practice, K.. Elements, last col Reference No
B26: Payment Breakdown - prior month | C26: Payment Breakdown Prior | D26: 14 | E26: 15 | F26: Same as above once the extra leading column is removed
B27: New Starters | C27: New Starters | D27: 13 | E27: 14 | F27: D Payroll No, K Personal Reference
B28: Leavers | C28: Leavers | D28: 11 | E28: 12 | F28: D Payroll No, K Personal Reference
B29: Structure report | C29: Structure | D29: 12 | E29: 13 | F29: L Position, N Basis, P Payroll Ref (MHR), AI Category
B32: ⚠ WARNING - PRIOR MONTH PAYMENT BREAKDOWN: some iTrent exports carry an extra leading 'Reference No' column that shifts Practice, elements and everything else one column to the right. If Practice does not land in column D and the first pay element does not land in column K on the 'Payment Breakdown Prior' tab, delete the extra leading column before pasting. Getting this wrong silently misaligns the whole comparison.

Sheet _Helpers
A1: PayrollNumber | B1: PriorNet | C1: CurrentNet | D1: Practice | E1: IsZeroHoursOnly | F1: IsMainList | G1: IsStarter | H1: IsLeaver | I1: PersonalRef | J1: IsPaired | K1: ToleranceGroupPct | L1: Diff | M1: DiffPct | N1: OverTolerance | O1: Flagged | P1: Status | Q1: NoPayNoLeaver | R1: IsReviewItem | S1: Priority | T1: BasicSalaryPrior | U1: BasicSalaryCurrent | V1: BasicSalaryPctChange | W1: Basic Salary | X1: Overtime | Y1: Bonus | Z1: Mileage Expenses | AA1: Other Expenses | AB1: SMP | AC1: SSP | AD1: Pension Deduction | AE1: Student Loan | AF1: Attachment of Earnings | AG1: On Call Allowance | AH1: Unsocial Hours Premium | AI1: MaxAbsDiff | AJ1: DriverElement | AK1: DriverDiffValue | AL1: RankKey
A2: =IF('NPV Comparison'!D15="","",'NPV Comparison'!D15) | B2: =IF('NPV Comparison'!E15="","",'NPV Comparison'!E15) | C2: =IF('NPV Comparison'!F15="","",'NPV Comparison'!F15) | D2: =IF($A2="","",IFERROR(INDEX(Structure!$E$13:$E$312,MATCH($A2,Structure!$P$13:$P$312,0)),"")) | E2: =IF($A2="",0,IF(COUNTIF(Structure!$P$13:$P$312,$A2)=0,0,IF(COUNTIFS(Structure!$P$13:$P$312,$A2,Structure!$N$13:$N$312,"<>Zero Hours")=0,1,0))) | F2: =IF($A2="",0,1-E2) | G2: =IF($A2="",0,IF(COUNTIF('New Starters'!$D$14:$D$73,$A2)>0,1,0)) | H2: =IF($A2="",0,IF(COUNTIF('Leavers'!$D$12:$D$71,$A2)>0,1,0)) | I2: =IF($A2="","",IFERROR(INDEX('New Starters'!$K$14:$K$73,MATCH($A2,'New Starters'!$D$14:$D$73,0)),IFERROR(INDEX('Leavers'!$K$12:$K$71,MATCH($A2,'Leavers'!$D$12:$D$71,0)),""))) | J2: =IF(AND(G2=1,I2<>"",COUNTIF('Leavers'!$K$12:$K$71,I2)>0),1,IF(AND(H2=1,I2<>"",COUNTIF('New Starters'!$K$14:$K$73,I2)>0),1,0)) | K2: =IF(ISNUMBER(SEARCH("Head Office",D2)),'Control Sheet'!$C$6,'Control Sheet'!$C$5) | L2: =IF(OR($A2="",AND(B2="",C2="")),"",IF(B2="",C2,IF(C2="",-B2,C2-B2))) | M2: =IFERROR(L2/B2,"") | N2: =IF($A2="",0,IF(OR(B2="",C2="",C2=0,AND(ISNUMBER(M2),ABS(M2)>K2)),1,0)) | O2: =IF(AND(N2=1,ABS(L2)>='Control Sheet'!$C$7,F2=1),1,0) | P2: =IF($A2="","",IF(F2=0,"Zero Hours",IF(J2=1,"Explained: Paired transfer",IF(AND(G2=1,H2=0,J2=0),"Explained: Starter",IF(AND(H2=1,G2=0,J2=0),"Explained: Leaver",IF(O2=1,"Review required","OK")))))) | Q2: =IF(AND(F2=1,OR(C2="",C2=0),H2=0,J2=0),1,0) | R2: =IF(F2=0,0,IF(P2="Review required",1,IF(AND(P2="Explained: Starter",ISNUMBER(C2),C2>=1500),1,0))) | S2: =IF(R2=0,"",IF(Q2=1,"High",IF(AND(P2="Explained: Starter",C2>=1500),"High",IF(ABS(L2)>=2000,"High",IF(ABS(L2)>=500,"Medium","Low"))))) | T2: =SUMIFS('Payment Breakdown Prior'!$S$15:$S$164,'Payment Breakdown Prior'!$AE$15:$AE$164,$A2) | U2: =SUMIFS('Payment Breakdown Current'!$S$15:$S$164,'Payment Breakdown Current'!$AE$15:$AE$164,$A2) | V2: =IFERROR((U2-T2)/T2,"") | W2: =(SUMIFS('Payment Breakdown Current'!$S$15:$S$164,'Payment Breakdown Current'!$AE$15:$AE$164,$A2))-(SUMIFS('Payment Breakdown Prior'!$S$15:$S$164,'Payment Breakdown Prior'!$AE$15:$AE$164,$A2)) | X2: =(SUMIFS('Payment Breakdown Current'!$T$15:$T$164,'Payment Breakdown Current'!$AE$15:$AE$164,$A2))-(SUMIFS('Payment Breakdown Prior'!$T$15:$T$164,'Payment Breakdown Prior'!$AE$15:$AE$164,$A2)) | Y2: =(SUMIFS('Payment Breakdown Current'!$U$15:$U$164,'Payment Breakdown Current'!$AE$15:$AE$164,$A2))-(SUMIFS('Payment Breakdown Prior'!$U$15:$U$164,'Payment Breakdown Prior'!$AE$15:$AE$164,$A2)) | Z2: =(SUMIFS('Payment Breakdown Current'!$V$15:$V$164,'Payment Breakdown Current'!$AE$15:$AE$164,$A2))-(SUMIFS('Payment Breakdown Prior'!$V$15:$V$164,'Payment Breakdown Prior'!$AE$15:$AE$164,$A2)) | AA2: =(SUMIFS('Payment Breakdown Current'!$W$15:$W$164,'Payment Breakdown Current'!$AE$15:$AE$164,$A2))-(SUMIFS('Payment Breakdown Prior'!$W$15:$W$164,'Payment Breakdown Prior'!$AE$15:$AE$164,$A2)) | AB2: =(SUMIFS('Payment Breakdown Current'!$X$15:$X$164,'Payment Breakdown Current'!$AE$15:$AE$164,$A2))-(SUMIFS('Payment Breakdown Prior'!$X$15:$X$164,'Payment Breakdown Prior'!$AE$15:$AE$164,$A2)) | AC2: =(SUMIFS('Payment Breakdown Current'!$Y$15:$Y$164,'Payment Breakdown Current'!$AE$15:$AE$164,$A2))-(SUMIFS('Payment Breakdown Prior'!$Y$15:$Y$164,'Payment Breakdown Prior'!$AE$15:$AE$164,$A2)) | AD2: =(SUMIFS('Payment Breakdown Current'!$Z$15:$Z$164,'Payment Breakdown Current'!$AE$15:$AE$164,$A2))-(SUMIFS('Payment Breakdown Prior'!$Z$15:$Z$164,'Payment Breakdown Prior'!$AE$15:$AE$164,$A2)) | AE2: =(SUMIFS('Payment Breakdown Current'!$AA$15:$AA$164,'Payment Breakdown Current'!$AE$15:$AE$164,$A2))-(SUMIFS('Payment Breakdown Prior'!$AA$15:$AA$164,'Payment Breakdown Prior'!$AE$15:$AE$164,$A2)) | AF2: =(SUMIFS('Payment Breakdown Current'!$AB$15:$AB$164,'Payment Breakdown Current'!$AE$15:$AE$164,$A2))-(SUMIFS('Payment Breakdown Prior'!$AB$15:$AB$164,'Payment Breakdown Prior'!$AE$15:$AE$164,$A2)) | AG2: =(SUMIFS('Payment Breakdown Current'!$AC$15:$AC$164,'Payment Breakdown Current'!$AE$15:$AE$164,$A2))-(SUMIFS('Payment Breakdown Prior'!$AC$15:$AC$164,'Payment Breakdown Prior'!$AE$15:$AE$164,$A2)) | AH2: =(SUMIFS('Payment Breakdown Current'!$AD$15:$AD$164,'Payment Breakdown Current'!$AE$15:$AE$164,$A2))-(SUMIFS('Payment Breakdown Prior'!$AD$15:$AD$164,'Payment Breakdown Prior'!$AE$15:$AE$164,$A2)) | AI2: {=MAX(ABS(W2:AH2))} | AJ2: {=IF(AI2<0.005,"",IFERROR(INDEX($W$1:$AH$1,MATCH(AI2,ABS(W2:AH2),0)),""))} | AK2: {=IF(AI2<0.005,"",IFERROR(INDEX(W2:AH2,MATCH(AI2,ABS(W2:AH2),0)),""))} | AL2: =IF(R2=1,ABS(L2)-ROW()/100000000,"")
A3: =IF('NPV Comparison'!D16="","",'NPV Comparison'!D16) | B3: =IF('NPV Comparison'!E16="","",'NPV Comparison'!E16) | C3: =IF('NPV Comparison'!F16="","",'NPV Comparison'!F16) | D3: =IF($A3="","",IFERROR(INDEX(Structure!$E$13:$E$312,MATCH($A3,Structure!$P$13:$P$312,0)),"")) | E3: =IF($A3="",0,IF(COUNTIF(Structure!$P$13:$P$312,$A3)=0,0,IF(COUNTIFS(Structure!$P$13:$P$312,$A3,Structure!$N$13:$N$312,"<>Zero Hours")=0,1,0))) | F3: =IF($A3="",0,1-E3) | G3: =IF($A3="",0,IF(COUNTIF('New Starters'!$D$14:$D$73,$A3)>0,1,0)) | H3: =IF($A3="",0,IF(COUNTIF('Leavers'!$D$12:$D$71,$A3)>0,1,0)) | I3: =IF($A3="","",IFERROR(INDEX('New Starters'!$K$14:$K$73,MATCH($A3,'New Starters'!$D$14:$D$73,0)),IFERROR(INDEX('Leavers'!$K$12:$K$71,MATCH($A3,'Leavers'!$D$12:$D$71,0)),""))) | J3: =IF(AND(G3=1,I3<>"",COUNTIF('Leavers'!$K$12:$K$71,I3)>0),1,IF(AND(H3=1,I3<>"",COUNTIF('New Starters'!$K$14:$K$73,I3)>0),1,0)) | K3: =IF(ISNUMBER(SEARCH("Head Office",D3)),'Control Sheet'!$C$6,'Control Sheet'!$C$5) | L3: =IF(OR($A3="",AND(B3="",C3="")),"",IF(B3="",C3,IF(C3="",-B3,C3-B3))) | M3: =IFERROR(L3/B3,"") | N3: =IF($A3="",0,IF(OR(B3="",C3="",C3=0,AND(ISNUMBER(M3),ABS(M3)>K3)),1,0)) | O3: =IF(AND(N3=1,ABS(L3)>='Control Sheet'!$C$7,F3=1),1,0) | P3: =IF($A3="","",IF(F3=0,"Zero Hours",IF(J3=1,"Explained: Paired transfer",IF(AND(G3=1,H3=0,J3=0),"Explained: Starter",IF(AND(H3=1,G3=0,J3=0),"Explained: Leaver",IF(O3=1,"Review required","OK")))))) | Q3: =IF(AND(F3=1,OR(C3="",C3=0),H3=0,J3=0),1,0) | R3: =IF(F3=0,0,IF(P3="Review required",1,IF(AND(P3="Explained: Starter",ISNUMBER(C3),C3>=1500),1,0))) | S3: =IF(R3=0,"",IF(Q3=1,"High",IF(AND(P3="Explained: Starter",C3>=1500),"High",IF(ABS(L3)>=2000,"High",IF(ABS(L3)>=500,"Medium","Low"))))) | T3: =SUMIFS('Payment Breakdown Prior'!$S$15:$S$164,'Payment Breakdown Prior'!$AE$15:$AE$164,$A3) | U3: =SUMIFS('Payment Breakdown Current'!$S$15:$S$164,'Payment Breakdown Current'!$AE$15:$AE$164,$A3) | V3: =IFERROR((U3-T3)/T3,"") | W3: =(SUMIFS('Payment Breakdown Current'!$S$15:$S$164,'Payment Breakdown Current'!$AE$15:$AE$164,$A3))-(SUMIFS('Payment Breakdown Prior'!$S$15:$S$164,'Payment Breakdown Prior'!$AE$15:$AE$164,$A3)) | X3: =(SUMIFS('Payment Breakdown Current'!$T$15:$T$164,'Payment Breakdown Current'!$AE$15:$AE$164,$A3))-(SUMIFS('Payment Breakdown Prior'!$T$15:$T$164,'Payment Breakdown Prior'!$AE$15:$AE$164,$A3)) | Y3: =(SUMIFS('Payment Breakdown Current'!$U$15:$U$164,'Payment Breakdown Current'!$AE$15:$AE$164,$A3))-(SUMIFS('Payment Breakdown Prior'!$U$15:$U$164,'Payment Breakdown Prior'!$AE$15:$AE$164,$A3)) | Z3: =(SUMIFS('Payment Breakdown Current'!$V$15:$V$164,'Payment Breakdown Current'!$AE$15:$AE$164,$A3))-(SUMIFS('Payment Breakdown Prior'!$V$15:$V$164,'Payment Breakdown Prior'!$AE$15:$AE$164,$A3)) | AA3: =(SUMIFS('Payment Breakdown Current'!$W$15:$W$164,'Payment Breakdown Current'!$AE$15:$AE$164,$A3))-(SUMIFS('Payment Breakdown Prior'!$W$15:$W$164,'Payment Breakdown Prior'!$AE$15:$AE$164,$A3)) | AB3: =(SUMIFS('Payment Breakdown Current'!$X$15:$X$164,'Payment Breakdown Current'!$AE$15:$AE$164,$A3))-(SUMIFS('Payment Breakdown Prior'!$X$15:$X$164,'Payment Breakdown Prior'!$AE$15:$AE$164,$A3)) | AC3: =(SUMIFS('Payment Breakdown Current'!$Y$15:$Y$164,'Payment Breakdown Current'!$AE$15:$AE$164,$A3))-(SUMIFS('Payment Breakdown Prior'!$Y$15:$Y$164,'Payment Breakdown Prior'!$AE$15:$AE$164,$A3)) | AD3: =(SUMIFS('Payment Breakdown Current'!$Z$15:$Z$164,'Payment Breakdown Current'!$AE$15:$AE$164,$A3))-(SUMIFS('Payment Breakdown Prior'!$Z$15:$Z$164,'Payment Breakdown Prior'!$AE$15:$AE$164,$A3)) | AE3: =(SUMIFS('Payment Breakdown Current'!$AA$15:$AA$164,'Payment Breakdown Current'!$AE$15:$AE$164,$A3))-(SUMIFS('Payment Breakdown Prior'!$AA$15:$AA$164,'Payment Breakdown Prior'!$AE$15:$AE$164,$A3)) | AF3: =(SUMIFS('Payment Breakdown Current'!$AB$15:$AB$164,'Payment Breakdown Current'!$AE$15:$AE$164,$A3))-(SUMIFS('Payment Breakdown Prior'!$AB$15:$AB$164,'Payment Breakdown Prior'!$AE$15:$AE$164,$A3)) | AG3: =(SUMIFS('Payment Breakdown Current'!$AC$15:$AC$164,'Payment Breakdown Current'!$AE$15:$AE$164,$A3))-(SUMIFS('Payment Breakdown Prior'!$AC$15:$AC$164,'Payment Breakdown Prior'!$AE$15:$AE$164,$A3)) | AH3: =(SUMIFS('Payment Breakdown Current'!$AD$15:$AD$164,'Payment Breakdown Current'!$AE$15:$AE$164,$A3))-(SUMIFS('Payment Breakdown Prior'!$AD$15:$AD$164,'Payment Breakdown Prior'!$AE$15:$AE$164,$A3)) | AI3: {=MAX(ABS(W3:AH3))} | AJ3: {=IF(AI3<0.005,"",IFERROR(INDEX($W$1:$AH$1,MATCH(AI3,ABS(W3:AH3),0)),""))} | AK3: {=IF(AI3<0.005,"",IFERROR(INDEX(W3:AH3,MATCH(AI3,ABS(W3:AH3),0)),""))} | AL3: =IF(R3=1,ABS(L3)-ROW()/100000000,"")
A4: =IF('NPV Comparison'!D17="","",'NPV Comparison'!D17) | B4: =IF('NPV Comparison'!E17="","",'NPV Comparison'!E17) | C4: =IF('NPV Comparison'!F17="","",'NPV Comparison'!F17) | D4: =IF($A4="","",IFERROR(INDEX(Structure!$E$13:$E$312,MATCH($A4,Structure!$P$13:$P$312,0)),"")) | E4: =IF($A4="",0,IF(COUNTIF(Structure!$P$13:$P$312,$A4)=0,0,IF(COUNTIFS(Structure!$P$13:$P$312,$A4,Structure!$N$13:$N$312,"<>Zero Hours")=0,1,0))) | F4: =IF($A4="",0,1-E4) | G4: =IF($A4="",0,IF(COUNTIF('New Starters'!$D$14:$D$73,$A4)>0,1,0)) | H4: =IF($A4="",0,IF(COUNTIF('Leavers'!$D$12:$D$71,$A4)>0,1,0)) | I4: =IF($A4="","",IFERROR(INDEX('New Starters'!$K$14:$K$73,MATCH($A4,'New Starters'!$D$14:$D$73,0)),IFERROR(INDEX('Leavers'!$K$12:$K$71,MATCH($A4,'Leavers'!$D$12:$D$71,0)),""))) | J4: =IF(AND(G4=1,I4<>"",COUNTIF('Leavers'!$K$12:$K$71,I4)>0),1,IF(AND(H4=1,I4<>"",COUNTIF('New Starters'!$K$14:$K$73,I4)>0),1,0)) | K4: =IF(ISNUMBER(SEARCH("Head Office",D4)),'Control Sheet'!$C$6,'Control Sheet'!$C$5) | L4: =IF(OR($A4="",AND(B4="",C4="")),"",IF(B4="",C4,IF(C4="",-B4,C4-B4))) | M4: =IFERROR(L4/B4,"") | N4: =IF($A4="",0,IF(OR(B4="",C4="",C4=0,AND(ISNUMBER(M4),ABS(M4)>K4)),1,0)) | O4: =IF(AND(N4=1,ABS(L4)>='Control Sheet'!$C$7,F4=1),1,0) | P4: =IF($A4="","",IF(F4=0,"Zero Hours",IF(J4=1,"Explained: Paired transfer",IF(AND(G4=1,H4=0,J4=0),"Explained: Starter",IF(AND(H4=1,G4=0,J4=0),"Explained: Leaver",IF(O4=1,"Review required","OK")))))) | Q4: =IF(AND(F4=1,OR(C4="",C4=0),H4=0,J4=0),1,0) | R4: =IF(F4=0,0,IF(P4="Review required",1,IF(AND(P4="Explained: Starter",ISNUMBER(C4),C4>=1500),1,0))) | S4: =IF(R4=0,"",IF(Q4=1,"High",IF(AND(P4="Explained: Starter",C4>=1500),"High",IF(ABS(L4)>=2000,"High",IF(ABS(L4)>=500,"Medium","Low"))))) | T4: =SUMIFS('Payment Breakdown Prior'!$S$15:$S$164,'Payment Breakdown Prior'!$AE$15:$AE$164,$A4) | U4: =SUMIFS('Payment Breakdown Current'!$S$15:$S$164,'Payment Breakdown Current'!$AE$15:$AE$164,$A4) | V4: =IFERROR((U4-T4)/T4,"") | W4: =(SUMIFS('Payment Breakdown Current'!$S$15:$S$164,'Payment Breakdown Current'!$AE$15:$AE$164,$A4))-(SUMIFS('Payment Breakdown Prior'!$S$15:$S$164,'Payment Breakdown Prior'!$AE$15:$AE$164,$A4)) | X4: =(SUMIFS('Payment Breakdown Current'!$T$15:$T$164,'Payment Breakdown Current'!$AE$15:$AE$164,$A4))-(SUMIFS('Payment Breakdown Prior'!$T$15:$T$164,'Payment Breakdown Prior'!$AE$15:$AE$164,$A4)) | Y4: =(SUMIFS('Payment Breakdown Current'!$U$15:$U$164,'Payment Breakdown Current'!$AE$15:$AE$164,$A4))-(SUMIFS('Payment Breakdown Prior'!$U$15:$U$164,'Payment Breakdown Prior'!$AE$15:$AE$164,$A4)) | Z4: =(SUMIFS('Payment Breakdown Current'!$V$15:$V$164,'Payment Breakdown Current'!$AE$15:$AE$164,$A4))-(SUMIFS('Payment Breakdown Prior'!$V$15:$V$164,'Payment Breakdown Prior'!$AE$15:$AE$164,$A4)) | AA4: =(SUMIFS('Payment Breakdown Current'!$W$15:$W$164,'Payment Breakdown Current'!$AE$15:$AE$164,$A4))-(SUMIFS('Payment Breakdown Prior'!$W$15:$W$164,'Payment Breakdown Prior'!$AE$15:$AE$164,$A4)) | AB4: =(SUMIFS('Payment Breakdown Current'!$X$15:$X$164,'Payment Breakdown Current'!$AE$15:$AE$164,$A4))-(SUMIFS('Payment Breakdown Prior'!$X$15:$X$164,'Payment Breakdown Prior'!$AE$15:$AE$164,$A4)) | AC4: =(SUMIFS('Payment Breakdown Current'!$Y$15:$Y$164,'Payment Breakdown Current'!$AE$15:$AE$164,$A4))-(SUMIFS('Payment Breakdown Prior'!$Y$15:$Y$164,'Payment Breakdown Prior'!$AE$15:$AE$164,$A4)) | AD4: =(SUMIFS('Payment Breakdown Current'!$Z$15:$Z$164,'Payment Breakdown Current'!$AE$15:$AE$164,$A4))-(SUMIFS('Payment Breakdown Prior'!$Z$15:$Z$164,'Payment Breakdown Prior'!$AE$15:$AE$164,$A4)) | AE4: =(SUMIFS('Payment Breakdown Current'!$AA$15:$AA$164,'Payment Breakdown Current'!$AE$15:$AE$164,$A4))-(SUMIFS('Payment Breakdown Prior'!$AA$15:$AA$164,'Payment Breakdown Prior'!$AE$15:$AE$164,$A4)) | AF4: =(SUMIFS('Payment Breakdown Current'!$AB$15:$AB$164,'Payment Breakdown Current'!$AE$15:$AE$164,$A4))-(SUMIFS('Payment Breakdown Prior'!$AB$15:$AB$164,'Payment Breakdown Prior'!$AE$15:$AE$164,$A4)) | AG4: =(SUMIFS('Payment Breakdown Current'!$AC$15:$AC$164,'Payment Breakdown Current'!$AE$15:$AE$164,$A4))-(SUMIFS('Payment Breakdown Prior'!$AC$15:$AC$164,'Payment Breakdown Prior'!$AE$15:$AE$164,$A4)) | AH4: =(SUMIFS('Payment Breakdown Current'!$AD$15:$AD$164,'Payment Breakdown Current'!$AE$15:$AE$164,$A4))-(SUMIFS('Payment Breakdown Prior'!$AD$15:$AD$164,'Payment Breakdown Prior'!$AE$15:$AE$164,$A4)) | AI4: {=MAX(ABS(W4:AH4))} | AJ4: {=IF(AI4<0.005,"",IFERROR(INDEX($W$1:$AH$1,MATCH(AI4,ABS(W4:AH4),0)),""))} | AK4: {=IF(AI4<0.005,"",IFERROR(INDEX(W4:AH4,MATCH(AI4,ABS(W4:AH4),0)),""))} | AL4: =IF(R4=1,ABS(L4)-ROW()/100000000,"")
A5: =IF('NPV Comparison'!D18="","",'NPV Comparison'!D18) | B5: =IF('NPV Comparison'!E18="","",'NPV Comparison'!E18) | C5: =IF('NPV Comparison'!F18="","",'NPV Comparison'!F18) | D5: =IF($A5="","",IFERROR(INDEX(Structure!$E$13:$E$312,MATCH($A5,Structure!$P$13:$P$312,0)),"")) | E5: =IF($A5="",0,IF(COUNTIF(Structure!$P$13:$P$312,$A5)=0,0,IF(COUNTIFS(Structure!$P$13:$P$312,$A5,Structure!$N$13:$N$312,"<>Zero Hours")=0,1,0))) | F5: =IF($A5="",0,1-E5) | G5: =IF($A5="",0,IF(COUNTIF('New Starters'!$D$14:$D$73,$A5)>0,1,0)) | H5: =IF($A5="",0,IF(COUNTIF('Leavers'!$D$12:$D$71,$A5)>0,1,0)) | I5: =IF($A5="","",IFERROR(INDEX('New Starters'!$K$14:$K$73,MATCH($A5,'New Starters'!$D$14:$D$73,0)),IFERROR(INDEX('Leavers'!$K$12:$K$71,MATCH($A5,'Leavers'!$D$12:$D$71,0)),""))) | J5: =IF(AND(G5=1,I5<>"",COUNTIF('Leavers'!$K$12:$K$71,I5)>0),1,IF(AND(H5=1,I5<>"",COUNTIF('New Starters'!$K$14:$K$73,I5)>0),1,0)) | K5: =IF(ISNUMBER(SEARCH("Head Office",D5)),'Control Sheet'!$C$6,'Control Sheet'!$C$5) | L5: =IF(OR($A5="",AND(B5="",C5="")),"",IF(B5="",C5,IF(C5="",-B5,C5-B5))) | M5: =IFERROR(L5/B5,"") | N5: =IF($A5="",0,IF(OR(B5="",C5="",C5=0,AND(ISNUMBER(M5),ABS(M5)>K5)),1,0)) | O5: =IF(AND(N5=1,ABS(L5)>='Control Sheet'!$C$7,F5=1),1,0) | P5: =IF($A5="","",IF(F5=0,"Zero Hours",IF(J5=1,"Explained: Paired transfer",IF(AND(G5=1,H5=0,J5=0),"Explained: Starter",IF(AND(H5=1,G5=0,J5=0),"Explained: Leaver",IF(O5=1,"Review required","OK")))))) | Q5: =IF(AND(F5=1,OR(C5="",C5=0),H5=0,J5=0),1,0) | R5: =IF(F5=0,0,IF(P5="Review required",1,IF(AND(P5="Explained: Starter",ISNUMBER(C5),C5>=1500),1,0))) | S5: =IF(R5=0,"",IF(Q5=1,"High",IF(AND(P5="Explained: Starter",C5>=1500),"High",IF(ABS(L5)>=2000,"High",IF(ABS(L5)>=500,"Medium","Low"))))) | T5: =SUMIFS('Payment Breakdown Prior'!$S$15:$S$164,'Payment Breakdown Prior'!$AE$15:$AE$164,$A5) | U5: =SUMIFS('Payment Breakdown Current'!$S$15:$S$164,'Payment Breakdown Current'!$AE$15:$AE$164,$A5) | V5: =IFERROR((U5-T5)/T5,"") | W5: =(SUMIFS('Payment Breakdown Current'!$S$15:$S$164,'Payment Breakdown Current'!$AE$15:$AE$164,$A5))-(SUMIFS('Payment Breakdown Prior'!$S$15:$S$164,'Payment Breakdown Prior'!$AE$15:$AE$164,$A5)) | X5: =(SUMIFS('Payment Breakdown Current'!$T$15:$T$164,'Payment Breakdown Current'!$AE$15:$AE$164,$A5))-(SUMIFS('Payment Breakdown Prior'!$T$15:$T$164,'Payment Breakdown Prior'!$AE$15:$AE$164,$A5)) | Y5: =(SUMIFS('Payment Breakdown Current'!$U$15:$U$164,'Payment Breakdown Current'!$AE$15:$AE$164,$A5))-(SUMIFS('Payment Breakdown Prior'!$U$15:$U$164,'Payment Breakdown Prior'!$AE$15:$AE$164,$A5)) | Z5: =(SUMIFS('Payment Breakdown Current'!$V$15:$V$164,'Payment Breakdown Current'!$AE$15:$AE$164,$A5))-(SUMIFS('Payment Breakdown Prior'!$V$15:$V$164,'Payment Breakdown Prior'!$AE$15:$AE$164,$A5)) | AA5: =(SUMIFS('Payment Breakdown Current'!$W$15:$W$164,'Payment Breakdown Current'!$AE$15:$AE$164,$A5))-(SUMIFS('Payment Breakdown Prior'!$W$15:$W$164,'Payment Breakdown Prior'!$AE$15:$AE$164,$A5)) | AB5: =(SUMIFS('Payment Breakdown Current'!$X$15:$X$164,'Payment Breakdown Current'!$AE$15:$AE$164,$A5))-(SUMIFS('Payment Breakdown Prior'!$X$15:$X$164,'Payment Breakdown Prior'!$AE$15:$AE$164,$A5)) | AC5: =(SUMIFS('Payment Breakdown Current'!$Y$15:$Y$164,'Payment Breakdown Current'!$AE$15:$AE$164,$A5))-(SUMIFS('Payment Breakdown Prior'!$Y$15:$Y$164,'Payment Breakdown Prior'!$AE$15:$AE$164,$A5)) | AD5: =(SUMIFS('Payment Breakdown Current'!$Z$15:$Z$164,'Payment Breakdown Current'!$AE$15:$AE$164,$A5))-(SUMIFS('Payment Breakdown Prior'!$Z$15:$Z$164,'Payment Breakdown Prior'!$AE$15:$AE$164,$A5)) | AE5: =(SUMIFS('Payment Breakdown Current'!$AA$15:$AA$164,'Payment Breakdown Current'!$AE$15:$AE$164,$A5))-(SUMIFS('Payment Breakdown Prior'!$AA$15:$AA$164,'Payment Breakdown Prior'!$AE$15:$AE$164,$A5)) | AF5: =(SUMIFS('Payment Breakdown Current'!$AB$15:$AB$164,'Payment Breakdown Current'!$AE$15:$AE$164,$A5))-(SUMIFS('Payment Breakdown Prior'!$AB$15:$AB$164,'Payment Breakdown Prior'!$AE$15:$AE$164,$A5)) | AG5: =(SUMIFS('Payment Breakdown Current'!$AC$15:$AC$164,'Payment Breakdown Current'!$AE$15:$AE$164,$A5))-(SUMIFS('Payment Breakdown Prior'!$AC$15:$AC$164,'Payment Breakdown Prior'!$AE$15:$AE$164,$A5)) | AH5: =(SUMIFS('Payment Breakdown Current'!$AD$15:$AD$164,'Payment Breakdown Current'!$AE$15:$AE$164,$A5))-(SUMIFS('Payment Breakdown Prior'!$AD$15:$AD$164,'Payment Breakdown Prior'!$AE$15:$AE$164,$A5)) | AI5: {=MAX(ABS(W5:AH5))} | AJ5: {=IF(AI5<0.005,"",IFERROR(INDEX($W$1:$AH$1,MATCH(AI5,ABS(W5:AH5),0)),""))} | AK5: {=IF(AI5<0.005,"",IFERROR(INDEX(W5:AH5,MATCH(AI5,ABS(W5:AH5),0)),""))} | AL5: =IF(R5=1,ABS(L5)-ROW()/100000000,"")
A6: =IF('NPV Comparison'!D19="","",'NPV Comparison'!D19) | B6: =IF('NPV Comparison'!E19="","",'NPV Comparison'!E19) | C6: =IF('NPV Comparison'!F19="","",'NPV Comparison'!F19) | D6: =IF($A6="","",IFERROR(INDEX(Structure!$E$13:$E$312,MATCH($A6,Structure!$P$13:$P$312,0)),"")) | E6: =IF($A6="",0,IF(COUNTIF(Structure!$P$13:$P$312,$A6)=0,0,IF(COUNTIFS(Structure!$P$13:$P$312,$A6,Structure!$N$13:$N$312,"<>Zero Hours")=0,1,0))) | F6: =IF($A6="",0,1-E6) | G6: =IF($A6="",0,IF(COUNTIF('New Starters'!$D$14:$D$73,$A6)>0,1,0)) | H6: =IF($A6="",0,IF(COUNTIF('Leavers'!$D$12:$D$71,$A6)>0,1,0)) | I6: =IF($A6="","",IFERROR(INDEX('New Starters'!$K$14:$K$73,MATCH($A6,'New Starters'!$D$14:$D$73,0)),IFERROR(INDEX('Leavers'!$K$12:$K$71,MATCH($A6,'Leavers'!$D$12:$D$71,0)),""))) | J6: =IF(AND(G6=1,I6<>"",COUNTIF('Leavers'!$K$12:$K$71,I6)>0),1,IF(AND(H6=1,I6<>"",COUNTIF('New Starters'!$K$14:$K$73,I6)>0),1,0)) | K6: =IF(ISNUMBER(SEARCH("Head Office",D6)),'Control Sheet'!$C$6,'Control Sheet'!$C$5) | L6: =IF(OR($A6="",AND(B6="",C6="")),"",IF(B6="",C6,IF(C6="",-B6,C6-B6))) | M6: =IFERROR(L6/B6,"") | N6: =IF($A6="",0,IF(OR(B6="",C6="",C6=0,AND(ISNUMBER(M6),ABS(M6)>K6)),1,0)) | O6: =IF(AND(N6=1,ABS(L6)>='Control Sheet'!$C$7,F6=1),1,0) | P6: =IF($A6="","",IF(F6=0,"Zero Hours",IF(J6=1,"Explained: Paired transfer",IF(AND(G6=1,H6=0,J6=0),"Explained: Starter",IF(AND(H6=1,G6=0,J6=0),"Explained: Leaver",IF(O6=1,"Review required","OK")))))) | Q6: =IF(AND(F6=1,OR(C6="",C6=0),H6=0,J6=0),1,0) | R6: =IF(F6=0,0,IF(P6="Review required",1,IF(AND(P6="Explained: Starter",ISNUMBER(C6),C6>=1500),1,0))) | S6: =IF(R6=0,"",IF(Q6=1,"High",IF(AND(P6="Explained: Starter",C6>=1500),"High",IF(ABS(L6)>=2000,"High",IF(ABS(L6)>=500,"Medium","Low"))))) | T6: =SUMIFS('Payment Breakdown Prior'!$S$15:$S$164,'Payment Breakdown Prior'!$AE$15:$AE$164,$A6) | U6: =SUMIFS('Payment Breakdown Current'!$S$15:$S$164,'Payment Breakdown Current'!$AE$15:$AE$164,$A6) | V6: =IFERROR((U6-T6)/T6,"") | W6: =(SUMIFS('Payment Breakdown Current'!$S$15:$S$164,'Payment Breakdown Current'!$AE$15:$AE$164,$A6))-(SUMIFS('Payment Breakdown Prior'!$S$15:$S$164,'Payment Breakdown Prior'!$AE$15:$AE$164,$A6)) | X6: =(SUMIFS('Payment Breakdown Current'!$T$15:$T$164,'Payment Breakdown Current'!$AE$15:$AE$164,$A6))-(SUMIFS('Payment Breakdown Prior'!$T$15:$T$164,'Payment Breakdown Prior'!$AE$15:$AE$164,$A6)) | Y6: =(SUMIFS('Payment Breakdown Current'!$U$15:$U$164,'Payment Breakdown Current'!$AE$15:$AE$164,$A6))-(SUMIFS('Payment Breakdown Prior'!$U$15:$U$164,'Payment Breakdown Prior'!$AE$15:$AE$164,$A6)) | Z6: =(SUMIFS('Payment Breakdown Current'!$V$15:$V$164,'Payment Breakdown Current'!$AE$15:$AE$164,$A6))-(SUMIFS('Payment Breakdown Prior'!$V$15:$V$164,'Payment Breakdown Prior'!$AE$15:$AE$164,$A6)) | AA6: =(SUMIFS('Payment Breakdown Current'!$W$15:$W$164,'Payment Breakdown Current'!$AE$15:$AE$164,$A6))-(SUMIFS('Payment Breakdown Prior'!$W$15:$W$164,'Payment Breakdown Prior'!$AE$15:$AE$164,$A6)) | AB6: =(SUMIFS('Payment Breakdown Current'!$X$15:$X$164,'Payment Breakdown Current'!$AE$15:$AE$164,$A6))-(SUMIFS('Payment Breakdown Prior'!$X$15:$X$164,'Payment Breakdown Prior'!$AE$15:$AE$164,$A6)) | AC6: =(SUMIFS('Payment Breakdown Current'!$Y$15:$Y$164,'Payment Breakdown Current'!$AE$15:$AE$164,$A6))-(SUMIFS('Payment Breakdown Prior'!$Y$15:$Y$164,'Payment Breakdown Prior'!$AE$15:$AE$164,$A6)) | AD6: =(SUMIFS('Payment Breakdown Current'!$Z$15:$Z$164,'Payment Breakdown Current'!$AE$15:$AE$164,$A6))-(SUMIFS('Payment Breakdown Prior'!$Z$15:$Z$164,'Payment Breakdown Prior'!$AE$15:$AE$164,$A6)) | AE6: =(SUMIFS('Payment Breakdown Current'!$AA$15:$AA$164,'Payment Breakdown Current'!$AE$15:$AE$164,$A6))-(SUMIFS('Payment Breakdown Prior'!$AA$15:$AA$164,'Payment Breakdown Prior'!$AE$15:$AE$164,$A6)) | AF6: =(SUMIFS('Payment Breakdown Current'!$AB$15:$AB$164,'Payment Breakdown Current'!$AE$15:$AE$164,$A6))-(SUMIFS('Payment Breakdown Prior'!$AB$15:$AB$164,'Payment Breakdown Prior'!$AE$15:$AE$164,$A6)) | AG6: =(SUMIFS('Payment Breakdown Current'!$AC$15:$AC$164,'Payment Breakdown Current'!$AE$15:$AE$164,$A6))-(SUMIFS('Payment Breakdown Prior'!$AC$15:$AC$164,'Payment Breakdown Prior'!$AE$15:$AE$164,$A6)) | AH6: =(SUMIFS('Payment Breakdown Current'!$AD$15:$AD$164,'Payment Breakdown Current'!$AE$15:$AE$164,$A6))-(SUMIFS('Payment Breakdown Prior'!$AD$15:$AD$164,'Payment Breakdown Prior'!$AE$15:$AE$164,$A6)) | AI6: {=MAX(ABS(W6:AH6))} | AJ6: {=IF(AI6<0.005,"",IFERROR(INDEX($W$1:$AH$1,MATCH(AI6,ABS(W6:AH6),0)),""))} | AK6: {=IF(AI6<0.005,"",IFERROR(INDEX(W6:AH6,MATCH(AI6,ABS(W6:AH6),0)),""))} | AL6: =IF(R6=1,ABS(L6)-ROW()/100000000,"")
A7: =IF('NPV Comparison'!D20="","",'NPV Comparison'!D20) | B7: =IF('NPV Comparison'!E20="","",'NPV Comparison'!E20) | C7: =IF('NPV Comparison'!F20="","",'NPV Comparison'!F20) | D7: =IF($A7="","",IFERROR(INDEX(Structure!$E$13:$E$312,MATCH($A7,Structure!$P$13:$P$312,0)),"")) | E7: =IF($A7="",0,IF(COUNTIF(Structure!$P$13:$P$312,$A7)=0,0,IF(COUNTIFS(Structure!$P$13:$P$312,$A7,Structure!$N$13:$N$312,"<>Zero Hours")=0,1,0))) | F7: =IF($A7="",0,1-E7) | G7: =IF($A7="",0,IF(COUNTIF('New Starters'!$D$14:$D$73,$A7)>0,1,0)) | H7: =IF($A7="",0,IF(COUNTIF('Leavers'!$D$12:$D$71,$A7)>0,1,0)) | I7: =IF($A7="","",IFERROR(INDEX('New Starters'!$K$14:$K$73,MATCH($A7,'New Starters'!$D$14:$D$73,0)),IFERROR(INDEX('Leavers'!$K$12:$K$71,MATCH($A7,'Leavers'!$D$12:$D$71,0)),""))) | J7: =IF(AND(G7=1,I7<>"",COUNTIF('Leavers'!$K$12:$K$71,I7)>0),1,IF(AND(H7=1,I7<>"",COUNTIF('New Starters'!$K$14:$K$73,I7)>0),1,0)) | K7: =IF(ISNUMBER(SEARCH("Head Office",D7)),'Control Sheet'!$C$6,'Control Sheet'!$C$5) | L7: =IF(OR($A7="",AND(B7="",C7="")),"",IF(B7="",C7,IF(C7="",-B7,C7-B7))) | M7: =IFERROR(L7/B7,"") | N7: =IF($A7="",0,IF(OR(B7="",C7="",C7=0,AND(ISNUMBER(M7),ABS(M7)>K7)),1,0)) | O7: =IF(AND(N7=1,ABS(L7)>='Control Sheet'!$C$7,F7=1),1,0) | P7: =IF($A7="","",IF(F7=0,"Zero Hours",IF(J7=1,"Explained: Paired transfer",IF(AND(G7=1,H7=0,J7=0),"Explained: Starter",IF(AND(H7=1,G7=0,J7=0),"Explained: Leaver",IF(O7=1,"Review required","OK")))))) | Q7: =IF(AND(F7=1,OR(C7="",C7=0),H7=0,J7=0),1,0) | R7: =IF(F7=0,0,IF(P7="Review required",1,IF(AND(P7="Explained: Starter",ISNUMBER(C7),C7>=1500),1,0))) | S7: =IF(R7=0,"",IF(Q7=1,"High",IF(AND(P7="Explained: Starter",C7>=1500),"High",IF(ABS(L7)>=2000,"High",IF(ABS(L7)>=500,"Medium","Low"))))) | T7: =SUMIFS('Payment Breakdown Prior'!$S$15:$S$164,'Payment Breakdown Prior'!$AE$15:$AE$164,$A7) | U7: =SUMIFS('Payment Breakdown Current'!$S$15:$S$164,'Payment Breakdown Current'!$AE$15:$AE$164,$A7) | V7: =IFERROR((U7-T7)/T7,"") | W7: =(SUMIFS('Payment Breakdown Current'!$S$15:$S$164,'Payment Breakdown Current'!$AE$15:$AE$164,$A7))-(SUMIFS('Payment Breakdown Prior'!$S$15:$S$164,'Payment Breakdown Prior'!$AE$15:$AE$164,$A7)) | X7: =(SUMIFS('Payment Breakdown Current'!$T$15:$T$164,'Payment Breakdown Current'!$AE$15:$AE$164,$A7))-(SUMIFS('Payment Breakdown Prior'!$T$15:$T$164,'Payment Breakdown Prior'!$AE$15:$AE$164,$A7)) | Y7: =(SUMIFS('Payment Breakdown Current'!$U$15:$U$164,'Payment Breakdown Current'!$AE$15:$AE$164,$A7))-(SUMIFS('Payment Breakdown Prior'!$U$15:$U$164,'Payment Breakdown Prior'!$AE$15:$AE$164,$A7)) | Z7: =(SUMIFS('Payment Breakdown Current'!$V$15:$V$164,'Payment Breakdown Current'!$AE$15:$AE$164,$A7))-(SUMIFS('Payment Breakdown Prior'!$V$15:$V$164,'Payment Breakdown Prior'!$AE$15:$AE$164,$A7)) | AA7: =(SUMIFS('Payment Breakdown Current'!$W$15:$W$164,'Payment Breakdown Current'!$AE$15:$AE$164,$A7))-(SUMIFS('Payment Breakdown Prior'!$W$15:$W$164,'Payment Breakdown Prior'!$AE$15:$AE$164,$A7)) | AB7: =(SUMIFS('Payment Breakdown Current'!$X$15:$X$164,'Payment Breakdown Current'!$AE$15:$AE$164,$A7))-(SUMIFS('Payment Breakdown Prior'!$X$15:$X$164,'Payment Breakdown Prior'!$AE$15:$AE$164,$A7)) | AC7: =(SUMIFS('Payment Breakdown Current'!$Y$15:$Y$164,'Payment Breakdown Current'!$AE$15:$AE$164,$A7))-(SUMIFS('Payment Breakdown Prior'!$Y$15:$Y$164,'Payment Breakdown Prior'!$AE$15:$AE$164,$A7)) | AD7: =(SUMIFS('Payment Breakdown Current'!$Z$15:$Z$164,'Payment Breakdown Current'!$AE$15:$AE$164,$A7))-(SUMIFS('Payment Breakdown Prior'!$Z$15:$Z$164,'Payment Breakdown Prior'!$AE$15:$AE$164,$A7)) | AE7: =(SUMIFS('Payment Breakdown Current'!$AA$15:$AA$164,'Payment Breakdown Current'!$AE$15:$AE$164,$A7))-(SUMIFS('Payment Breakdown Prior'!$AA$15:$AA$164,'Payment Breakdown Prior'!$AE$15:$AE$164,$A7)) | AF7: =(SUMIFS('Payment Breakdown Current'!$AB$15:$AB$164,'Payment Breakdown Current'!$AE$15:$AE$164,$A7))-(SUMIFS('Payment Breakdown Prior'!$AB$15:$AB$164,'Payment Breakdown Prior'!$AE$15:$AE$164,$A7)) | AG7: =(SUMIFS('Payment Breakdown Current'!$AC$15:$AC$164,'Payment Breakdown Current'!$AE$15:$AE$164,$A7))-(SUMIFS('Payment Breakdown Prior'!$AC$15:$AC$164,'Payment Breakdown Prior'!$AE$15:$AE$164,$A7)) | AH7: =(SUMIFS('Payment Breakdown Current'!$AD$15:$AD$164,'Payment Breakdown Current'!$AE$15:$AE$164,$A7))-(SUMIFS('Payment Breakdown Prior'!$AD$15:$AD$164,'Payment Breakdown Prior'!$AE$15:$AE$164,$A7)) | AI7: {=MAX(ABS(W7:AH7))} | AJ7: {=IF(AI7<0.005,"",IFERROR(INDEX($W$1:$AH$1,MATCH(AI7,ABS(W7:AH7),0)),""))} | AK7: {=IF(AI7<0.005,"",IFERROR(INDEX(W7:AH7,MATCH(AI7,ABS(W7:AH7),0)),""))} | AL7: =IF(R7=1,ABS(L7)-ROW()/100000000,"")
A8: =IF('NPV Comparison'!D21="","",'NPV Comparison'!D21) | B8: =IF('NPV Comparison'!E21="","",'NPV Comparison'!E21) | C8: =IF('NPV Comparison'!F21="","",'NPV Comparison'!F21) | D8: =IF($A8="","",IFERROR(INDEX(Structure!$E$13:$E$312,MATCH($A8,Structure!$P$13:$P$312,0)),"")) | E8: =IF($A8="",0,IF(COUNTIF(Structure!$P$13:$P$312,$A8)=0,0,IF(COUNTIFS(Structure!$P$13:$P$312,$A8,Structure!$N$13:$N$312,"<>Zero Hours")=0,1,0))) | F8: =IF($A8="",0,1-E8) | G8: =IF($A8="",0,IF(COUNTIF('New Starters'!$D$14:$D$73,$A8)>0,1,0)) | H8: =IF($A8="",0,IF(COUNTIF('Leavers'!$D$12:$D$71,$A8)>0,1,0)) | I8: =IF($A8="","",IFERROR(INDEX('New Starters'!$K$14:$K$73,MATCH($A8,'New Starters'!$D$14:$D$73,0)),IFERROR(INDEX('Leavers'!$K$12:$K$71,MATCH($A8,'Leavers'!$D$12:$D$71,0)),""))) | J8: =IF(AND(G8=1,I8<>"",COUNTIF('Leavers'!$K$12:$K$71,I8)>0),1,IF(AND(H8=1,I8<>"",COUNTIF('New Starters'!$K$14:$K$73,I8)>0),1,0)) | K8: =IF(ISNUMBER(SEARCH("Head Office",D8)),'Control Sheet'!$C$6,'Control Sheet'!$C$5) | L8: =IF(OR($A8="",AND(B8="",C8="")),"",IF(B8="",C8,IF(C8="",-B8,C8-B8))) | M8: =IFERROR(L8/B8,"") | N8: =IF($A8="",0,IF(OR(B8="",C8="",C8=0,AND(ISNUMBER(M8),ABS(M8)>K8)),1,0)) | O8: =IF(AND(N8=1,ABS(L8)>='Control Sheet'!$C$7,F8=1),1,0) | P8: =IF($A8="","",IF(F8=0,"Zero Hours",IF(J8=1,"Explained: Paired transfer",IF(AND(G8=1,H8=0,J8=0),"Explained: Starter",IF(AND(H8=1,G8=0,J8=0),"Explained: Leaver",IF(O8=1,"Review required","OK")))))) | Q8: =IF(AND(F8=1,OR(C8="",C8=0),H8=0,J8=0),1,0) | R8: =IF(F8=0,0,IF(P8="Review required",1,IF(AND(P8="Explained: Starter",ISNUMBER(C8),C8>=1500),1,0))) | S8: =IF(R8=0,"",IF(Q8=1,"High",IF(AND(P8="Explained: Starter",C8>=1500),"High",IF(ABS(L8)>=2000,"High",IF(ABS(L8)>=500,"Medium","Low"))))) | T8: =SUMIFS('Payment Breakdown Prior'!$S$15:$S$164,'Payment Breakdown Prior'!$AE$15:$AE$164,$A8) | U8: =SUMIFS('Payment Breakdown Current'!$S$15:$S$164,'Payment Breakdown Current'!$AE$15:$AE$164,$A8) | V8: =IFERROR((U8-T8)/T8,"") | W8: =(SUMIFS('Payment Breakdown Current'!$S$15:$S$164,'Payment Breakdown Current'!$AE$15:$AE$164,$A8))-(SUMIFS('Payment Breakdown Prior'!$S$15:$S$164,'Payment Breakdown Prior'!$AE$15:$AE$164,$A8)) | X8: =(SUMIFS('Payment Breakdown Current'!$T$15:$T$164,'Payment Breakdown Current'!$AE$15:$AE$164,$A8))-(SUMIFS('Payment Breakdown Prior'!$T$15:$T$164,'Payment Breakdown Prior'!$AE$15:$AE$164,$A8)) | Y8: =(SUMIFS('Payment Breakdown Current'!$U$15:$U$164,'Payment Breakdown Current'!$AE$15:$AE$164,$A8))-(SUMIFS('Payment Breakdown Prior'!$U$15:$U$164,'Payment Breakdown Prior'!$AE$15:$AE$164,$A8)) | Z8: =(SUMIFS('Payment Breakdown Current'!$V$15:$V$164,'Payment Breakdown Current'!$AE$15:$AE$164,$A8))-(SUMIFS('Payment Breakdown Prior'!$V$15:$V$164,'Payment Breakdown Prior'!$AE$15:$AE$164,$A8)) | AA8: =(SUMIFS('Payment Breakdown Current'!$W$15:$W$164,'Payment Breakdown Current'!$AE$15:$AE$164,$A8))-(SUMIFS('Payment Breakdown Prior'!$W$15:$W$164,'Payment Breakdown Prior'!$AE$15:$AE$164,$A8)) | AB8: =(SUMIFS('Payment Breakdown Current'!$X$15:$X$164,'Payment Breakdown Current'!$AE$15:$AE$164,$A8))-(SUMIFS('Payment Breakdown Prior'!$X$15:$X$164,'Payment Breakdown Prior'!$AE$15:$AE$164,$A8)) | AC8: =(SUMIFS('Payment Breakdown Current'!$Y$15:$Y$164,'Payment Breakdown Current'!$AE$15:$AE$164,$A8))-(SUMIFS('Payment Breakdown Prior'!$Y$15:$Y$164,'Payment Breakdown Prior'!$AE$15:$AE$164,$A8)) | AD8: =(SUMIFS('Payment Breakdown Current'!$Z$15:$Z$164,'Payment Breakdown Current'!$AE$15:$AE$164,$A8))-(SUMIFS('Payment Breakdown Prior'!$Z$15:$Z$164,'Payment Breakdown Prior'!$AE$15:$AE$164,$A8)) | AE8: =(SUMIFS('Payment Breakdown Current'!$AA$15:$AA$164,'Payment Breakdown Current'!$AE$15:$AE$164,$A8))-(SUMIFS('Payment Breakdown Prior'!$AA$15:$AA$164,'Payment Breakdown Prior'!$AE$15:$AE$164,$A8)) | AF8: =(SUMIFS('Payment Breakdown Current'!$AB$15:$AB$164,'Payment Breakdown Current'!$AE$15:$AE$164,$A8))-(SUMIFS('Payment Breakdown Prior'!$AB$15:$AB$164,'Payment Breakdown Prior'!$AE$15:$AE$164,$A8)) | AG8: =(SUMIFS('Payment Breakdown Current'!$AC$15:$AC$164,'Payment Breakdown Current'!$AE$15:$AE$164,$A8))-(SUMIFS('Payment Breakdown Prior'!$AC$15:$AC$164,'Payment Breakdown Prior'!$AE$15:$AE$164,$A8)) | AH8: =(SUMIFS('Payment Breakdown Current'!$AD$15:$AD$164,'Payment Breakdown Current'!$AE$15:$AE$164,$A8))-(SUMIFS('Payment Breakdown Prior'!$AD$15:$AD$164,'Payment Breakdown Prior'!$AE$15:$AE$164,$A8)) | AI8: {=MAX(ABS(W8:AH8))} | AJ8: {=IF(AI8<0.005,"",IFERROR(INDEX($W$1:$AH$1,MATCH(AI8,ABS(W8:AH8),0)),""))} | AK8: {=IF(AI8<0.005,"",IFERROR(INDEX(W8:AH8,MATCH(AI8,ABS(W8:AH8),0)),""))} | AL8: =IF(R8=1,ABS(L8)-ROW()/100000000,"")
A9: =IF('NPV Comparison'!D22="","",'NPV Comparison'!D22) | B9: =IF('NPV Comparison'!E22="","",'NPV Comparison'!E22) | C9: =IF('NPV Comparison'!F22="","",'NPV Comparison'!F22) | D9: =IF($A9="","",IFERROR(INDEX(Structure!$E$13:$E$312,MATCH($A9,Structure!$P$13:$P$312,0)),"")) | E9: =IF($A9="",0,IF(COUNTIF(Structure!$P$13:$P$312,$A9)=0,0,IF(COUNTIFS(Structure!$P$13:$P$312,$A9,Structure!$N$13:$N$312,"<>Zero Hours")=0,1,0))) | F9: =IF($A9="",0,1-E9) | G9: =IF($A9="",0,IF(COUNTIF('New Starters'!$D$14:$D$73,$A9)>0,1,0)) | H9: =IF($A9="",0,IF(COUNTIF('Leavers'!$D$12:$D$71,$A9)>0,1,0)) | I9: =IF($A9="","",IFERROR(INDEX('New Starters'!$K$14:$K$73,MATCH($A9,'New Starters'!$D$14:$D$73,0)),IFERROR(INDEX('Leavers'!$K$12:$K$71,MATCH($A9,'Leavers'!$D$12:$D$71,0)),""))) | J9: =IF(AND(G9=1,I9<>"",COUNTIF('Leavers'!$K$12:$K$71,I9)>0),1,IF(AND(H9=1,I9<>"",COUNTIF('New Starters'!$K$14:$K$73,I9)>0),1,0)) | K9: =IF(ISNUMBER(SEARCH("Head Office",D9)),'Control Sheet'!$C$6,'Control Sheet'!$C$5) | L9: =IF(OR($A9="",AND(B9="",C9="")),"",IF(B9="",C9,IF(C9="",-B9,C9-B9))) | M9: =IFERROR(L9/B9,"") | N9: =IF($A9="",0,IF(OR(B9="",C9="",C9=0,AND(ISNUMBER(M9),ABS(M9)>K9)),1,0)) | O9: =IF(AND(N9=1,ABS(L9)>='Control Sheet'!$C$7,F9=1),1,0) | P9: =IF($A9="","",IF(F9=0,"Zero Hours",IF(J9=1,"Explained: Paired transfer",IF(AND(G9=1,H9=0,J9=0),"Explained: Starter",IF(AND(H9=1,G9=0,J9=0),"Explained: Leaver",IF(O9=1,"Review required","OK")))))) | Q9: =IF(AND(F9=1,OR(C9="",C9=0),H9=0,J9=0),1,0) | R9: =IF(F9=0,0,IF(P9="Review required",1,IF(AND(P9="Explained: Starter",ISNUMBER(C9),C9>=1500),1,0))) | S9: =IF(R9=0,"",IF(Q9=1,"High",IF(AND(P9="Explained: Starter",C9>=1500),"High",IF(ABS(L9)>=2000,"High",IF(ABS(L9)>=500,"Medium","Low"))))) | T9: =SUMIFS('Payment Breakdown Prior'!$S$15:$S$164,'Payment Breakdown Prior'!$AE$15:$AE$164,$A9) | U9: =SUMIFS('Payment Breakdown Current'!$S$15:$S$164,'Payment Breakdown Current'!$AE$15:$AE$164,$A9) | V9: =IFERROR((U9-T9)/T9,"") | W9: =(SUMIFS('Payment Breakdown Current'!$S$15:$S$164,'Payment Breakdown Current'!$AE$15:$AE$164,$A9))-(SUMIFS('Payment Breakdown Prior'!$S$15:$S$164,'Payment Breakdown Prior'!$AE$15:$AE$164,$A9)) | X9: =(SUMIFS('Payment Breakdown Current'!$T$15:$T$164,'Payment Breakdown Current'!$AE$15:$AE$164,$A9))-(SUMIFS('Payment Breakdown Prior'!$T$15:$T$164,'Payment Breakdown Prior'!$AE$15:$AE$164,$A9)) | Y9: =(SUMIFS('Payment Breakdown Current'!$U$15:$U$164,'Payment Breakdown Current'!$AE$15:$AE$164,$A9))-(SUMIFS('Payment Breakdown Prior'!$U$15:$U$164,'Payment Breakdown Prior'!$AE$15:$AE$164,$A9)) | Z9: =(SUMIFS('Payment Breakdown Current'!$V$15:$V$164,'Payment Breakdown Current'!$AE$15:$AE$164,$A9))-(SUMIFS('Payment Breakdown Prior'!$V$15:$V$164,'Payment Breakdown Prior'!$AE$15:$AE$164,$A9)) | AA9: =(SUMIFS('Payment Breakdown Current'!$W$15:$W$164,'Payment Breakdown Current'!$AE$15:$AE$164,$A9))-(SUMIFS('Payment Breakdown Prior'!$W$15:$W$164,'Payment Breakdown Prior'!$AE$15:$AE$164,$A9)) | AB9: =(SUMIFS('Payment Breakdown Current'!$X$15:$X$164,'Payment Breakdown Current'!$AE$15:$AE$164,$A9))-(SUMIFS('Payment Breakdown Prior'!$X$15:$X$164,'Payment Breakdown Prior'!$AE$15:$AE$164,$A9)) | AC9: =(SUMIFS('Payment Breakdown Current'!$Y$15:$Y$164,'Payment Breakdown Current'!$AE$15:$AE$164,$A9))-(SUMIFS('Payment Breakdown Prior'!$Y$15:$Y$164,'Payment Breakdown Prior'!$AE$15:$AE$164,$A9)) | AD9: =(SUMIFS('Payment Breakdown Current'!$Z$15:$Z$164,'Payment Breakdown Current'!$AE$15:$AE$164,$A9))-(SUMIFS('Payment Breakdown Prior'!$Z$15:$Z$164,'Payment Breakdown Prior'!$AE$15:$AE$164,$A9)) | AE9: =(SUMIFS('Payment Breakdown Current'!$AA$15:$AA$164,'Payment Breakdown Current'!$AE$15:$AE$164,$A9))-(SUMIFS('Payment Breakdown Prior'!$AA$15:$AA$164,'Payment Breakdown Prior'!$AE$15:$AE$164,$A9)) | AF9: =(SUMIFS('Payment Breakdown Current'!$AB$15:$AB$164,'Payment Breakdown Current'!$AE$15:$AE$164,$A9))-(SUMIFS('Payment Breakdown Prior'!$AB$15:$AB$164,'Payment Breakdown Prior'!$AE$15:$AE$164,$A9)) | AG9: =(SUMIFS('Payment Breakdown Current'!$AC$15:$AC$164,'Payment Breakdown Current'!$AE$15:$AE$164,$A9))-(SUMIFS('Payment Breakdown Prior'!$AC$15:$AC$164,'Payment Breakdown Prior'!$AE$15:$AE$164,$A9)) | AH9: =(SUMIFS('Payment Breakdown Current'!$AD$15:$AD$164,'Payment Breakdown Current'!$AE$15:$AE$164,$A9))-(SUMIFS('Payment Breakdown Prior'!$AD$15:$AD$164,'Payment Breakdown Prior'!$AE$15:$AE$164,$A9)) | AI9: {=MAX(ABS(W9:AH9))} | AJ9: {=IF(AI9<0.005,"",IFERROR(INDEX($W$1:$AH$1,MATCH(AI9,ABS(W9:AH9),0)),""))} | AK9: {=IF(AI9<0.005,"",IFERROR(INDEX(W9:AH9,MATCH(AI9,ABS(W9:AH9),0)),""))} | AL9: =IF(R9=1,ABS(L9)-ROW()/100000000,"")
A10: =IF('NPV Comparison'!D23="","",'NPV Comparison'!D23) | B10: =IF('NPV Comparison'!E23="","",'NPV Comparison'!E23) | C10: =IF('NPV Comparison'!F23="","",'NPV Comparison'!F23) | D10: =IF($A10="","",IFERROR(INDEX(Structure!$E$13:$E$312,MATCH($A10,Structure!$P$13:$P$312,0)),"")) | E10: =IF($A10="",0,IF(COUNTIF(Structure!$P$13:$P$312,$A10)=0,0,IF(COUNTIFS(Structure!$P$13:$P$312,$A10,Structure!$N$13:$N$312,"<>Zero Hours")=0,1,0))) | F10: =IF($A10="",0,1-E10) | G10: =IF($A10="",0,IF(COUNTIF('New Starters'!$D$14:$D$73,$A10)>0,1,0)) | H10: =IF($A10="",0,IF(COUNTIF('Leavers'!$D$12:$D$71,$A10)>0,1,0)) | I10: =IF($A10="","",IFERROR(INDEX('New Starters'!$K$14:$K$73,MATCH($A10,'New Starters'!$D$14:$D$73,0)),IFERROR(INDEX('Leavers'!$K$12:$K$71,MATCH($A10,'Leavers'!$D$12:$D$71,0)),""))) | J10: =IF(AND(G10=1,I10<>"",COUNTIF('Leavers'!$K$12:$K$71,I10)>0),1,IF(AND(H10=1,I10<>"",COUNTIF('New Starters'!$K$14:$K$73,I10)>0),1,0)) | K10: =IF(ISNUMBER(SEARCH("Head Office",D10)),'Control Sheet'!$C$6,'Control Sheet'!$C$5) | L10: =IF(OR($A10="",AND(B10="",C10="")),"",IF(B10="",C10,IF(C10="",-B10,C10-B10))) | M10: =IFERROR(L10/B10,"") | N10: =IF($A10="",0,IF(OR(B10="",C10="",C10=0,AND(ISNUMBER(M10),ABS(M10)>K10)),1,0)) | O10: =IF(AND(N10=1,ABS(L10)>='Control Sheet'!$C$7,F10=1),1,0) | P10: =IF($A10="","",IF(F10=0,"Zero Hours",IF(J10=1,"Explained: Paired transfer",IF(AND(G10=1,H10=0,J10=0),"Explained: Starter",IF(AND(H10=1,G10=0,J10=0),"Explained: Leaver",IF(O10=1,"Review required","OK")))))) | Q10: =IF(AND(F10=1,OR(C10="",C10=0),H10=0,J10=0),1,0) | R10: =IF(F10=0,0,IF(P10="Review required",1,IF(AND(P10="Explained: Starter",ISNUMBER(C10),C10>=1500),1,0))) | S10: =IF(R10=0,"",IF(Q10=1,"High",IF(AND(P10="Explained: Starter",C10>=1500),"High",IF(ABS(L10)>=2000,"High",IF(ABS(L10)>=500,"Medium","Low"))))) | T10: =SUMIFS('Payment Breakdown Prior'!$S$15:$S$164,'Payment Breakdown Prior'!$AE$15:$AE$164,$A10) | U10: =SUMIFS('Payment Breakdown Current'!$S$15:$S$164,'Payment Breakdown Current'!$AE$15:$AE$164,$A10) | V10: =IFERROR((U10-T10)/T10,"") | W10: =(SUMIFS('Payment Breakdown Current'!$S$15:$S$164,'Payment Breakdown Current'!$AE$15:$AE$164,$A10))-(SUMIFS('Payment Breakdown Prior'!$S$15:$S$164,'Payment Breakdown Prior'!$AE$15:$AE$164,$A10)) | X10: =(SUMIFS('Payment Breakdown Current'!$T$15:$T$164,'Payment Breakdown Current'!$AE$15:$AE$164,$A10))-(SUMIFS('Payment Breakdown Prior'!$T$15:$T$164,'Payment Breakdown Prior'!$AE$15:$AE$164,$A10)) | Y10: =(SUMIFS('Payment Breakdown Current'!$U$15:$U$164,'Payment Breakdown Current'!$AE$15:$AE$164,$A10))-(SUMIFS('Payment Breakdown Prior'!$U$15:$U$164,'Payment Breakdown Prior'!$AE$15:$AE$164,$A10)) | Z10: =(SUMIFS('Payment Breakdown Current'!$V$15:$V$164,'Payment Breakdown Current'!$AE$15:$AE$164,$A10))-(SUMIFS('Payment Breakdown Prior'!$V$15:$V$164,'Payment Breakdown Prior'!$AE$15:$AE$164,$A10)) | AA10: =(SUMIFS('Payment Breakdown Current'!$W$15:$W$164,'Payment Breakdown Current'!$AE$15:$AE$164,$A10))-(SUMIFS('Payment Breakdown Prior'!$W$15:$W$164,'Payment Breakdown Prior'!$AE$15:$AE$164,$A10)) | AB10: =(SUMIFS('Payment Breakdown Current'!$X$15:$X$164,'Payment Breakdown Current'!$AE$15:$AE$164,$A10))-(SUMIFS('Payment Breakdown Prior'!$X$15:$X$164,'Payment Breakdown Prior'!$AE$15:$AE$164,$A10)) | AC10: =(SUMIFS('Payment Breakdown Current'!$Y$15:$Y$164,'Payment Breakdown Current'!$AE$15:$AE$164,$A10))-(SUMIFS('Payment Breakdown Prior'!$Y$15:$Y$164,'Payment Breakdown Prior'!$AE$15:$AE$164,$A10)) | AD10: =(SUMIFS('Payment Breakdown Current'!$Z$15:$Z$164,'Payment Breakdown Current'!$AE$15:$AE$164,$A10))-(SUMIFS('Payment Breakdown Prior'!$Z$15:$Z$164,'Payment Breakdown Prior'!$AE$15:$AE$164,$A10)) | AE10: =(SUMIFS('Payment Breakdown Current'!$AA$15:$AA$164,'Payment Breakdown Current'!$AE$15:$AE$164,$A10))-(SUMIFS('Payment Breakdown Prior'!$AA$15:$AA$164,'Payment Breakdown Prior'!$AE$15:$AE$164,$A10)) | AF10: =(SUMIFS('Payment Breakdown Current'!$AB$15:$AB$164,'Payment Breakdown Current'!$AE$15:$AE$164,$A10))-(SUMIFS('Payment Breakdown Prior'!$AB$15:$AB$164,'Payment Breakdown Prior'!$AE$15:$AE$164,$A10)) | AG10: =(SUMIFS('Payment Breakdown Current'!$AC$15:$AC$164,'Payment Breakdown Current'!$AE$15:$AE$164,$A10))-(SUMIFS('Payment Breakdown Prior'!$AC$15:$AC$164,'Payment Breakdown Prior'!$AE$15:$AE$164,$A10)) | AH10: =(SUMIFS('Payment Breakdown Current'!$AD$15:$AD$164,'Payment Breakdown Current'!$AE$15:$AE$164,$A10))-(SUMIFS('Payment Breakdown Prior'!$AD$15:$AD$164,'Payment Breakdown Prior'!$AE$15:$AE$164,$A10)) | AI10: {=MAX(ABS(W10:AH10))} | AJ10: {=IF(AI10<0.005,"",IFERROR(INDEX($W$1:$AH$1,MATCH(AI10,ABS(W10:AH10),0)),""))} | AK10: {=IF(AI10<0.005,"",IFERROR(INDEX(W10:AH10,MATCH(AI10,ABS(W10:AH10),0)),""))} | AL10: =IF(R10=1,ABS(L10)-ROW()/100000000,"")
A11: =IF('NPV Comparison'!D24="","",'NPV Comparison'!D24) | B11: =IF('NPV Comparison'!E24="","",'NPV Comparison'!E24) | C11: =IF('NPV Comparison'!F24="","",'NPV Comparison'!F24) | D11: =IF($A11="","",IFERROR(INDEX(Structure!$E$13:$E$312,MATCH($A11,Structure!$P$13:$P$312,0)),"")) | E11: =IF($A11="",0,IF(COUNTIF(Structure!$P$13:$P$312,$A11)=0,0,IF(COUNTIFS(Structure!$P$13:$P$312,$A11,Structure!$N$13:$N$312,"<>Zero Hours")=0,1,0))) | F11: =IF($A11="",0,1-E11) | G11: =IF($A11="",0,IF(COUNTIF('New Starters'!$D$14:$D$73,$A11)>0,1,0)) | H11: =IF($A11="",0,IF(COUNTIF('Leavers'!$D$12:$D$71,$A11)>0,1,0)) | I11: =IF($A11="","",IFERROR(INDEX('New Starters'!$K$14:$K$73,MATCH($A11,'New Starters'!$D$14:$D$73,0)),IFERROR(INDEX('Leavers'!$K$12:$K$71,MATCH($A11,'Leavers'!$D$12:$D$71,0)),""))) | J11: =IF(AND(G11=1,I11<>"",COUNTIF('Leavers'!$K$12:$K$71,I11)>0),1,IF(AND(H11=1,I11<>"",COUNTIF('New Starters'!$K$14:$K$73,I11)>0),1,0)) | K11: =IF(ISNUMBER(SEARCH("Head Office",D11)),'Control Sheet'!$C$6,'Control Sheet'!$C$5) | L11: =IF(OR($A11="",AND(B11="",C11="")),"",IF(B11="",C11,IF(C11="",-B11,C11-B11))) | M11: =IFERROR(L11/B11,"") | N11: =IF($A11="",0,IF(OR(B11="",C11="",C11=0,AND(ISNUMBER(M11),ABS(M11)>K11)),1,0)) | O11: =IF(AND(N11=1,ABS(L11)>='Control Sheet'!$C$7,F11=1),1,0) | P11: =IF($A11="","",IF(F11=0,"Zero Hours",IF(J11=1,"Explained: Paired transfer",IF(AND(G11=1,H11=0,J11=0),"Explained: Starter",IF(AND(H11=1,G11=0,J11=0),"Explained: Leaver",IF(O11=1,"Review required","OK")))))) | Q11: =IF(AND(F11=1,OR(C11="",C11=0),H11=0,J11=0),1,0) | R11: =IF(F11=0,0,IF(P11="Review required",1,IF(AND(P11="Explained: Starter",ISNUMBER(C11),C11>=1500),1,0))) | S11: =IF(R11=0,"",IF(Q11=1,"High",IF(AND(P11="Explained: Starter",C11>=1500),"High",IF(ABS(L11)>=2000,"High",IF(ABS(L11)>=500,"Medium","Low"))))) | T11: =SUMIFS('Payment Breakdown Prior'!$S$15:$S$164,'Payment Breakdown Prior'!$AE$15:$AE$164,$A11) | U11: =SUMIFS('Payment Breakdown Current'!$S$15:$S$164,'Payment Breakdown Current'!$AE$15:$AE$164,$A11) | V11: =IFERROR((U11-T11)/T11,"") | W11: =(SUMIFS('Payment Breakdown Current'!$S$15:$S$164,'Payment Breakdown Current'!$AE$15:$AE$164,$A11))-(SUMIFS('Payment Breakdown Prior'!$S$15:$S$164,'Payment Breakdown Prior'!$AE$15:$AE$164,$A11)) | X11: =(SUMIFS('Payment Breakdown Current'!$T$15:$T$164,'Payment Breakdown Current'!$AE$15:$AE$164,$A11))-(SUMIFS('Payment Breakdown Prior'!$T$15:$T$164,'Payment Breakdown Prior'!$AE$15:$AE$164,$A11)) | Y11: =(SUMIFS('Payment Breakdown Current'!$U$15:$U$164,'Payment Breakdown Current'!$AE$15:$AE$164,$A11))-(SUMIFS('Payment Breakdown Prior'!$U$15:$U$164,'Payment Breakdown Prior'!$AE$15:$AE$164,$A11)) | Z11: =(SUMIFS('Payment Breakdown Current'!$V$15:$V$164,'Payment Breakdown Current'!$AE$15:$AE$164,$A11))-(SUMIFS('Payment Breakdown Prior'!$V$15:$V$164,'Payment Breakdown Prior'!$AE$15:$AE$164,$A11)) | AA11: =(SUMIFS('Payment Breakdown Current'!$W$15:$W$164,'Payment Breakdown Current'!$AE$15:$AE$164,$A11))-(SUMIFS('Payment Breakdown Prior'!$W$15:$W$164,'Payment Breakdown Prior'!$AE$15:$AE$164,$A11)) | AB11: =(SUMIFS('Payment Breakdown Current'!$X$15:$X$164,'Payment Breakdown Current'!$AE$15:$AE$164,$A11))-(SUMIFS('Payment Breakdown Prior'!$X$15:$X$164,'Payment Breakdown Prior'!$AE$15:$AE$164,$A11)) | AC11: =(SUMIFS('Payment Breakdown Current'!$Y$15:$Y$164,'Payment Breakdown Current'!$AE$15:$AE$164,$A11))-(SUMIFS('Payment Breakdown Prior'!$Y$15:$Y$164,'Payment Breakdown Prior'!$AE$15:$AE$164,$A11)) | AD11: =(SUMIFS('Payment Breakdown Current'!$Z$15:$Z$164,'Payment Breakdown Current'!$AE$15:$AE$164,$A11))-(SUMIFS('Payment Breakdown Prior'!$Z$15:$Z$164,'Payment Breakdown Prior'!$AE$15:$AE$164,$A11)) | AE11: =(SUMIFS('Payment Breakdown Current'!$AA$15:$AA$164,'Payment Breakdown Current'!$AE$15:$AE$164,$A11))-(SUMIFS('Payment Breakdown Prior'!$AA$15:$AA$164,'Payment Breakdown Prior'!$AE$15:$AE$164,$A11)) | AF11: =(SUMIFS('Payment Breakdown Current'!$AB$15:$AB$164,'Payment Breakdown Current'!$AE$15:$AE$164,$A11))-(SUMIFS('Payment Breakdown Prior'!$AB$15:$AB$164,'Payment Breakdown Prior'!$AE$15:$AE$164,$A11)) | AG11: =(SUMIFS('Payment Breakdown Current'!$AC$15:$AC$164,'Payment Breakdown Current'!$AE$15:$AE$164,$A11))-(SUMIFS('Payment Breakdown Prior'!$AC$15:$AC$164,'Payment Breakdown Prior'!$AE$15:$AE$164,$A11)) | AH11: =(SUMIFS('Payment Breakdown Current'!$AD$15:$AD$164,'Payment Breakdown Current'!$AE$15:$AE$164,$A11))-(SUMIFS('Payment Breakdown Prior'!$AD$15:$AD$164,'Payment Breakdown Prior'!$AE$15:$AE$164,$A11)) | AI11: {=MAX(ABS(W11:AH11))} | AJ11: {=IF(AI11<0.005,"",IFERROR(INDEX($W$1:$AH$1,MATCH(AI11,ABS(W11:AH11),0)),""))} | AK11: {=IF(AI11<0.005,"",IFERROR(INDEX(W11:AH11,MATCH(AI11,ABS(W11:AH11),0)),""))} | AL11: =IF(R11=1,ABS(L11)-ROW()/100000000,"")
A12: =IF('NPV Comparison'!D25="","",'NPV Comparison'!D25) | B12: =IF('NPV Comparison'!E25="","",'NPV Comparison'!E25) | C12: =IF('NPV Comparison'!F25="","",'NPV Comparison'!F25) | D12: =IF($A12="","",IFERROR(INDEX(Structure!$E$13:$E$312,MATCH($A12,Structure!$P$13:$P$312,0)),"")) | E12: =IF($A12="",0,IF(COUNTIF(Structure!$P$13:$P$312,$A12)=0,0,IF(COUNTIFS(Structure!$P$13:$P$312,$A12,Structure!$N$13:$N$312,"<>Zero Hours")=0,1,0))) | F12: =IF($A12="",0,1-E12) | G12: =IF($A12="",0,IF(COUNTIF('New Starters'!$D$14:$D$73,$A12)>0,1,0)) | H12: =IF($A12="",0,IF(COUNTIF('Leavers'!$D$12:$D$71,$A12)>0,1,0)) | I12: =IF($A12="","",IFERROR(INDEX('New Starters'!$K$14:$K$73,MATCH($A12,'New Starters'!$D$14:$D$73,0)),IFERROR(INDEX('Leavers'!$K$12:$K$71,MATCH($A12,'Leavers'!$D$12:$D$71,0)),""))) | J12: =IF(AND(G12=1,I12<>"",COUNTIF('Leavers'!$K$12:$K$71,I12)>0),1,IF(AND(H12=1,I12<>"",COUNTIF('New Starters'!$K$14:$K$73,I12)>0),1,0)) | K12: =IF(ISNUMBER(SEARCH("Head Office",D12)),'Control Sheet'!$C$6,'Control Sheet'!$C$5) | L12: =IF(OR($A12="",AND(B12="",C12="")),"",IF(B12="",C12,IF(C12="",-B12,C12-B12))) | M12: =IFERROR(L12/B12,"") | N12: =IF($A12="",0,IF(OR(B12="",C12="",C12=0,AND(ISNUMBER(M12),ABS(M12)>K12)),1,0)) | O12: =IF(AND(N12=1,ABS(L12)>='Control Sheet'!$C$7,F12=1),1,0) | P12: =IF($A12="","",IF(F12=0,"Zero Hours",IF(J12=1,"Explained: Paired transfer",IF(AND(G12=1,H12=0,J12=0),"Explained: Starter",IF(AND(H12=1,G12=0,J12=0),"Explained: Leaver",IF(O12=1,"Review required","OK")))))) | Q12: =IF(AND(F12=1,OR(C12="",C12=0),H12=0,J12=0),1,0) | R12: =IF(F12=0,0,IF(P12="Review required",1,IF(AND(P12="Explained: Starter",ISNUMBER(C12),C12>=1500),1,0))) | S12: =IF(R12=0,"",IF(Q12=1,"High",IF(AND(P12="Explained: Starter",C12>=1500),"High",IF(ABS(L12)>=2000,"High",IF(ABS(L12)>=500,"Medium","Low"))))) | T12: =SUMIFS('Payment Breakdown Prior'!$S$15:$S$164,'Payment Breakdown Prior'!$AE$15:$AE$164,$A12) | U12: =SUMIFS('Payment Breakdown Current'!$S$15:$S$164,'Payment Breakdown Current'!$AE$15:$AE$164,$A12) | V12: =IFERROR((U12-T12)/T12,"") | W12: =(SUMIFS('Payment Breakdown Current'!$S$15:$S$164,'Payment Breakdown Current'!$AE$15:$AE$164,$A12))-(SUMIFS('Payment Breakdown Prior'!$S$15:$S$164,'Payment Breakdown Prior'!$AE$15:$AE$164,$A12)) | X12: =(SUMIFS('Payment Breakdown Current'!$T$15:$T$164,'Payment Breakdown Current'!$AE$15:$AE$164,$A12))-(SUMIFS('Payment Breakdown Prior'!$T$15:$T$164,'Payment Breakdown Prior'!$AE$15:$AE$164,$A12)) | Y12: =(SUMIFS('Payment Breakdown Current'!$U$15:$U$164,'Payment Breakdown Current'!$AE$15:$AE$164,$A12))-(SUMIFS('Payment Breakdown Prior'!$U$15:$U$164,'Payment Breakdown Prior'!$AE$15:$AE$164,$A12)) | Z12: =(SUMIFS('Payment Breakdown Current'!$V$15:$V$164,'Payment Breakdown Current'!$AE$15:$AE$164,$A12))-(SUMIFS('Payment Breakdown Prior'!$V$15:$V$164,'Payment Breakdown Prior'!$AE$15:$AE$164,$A12)) | AA12: =(SUMIFS('Payment Breakdown Current'!$W$15:$W$164,'Payment Breakdown Current'!$AE$15:$AE$164,$A12))-(SUMIFS('Payment Breakdown Prior'!$W$15:$W$164,'Payment Breakdown Prior'!$AE$15:$AE$164,$A12)) | AB12: =(SUMIFS('Payment Breakdown Current'!$X$15:$X$164,'Payment Breakdown Current'!$AE$15:$AE$164,$A12))-(SUMIFS('Payment Breakdown Prior'!$X$15:$X$164,'Payment Breakdown Prior'!$AE$15:$AE$164,$A12)) | AC12: =(SUMIFS('Payment Breakdown Current'!$Y$15:$Y$164,'Payment Breakdown Current'!$AE$15:$AE$164,$A12))-(SUMIFS('Payment Breakdown Prior'!$Y$15:$Y$164,'Payment Breakdown Prior'!$AE$15:$AE$164,$A12)) | AD12: =(SUMIFS('Payment Breakdown Current'!$Z$15:$Z$164,'Payment Breakdown Current'!$AE$15:$AE$164,$A12))-(SUMIFS('Payment Breakdown Prior'!$Z$15:$Z$164,'Payment Breakdown Prior'!$AE$15:$AE$164,$A12)) | AE12: =(SUMIFS('Payment Breakdown Current'!$AA$15:$AA$164,'Payment Breakdown Current'!$AE$15:$AE$164,$A12))-(SUMIFS('Payment Breakdown Prior'!$AA$15:$AA$164,'Payment Breakdown Prior'!$AE$15:$AE$164,$A12)) | AF12: =(SUMIFS('Payment Breakdown Current'!$AB$15:$AB$164,'Payment Breakdown Current'!$AE$15:$AE$164,$A12))-(SUMIFS('Payment Breakdown Prior'!$AB$15:$AB$164,'Payment Breakdown Prior'!$AE$15:$AE$164,$A12)) | AG12: =(SUMIFS('Payment Breakdown Current'!$AC$15:$AC$164,'Payment Breakdown Current'!$AE$15:$AE$164,$A12))-(SUMIFS('Payment Breakdown Prior'!$AC$15:$AC$164,'Payment Breakdown Prior'!$AE$15:$AE$164,$A12)) | AH12: =(SUMIFS('Payment Breakdown Current'!$AD$15:$AD$164,'Payment Breakdown Current'!$AE$15:$AE$164,$A12))-(SUMIFS('Payment Breakdown Prior'!$AD$15:$AD$164,'Payment Breakdown Prior'!$AE$15:$AE$164,$A12)) | AI12: {=MAX(ABS(W12:AH12))} | AJ12: {=IF(AI12<0.005,"",IFERROR(INDEX($W$1:$AH$1,MATCH(AI12,ABS(W12:AH12),0)),""))} | AK12: {=IF(AI12<0.005,"",IFERROR(INDEX(W12:AH12,MATCH(AI12,ABS(W12:AH12),0)),""))} | AL12: =IF(R12=1,ABS(L12)-ROW()/100000000,"")
A13: =IF('NPV Comparison'!D26="","",'NPV Comparison'!D26) | B13: =IF('NPV Comparison'!E26="","",'NPV Comparison'!E26) | C13: =IF('NPV Comparison'!F26="","",'NPV Comparison'!F26) | D13: =IF($A13="","",IFERROR(INDEX(Structure!$E$13:$E$312,MATCH($A13,Structure!$P$13:$P$312,0)),"")) | E13: =IF($A13="",0,IF(COUNTIF(Structure!$P$13:$P$312,$A13)=0,0,IF(COUNTIFS(Structure!$P$13:$P$312,$A13,Structure!$N$13:$N$312,"<>Zero Hours")=0,1,0))) | F13: =IF($A13="",0,1-E13) | G13: =IF($A13="",0,IF(COUNTIF('New Starters'!$D$14:$D$73,$A13)>0,1,0)) | H13: =IF($A13="",0,IF(COUNTIF('Leavers'!$D$12:$D$71,$A13)>0,1,0)) | I13: =IF($A13="","",IFERROR(INDEX('New Starters'!$K$14:$K$73,MATCH($A13,'New Starters'!$D$14:$D$73,0)),IFERROR(INDEX('Leavers'!$K$12:$K$71,MATCH($A13,'Leavers'!$D$12:$D$71,0)),""))) | J13: =IF(AND(G13=1,I13<>"",COUNTIF('Leavers'!$K$12:$K$71,I13)>0),1,IF(AND(H13=1,I13<>"",COUNTIF('New Starters'!$K$14:$K$73,I13)>0),1,0)) | K13: =IF(ISNUMBER(SEARCH("Head Office",D13)),'Control Sheet'!$C$6,'Control Sheet'!$C$5) | L13: =IF(OR($A13="",AND(B13="",C13="")),"",IF(B13="",C13,IF(C13="",-B13,C13-B13))) | M13: =IFERROR(L13/B13,"") | N13: =IF($A13="",0,IF(OR(B13="",C13="",C13=0,AND(ISNUMBER(M13),ABS(M13)>K13)),1,0)) | O13: =IF(AND(N13=1,ABS(L13)>='Control Sheet'!$C$7,F13=1),1,0) | P13: =IF($A13="","",IF(F13=0,"Zero Hours",IF(J13=1,"Explained: Paired transfer",IF(AND(G13=1,H13=0,J13=0),"Explained: Starter",IF(AND(H13=1,G13=0,J13=0),"Explained: Leaver",IF(O13=1,"Review required","OK")))))) | Q13: =IF(AND(F13=1,OR(C13="",C13=0),H13=0,J13=0),1,0) | R13: =IF(F13=0,0,IF(P13="Review required",1,IF(AND(P13="Explained: Starter",ISNUMBER(C13),C13>=1500),1,0))) | S13: =IF(R13=0,"",IF(Q13=1,"High",IF(AND(P13="Explained: Starter",C13>=1500),"High",IF(ABS(L13)>=2000,"High",IF(ABS(L13)>=500,"Medium","Low"))))) | T13: =SUMIFS('Payment Breakdown Prior'!$S$15:$S$164,'Payment Breakdown Prior'!$AE$15:$AE$164,$A13) | U13: =SUMIFS('Payment Breakdown Current'!$S$15:$S$164,'Payment Breakdown Current'!$AE$15:$AE$164,$A13) | V13: =IFERROR((U13-T13)/T13,"") | W13: =(SUMIFS('Payment Breakdown Current'!$S$15:$S$164,'Payment Breakdown Current'!$AE$15:$AE$164,$A13))-(SUMIFS('Payment Breakdown Prior'!$S$15:$S$164,'Payment Breakdown Prior'!$AE$15:$AE$164,$A13)) | X13: =(SUMIFS('Payment Breakdown Current'!$T$15:$T$164,'Payment Breakdown Current'!$AE$15:$AE$164,$A13))-(SUMIFS('Payment Breakdown Prior'!$T$15:$T$164,'Payment Breakdown Prior'!$AE$15:$AE$164,$A13)) | Y13: =(SUMIFS('Payment Breakdown Current'!$U$15:$U$164,'Payment Breakdown Current'!$AE$15:$AE$164,$A13))-(SUMIFS('Payment Breakdown Prior'!$U$15:$U$164,'Payment Breakdown Prior'!$AE$15:$AE$164,$A13)) | Z13: =(SUMIFS('Payment Breakdown Current'!$V$15:$V$164,'Payment Breakdown Current'!$AE$15:$AE$164,$A13))-(SUMIFS('Payment Breakdown Prior'!$V$15:$V$164,'Payment Breakdown Prior'!$AE$15:$AE$164,$A13)) | AA13: =(SUMIFS('Payment Breakdown Current'!$W$15:$W$164,'Payment Breakdown Current'!$AE$15:$AE$164,$A13))-(SUMIFS('Payment Breakdown Prior'!$W$15:$W$164,'Payment Breakdown Prior'!$AE$15:$AE$164,$A13)) | AB13: =(SUMIFS('Payment Breakdown Current'!$X$15:$X$164,'Payment Breakdown Current'!$AE$15:$AE$164,$A13))-(SUMIFS('Payment Breakdown Prior'!$X$15:$X$164,'Payment Breakdown Prior'!$AE$15:$AE$164,$A13)) | AC13: =(SUMIFS('Payment Breakdown Current'!$Y$15:$Y$164,'Payment Breakdown Current'!$AE$15:$AE$164,$A13))-(SUMIFS('Payment Breakdown Prior'!$Y$15:$Y$164,'Payment Breakdown Prior'!$AE$15:$AE$164,$A13)) | AD13: =(SUMIFS('Payment Breakdown Current'!$Z$15:$Z$164,'Payment Breakdown Current'!$AE$15:$AE$164,$A13))-(SUMIFS('Payment Breakdown Prior'!$Z$15:$Z$164,'Payment Breakdown Prior'!$AE$15:$AE$164,$A13)) | AE13: =(SUMIFS('Payment Breakdown Current'!$AA$15:$AA$164,'Payment Breakdown Current'!$AE$15:$AE$164,$A13))-(SUMIFS('Payment Breakdown Prior'!$AA$15:$AA$164,'Payment Breakdown Prior'!$AE$15:$AE$164,$A13)) | AF13: =(SUMIFS('Payment Breakdown Current'!$AB$15:$AB$164,'Payment Breakdown Current'!$AE$15:$AE$164,$A13))-(SUMIFS('Payment Breakdown Prior'!$AB$15:$AB$164,'Payment Breakdown Prior'!$AE$15:$AE$164,$A13)) | AG13: =(SUMIFS('Payment Breakdown Current'!$AC$15:$AC$164,'Payment Breakdown Current'!$AE$15:$AE$164,$A13))-(SUMIFS('Payment Breakdown Prior'!$AC$15:$AC$164,'Payment Breakdown Prior'!$AE$15:$AE$164,$A13)) | AH13: =(SUMIFS('Payment Breakdown Current'!$AD$15:$AD$164,'Payment Breakdown Current'!$AE$15:$AE$164,$A13))-(SUMIFS('Payment Breakdown Prior'!$AD$15:$AD$164,'Payment Breakdown Prior'!$AE$15:$AE$164,$A13)) | AI13: {=MAX(ABS(W13:AH13))} | AJ13: {=IF(AI13<0.005,"",IFERROR(INDEX($W$1:$AH$1,MATCH(AI13,ABS(W13:AH13),0)),""))} | AK13: {=IF(AI13<0.005,"",IFERROR(INDEX(W13:AH13,MATCH(AI13,ABS(W13:AH13),0)),""))} | AL13: =IF(R13=1,ABS(L13)-ROW()/100000000,"")
... A151: =IF('NPV Comparison'!D164="","",'NPV Comparison'!D164) | B151: =IF('NPV Comparison'!E164="","",'NPV Comparison'!E164) | C151: =IF('NPV Comparison'!F164="","",'NPV Comparison'!F164) | D151: =IF($A151="","",IFERROR(INDEX(Structure!$E$13:$E$312,MATCH($A151,Structure!$P$13:$P$312,0)),"")) | E151: =IF($A151="",0,IF(COUNTIF(Structure!$P$13:$P$312,$A151)=0,0,IF(COUNTIFS(Structure!$P$13:$P$312,$A151,Structure!$N$13:$N$312,"<>Zero Hours")=0,1,0))) | F151: =IF($A151="",0,1-E151) | G151: =IF($A151="",0,IF(COUNTIF('New Starters'!$D$14:$D$73,$A151)>0,1,0)) | H151: =IF($A151="",0,IF(COUNTIF('Leavers'!$D$12:$D$71,$A151)>0,1,0)) | I151: =IF($A151="","",IFERROR(INDEX('New Starters'!$K$14:$K$73,MATCH($A151,'New Starters'!$D$14:$D$73,0)),IFERROR(INDEX('Leavers'!$K$12:$K$71,MATCH($A151,'Leavers'!$D$12:$D$71,0)),""))) | J151: =IF(AND(G151=1,I151<>"",COUNTIF('Leavers'!$K$12:$K$71,I151)>0),1,IF(AND(H151=1,I151<>"",COUNTIF('New Starters'!$K$14:$K$73,I151)>0),1,0)) | K151: =IF(ISNUMBER(SEARCH("Head Office",D151)),'Control Sheet'!$C$6,'Control Sheet'!$C$5) | L151: =IF(OR($A151="",AND(B151="",C151="")),"",IF(B151="",C151,IF(C151="",-B151,C151-B151))) | M151: =IFERROR(L151/B151,"") | N151: =IF($A151="",0,IF(OR(B151="",C151="",C151=0,AND(ISNUMBER(M151),ABS(M151)>K151)),1,0)) | O151: =IF(AND(N151=1,ABS(L151)>='Control Sheet'!$C$7,F151=1),1,0) | P151: =IF($A151="","",IF(F151=0,"Zero Hours",IF(J151=1,"Explained: Paired transfer",IF(AND(G151=1,H151=0,J151=0),"Explained: Starter",IF(AND(H151=1,G151=0,J151=0),"Explained: Leaver",IF(O151=1,"Review required","OK")))))) | Q151: =IF(AND(F151=1,OR(C151="",C151=0),H151=0,J151=0),1,0) | R151: =IF(F151=0,0,IF(P151="Review required",1,IF(AND(P151="Explained: Starter",ISNUMBER(C151),C151>=1500),1,0))) | S151: =IF(R151=0,"",IF(Q151=1,"High",IF(AND(P151="Explained: Starter",C151>=1500),"High",IF(ABS(L151)>=2000,"High",IF(ABS(L151)>=500,"Medium","Low"))))) | T151: =SUMIFS('Payment Breakdown Prior'!$S$15:$S$164,'Payment Breakdown Prior'!$AE$15:$AE$164,$A151) | U151: =SUMIFS('Payment Breakdown Current'!$S$15:$S$164,'Payment Breakdown Current'!$AE$15:$AE$164,$A151) | V151: =IFERROR((U151-T151)/T151,"") | W151: =(SUMIFS('Payment Breakdown Current'!$S$15:$S$164,'Payment Breakdown Current'!$AE$15:$AE$164,$A151))-(SUMIFS('Payment Breakdown Prior'!$S$15:$S$164,'Payment Breakdown Prior'!$AE$15:$AE$164,$A151)) | X151: =(SUMIFS('Payment Breakdown Current'!$T$15:$T$164,'Payment Breakdown Current'!$AE$15:$AE$164,$A151))-(SUMIFS('Payment Breakdown Prior'!$T$15:$T$164,'Payment Breakdown Prior'!$AE$15:$AE$164,$A151)) | Y151: =(SUMIFS('Payment Breakdown Current'!$U$15:$U$164,'Payment Breakdown Current'!$AE$15:$AE$164,$A151))-(SUMIFS('Payment Breakdown Prior'!$U$15:$U$164,'Payment Breakdown Prior'!$AE$15:$AE$164,$A151)) | Z151: =(SUMIFS('Payment Breakdown Current'!$V$15:$V$164,'Payment Breakdown Current'!$AE$15:$AE$164,$A151))-(SUMIFS('Payment Breakdown Prior'!$V$15:$V$164,'Payment Breakdown Prior'!$AE$15:$AE$164,$A151)) | AA151: =(SUMIFS('Payment Breakdown Current'!$W$15:$W$164,'Payment Breakdown Current'!$AE$15:$AE$164,$A151))-(SUMIFS('Payment Breakdown Prior'!$W$15:$W$164,'Payment Breakdown Prior'!$AE$15:$AE$164,$A151)) | AB151: =(SUMIFS('Payment Breakdown Current'!$X$15:$X$164,'Payment Breakdown Current'!$AE$15:$AE$164,$A151))-(SUMIFS('Payment Breakdown Prior'!$X$15:$X$164,'Payment Breakdown Prior'!$AE$15:$AE$164,$A151)) | AC151: =(SUMIFS('Payment Breakdown Current'!$Y$15:$Y$164,'Payment Breakdown Current'!$AE$15:$AE$164,$A151))-(SUMIFS('Payment Breakdown Prior'!$Y$15:$Y$164,'Payment Breakdown Prior'!$AE$15:$AE$164,$A151)) | AD151: =(SUMIFS('Payment Breakdown Current'!$Z$15:$Z$164,'Payment Breakdown Current'!$AE$15:$AE$164,$A151))-(SUMIFS('Payment Breakdown Prior'!$Z$15:$Z$164,'Payment Breakdown Prior'!$AE$15:$AE$164,$A151)) | AE151: =(SUMIFS('Payment Breakdown Current'!$AA$15:$AA$164,'Payment Breakdown Current'!$AE$15:$AE$164,$A151))-(SUMIFS('Payment Breakdown Prior'!$AA$15:$AA$164,'Payment Breakdown Prior'!$AE$15:$AE$164,$A151)) | AF151: =(SUMIFS('Payment Breakdown Current'!$AB$15:$AB$164,'Payment Breakdown Current'!$AE$15:$AE$164,$A151))-(SUMIFS('Payment Breakdown Prior'!$AB$15:$AB$164,'Payment Breakdown Prior'!$AE$15:$AE$164,$A151)) | AG151: =(SUMIFS('Payment Breakdown Current'!$AC$15:$AC$164,'Payment Breakdown Current'!$AE$15:$AE$164,$A151))-(SUMIFS('Payment Breakdown Prior'!$AC$15:$AC$164,'Payment Breakdown Prior'!$AE$15:$AE$164,$A151)) | AH151: =(SUMIFS('Payment Breakdown Current'!$AD$15:$AD$164,'Payment Breakdown Current'!$AE$15:$AE$164,$A151))-(SUMIFS('Payment Breakdown Prior'!$AD$15:$AD$164,'Payment Breakdown Prior'!$AE$15:$AE$164,$A151)) | AI151: {=MAX(ABS(W151:AH151))} | AJ151: {=IF(AI151<0.005,"",IFERROR(INDEX($W$1:$AH$1,MATCH(AI151,ABS(W151:AH151),0)),""))} | AK151: {=IF(AI151<0.005,"",IFERROR(INDEX(W151:AH151,MATCH(AI151,ABS(W151:AH151),0)),""))} | AL151: =IF(R151=1,ABS(L151)-ROW()/100000000,"")

Sheet Summary
A1: Payroll Reconciliation - Summary
B4: Key Metrics
B5: Employee count (compared) | D5: =COUNTIF(_Helpers!$F$2:$F$151,1)
B6: Movements over tolerance | D6: =SUMPRODUCT((_Helpers!$F$2:$F$151=1)*(_Helpers!$P$2:$P$151<>"OK")*(_Helpers!$P$2:$P$151<>""))
B7: Explained starters/leavers | D7: =SUMPRODUCT((_Helpers!$F$2:$F$151=1)*(LEFT(_Helpers!$P$2:$P$151,9)="Explained"))
B8: Zero hours count | D8: =COUNTIF(_Helpers!$E$2:$E$151,1)
B9: Review required count | D9: =COUNTIF(_Helpers!$R$2:$R$151,1)
B12: Top 20 review movements by £
B13: Rank | C13: Payroll Number | D13: Practice | E13: Prior Net | F13: Current Net | G13: Difference £ | H13: Difference % | I13: Status | J13: Priority | K13: Main Movement
B14: 1 | C14: =IF($J14="","",INDEX(_Helpers!$A$2:$A$151,$J14-2+1)) | D14: =IF($J14="","",INDEX(_Helpers!$D$2:$D$151,$J14-2+1)) | E14: =IF($J14="","",INDEX(_Helpers!$B$2:$B$151,$J14-2+1)) | F14: =IF($J14="","",INDEX(_Helpers!$C$2:$C$151,$J14-2+1)) | G14: =IF($J14="","",INDEX(_Helpers!$L$2:$L$151,$J14-2+1)) | H14: =IF($J14="","",INDEX(_Helpers!$M$2:$M$151,$J14-2+1)) | I14: =IF($J14="","",INDEX(_Helpers!$P$2:$P$151,$J14-2+1)) | J14: =IFERROR(MATCH(IFERROR(LARGE(_Helpers!$AL$2:$AL$151,1),""),_Helpers!$AL$2:$AL$151,0)+1,"") | K14: =IF($J14="","",INDEX(_Helpers!$S$2:$S$151,$J14-2+1)) | L14: =IF($J14="","",INDEX(_Helpers!$AJ$2:$AJ$151,$J14-2+1))
B15: 2 | C15: =IF($J15="","",INDEX(_Helpers!$A$2:$A$151,$J15-2+1)) | D15: =IF($J15="","",INDEX(_Helpers!$D$2:$D$151,$J15-2+1)) | E15: =IF($J15="","",INDEX(_Helpers!$B$2:$B$151,$J15-2+1)) | F15: =IF($J15="","",INDEX(_Helpers!$C$2:$C$151,$J15-2+1)) | G15: =IF($J15="","",INDEX(_Helpers!$L$2:$L$151,$J15-2+1)) | H15: =IF($J15="","",INDEX(_Helpers!$M$2:$M$151,$J15-2+1)) | I15: =IF($J15="","",INDEX(_Helpers!$P$2:$P$151,$J15-2+1)) | J15: =IFERROR(MATCH(IFERROR(LARGE(_Helpers!$AL$2:$AL$151,2),""),_Helpers!$AL$2:$AL$151,0)+1,"") | K15: =IF($J15="","",INDEX(_Helpers!$S$2:$S$151,$J15-2+1)) | L15: =IF($J15="","",INDEX(_Helpers!$AJ$2:$AJ$151,$J15-2+1))
B16: 3 | C16: =IF($J16="","",INDEX(_Helpers!$A$2:$A$151,$J16-2+1)) | D16: =IF($J16="","",INDEX(_Helpers!$D$2:$D$151,$J16-2+1)) | E16: =IF($J16="","",INDEX(_Helpers!$B$2:$B$151,$J16-2+1)) | F16: =IF($J16="","",INDEX(_Helpers!$C$2:$C$151,$J16-2+1)) | G16: =IF($J16="","",INDEX(_Helpers!$L$2:$L$151,$J16-2+1)) | H16: =IF($J16="","",INDEX(_Helpers!$M$2:$M$151,$J16-2+1)) | I16: =IF($J16="","",INDEX(_Helpers!$P$2:$P$151,$J16-2+1)) | J16: =IFERROR(MATCH(IFERROR(LARGE(_Helpers!$AL$2:$AL$151,3),""),_Helpers!$AL$2:$AL$151,0)+1,"") | K16: =IF($J16="","",INDEX(_Helpers!$S$2:$S$151,$J16-2+1)) | L16: =IF($J16="","",INDEX(_Helpers!$AJ$2:$AJ$151,$J16-2+1))
B17: 4 | C17: =IF($J17="","",INDEX(_Helpers!$A$2:$A$151,$J17-2+1)) | D17: =IF($J17="","",INDEX(_Helpers!$D$2:$D$151,$J17-2+1)) | E17: =IF($J17="","",INDEX(_Helpers!$B$2:$B$151,$J17-2+1)) | F17: =IF($J17="","",INDEX(_Helpers!$C$2:$C$151,$J17-2+1)) | G17: =IF($J17="","",INDEX(_Helpers!$L$2:$L$151,$J17-2+1)) | H17: =IF($J17="","",INDEX(_Helpers!$M$2:$M$151,$J17-2+1)) | I17: =IF($J17="","",INDEX(_Helpers!$P$2:$P$151,$J17-2+1)) | J17: =IFERROR(MATCH(IFERROR(LARGE(_Helpers!$AL$2:$AL$151,4),""),_Helpers!$AL$2:$AL$151,0)+1,"") | K17: =IF($J17="","",INDEX(_Helpers!$S$2:$S$151,$J17-2+1)) | L17: =IF($J17="","",INDEX(_Helpers!$AJ$2:$AJ$151,$J17-2+1))
B18: 5 | C18: =IF($J18="","",INDEX(_Helpers!$A$2:$A$151,$J18-2+1)) | D18: =IF($J18="","",INDEX(_Helpers!$D$2:$D$151,$J18-2+1)) | E18: =IF($J18="","",INDEX(_Helpers!$B$2:$B$151,$J18-2+1)) | F18: =IF($J18="","",INDEX(_Helpers!$C$2:$C$151,$J18-2+1)) | G18: =IF($J18="","",INDEX(_Helpers!$L$2:$L$151,$J18-2+1)) | H18: =IF($J18="","",INDEX(_Helpers!$M$2:$M$151,$J18-2+1)) | I18: =IF($J18="","",INDEX(_Helpers!$P$2:$P$151,$J18-2+1)) | J18: =IFERROR(MATCH(IFERROR(LARGE(_Helpers!$AL$2:$AL$151,5),""),_Helpers!$AL$2:$AL$151,0)+1,"") | K18: =IF($J18="","",INDEX(_Helpers!$S$2:$S$151,$J18-2+1)) | L18: =IF($J18="","",INDEX(_Helpers!$AJ$2:$AJ$151,$J18-2+1))
B19: 6 | C19: =IF($J19="","",INDEX(_Helpers!$A$2:$A$151,$J19-2+1)) | D19: =IF($J19="","",INDEX(_Helpers!$D$2:$D$151,$J19-2+1)) | E19: =IF($J19="","",INDEX(_Helpers!$B$2:$B$151,$J19-2+1)) | F19: =IF($J19="","",INDEX(_Helpers!$C$2:$C$151,$J19-2+1)) | G19: =IF($J19="","",INDEX(_Helpers!$L$2:$L$151,$J19-2+1)) | H19: =IF($J19="","",INDEX(_Helpers!$M$2:$M$151,$J19-2+1)) | I19: =IF($J19="","",INDEX(_Helpers!$P$2:$P$151,$J19-2+1)) | J19: =IFERROR(MATCH(IFERROR(LARGE(_Helpers!$AL$2:$AL$151,6),""),_Helpers!$AL$2:$AL$151,0)+1,"") | K19: =IF($J19="","",INDEX(_Helpers!$S$2:$S$151,$J19-2+1)) | L19: =IF($J19="","",INDEX(_Helpers!$AJ$2:$AJ$151,$J19-2+1))
B20: 7 | C20: =IF($J20="","",INDEX(_Helpers!$A$2:$A$151,$J20-2+1)) | D20: =IF($J20="","",INDEX(_Helpers!$D$2:$D$151,$J20-2+1)) | E20: =IF($J20="","",INDEX(_Helpers!$B$2:$B$151,$J20-2+1)) | F20: =IF($J20="","",INDEX(_Helpers!$C$2:$C$151,$J20-2+1)) | G20: =IF($J20="","",INDEX(_Helpers!$L$2:$L$151,$J20-2+1)) | H20: =IF($J20="","",INDEX(_Helpers!$M$2:$M$151,$J20-2+1)) | I20: =IF($J20="","",INDEX(_Helpers!$P$2:$P$151,$J20-2+1)) | J20: =IFERROR(MATCH(IFERROR(LARGE(_Helpers!$AL$2:$AL$151,7),""),_Helpers!$AL$2:$AL$151,0)+1,"") | K20: =IF($J20="","",INDEX(_Helpers!$S$2:$S$151,$J20-2+1)) | L20: =IF($J20="","",INDEX(_Helpers!$AJ$2:$AJ$151,$J20-2+1))
B21: 8 | C21: =IF($J21="","",INDEX(_Helpers!$A$2:$A$151,$J21-2+1)) | D21: =IF($J21="","",INDEX(_Helpers!$D$2:$D$151,$J21-2+1)) | E21: =IF($J21="","",INDEX(_Helpers!$B$2:$B$151,$J21-2+1)) | F21: =IF($J21="","",INDEX(_Helpers!$C$2:$C$151,$J21-2+1)) | G21: =IF($J21="","",INDEX(_Helpers!$L$2:$L$151,$J21-2+1)) | H21: =IF($J21="","",INDEX(_Helpers!$M$2:$M$151,$J21-2+1)) | I21: =IF($J21="","",INDEX(_Helpers!$P$2:$P$151,$J21-2+1)) | J21: =IFERROR(MATCH(IFERROR(LARGE(_Helpers!$AL$2:$AL$151,8),""),_Helpers!$AL$2:$AL$151,0)+1,"") | K21: =IF($J21="","",INDEX(_Helpers!$S$2:$S$151,$J21-2+1)) | L21: =IF($J21="","",INDEX(_Helpers!$AJ$2:$AJ$151,$J21-2+1))
B22: 9 | C22: =IF($J22="","",INDEX(_Helpers!$A$2:$A$151,$J22-2+1)) | D22: =IF($J22="","",INDEX(_Helpers!$D$2:$D$151,$J22-2+1)) | E22: =IF($J22="","",INDEX(_Helpers!$B$2:$B$151,$J22-2+1)) | F22: =IF($J22="","",INDEX(_Helpers!$C$2:$C$151,$J22-2+1)) | G22: =IF($J22="","",INDEX(_Helpers!$L$2:$L$151,$J22-2+1)) | H22: =IF($J22="","",INDEX(_Helpers!$M$2:$M$151,$J22-2+1)) | I22: =IF($J22="","",INDEX(_Helpers!$P$2:$P$151,$J22-2+1)) | J22: =IFERROR(MATCH(IFERROR(LARGE(_Helpers!$AL$2:$AL$151,9),""),_Helpers!$AL$2:$AL$151,0)+1,"") | K22: =IF($J22="","",INDEX(_Helpers!$S$2:$S$151,$J22-2+1)) | L22: =IF($J22="","",INDEX(_Helpers!$AJ$2:$AJ$151,$J22-2+1))
B23: 10 | C23: =IF($J23="","",INDEX(_Helpers!$A$2:$A$151,$J23-2+1)) | D23: =IF($J23="","",INDEX(_Helpers!$D$2:$D$151,$J23-2+1)) | E23: =IF($J23="","",INDEX(_Helpers!$B$2:$B$151,$J23-2+1)) | F23: =IF($J23="","",INDEX(_Helpers!$C$2:$C$151,$J23-2+1)) | G23: =IF($J23="","",INDEX(_Helpers!$L$2:$L$151,$J23-2+1)) | H23: =IF($J23="","",INDEX(_Helpers!$M$2:$M$151,$J23-2+1)) | I23: =IF($J23="","",INDEX(_Helpers!$P$2:$P$151,$J23-2+1)) | J23: =IFERROR(MATCH(IFERROR(LARGE(_Helpers!$AL$2:$AL$151,10),""),_Helpers!$AL$2:$AL$151,0)+1,"") | K23: =IF($J23="","",INDEX(_Helpers!$S$2:$S$151,$J23-2+1)) | L23: =IF($J23="","",INDEX(_Helpers!$AJ$2:$AJ$151,$J23-2+1))
B24: 11 | C24: =IF($J24="","",INDEX(_Helpers!$A$2:$A$151,$J24-2+1)) | D24: =IF($J24="","",INDEX(_Helpers!$D$2:$D$151,$J24-2+1)) | E24: =IF($J24="","",INDEX(_Helpers!$B$2:$B$151,$J24-2+1)) | F24: =IF($J24="","",INDEX(_Helpers!$C$2:$C$151,$J24-2+1)) | G24: =IF($J24="","",INDEX(_Helpers!$L$2:$L$151,$J24-2+1)) | H24: =IF($J24="","",INDEX(_Helpers!$M$2:$M$151,$J24-2+1)) | I24: =IF($J24="","",INDEX(_Helpers!$P$2:$P$151,$J24-2+1)) | J24: =IFERROR(MATCH(IFERROR(LARGE(_Helpers!$AL$2:$AL$151,11),""),_Helpers!$AL$2:$AL$151,0)+1,"") | K24: =IF($J24="","",INDEX(_Helpers!$S$2:$S$151,$J24-2+1)) | L24: =IF($J24="","",INDEX(_Helpers!$AJ$2:$AJ$151,$J24-2+1))
B25: 12 | C25: =IF($J25="","",INDEX(_Helpers!$A$2:$A$151,$J25-2+1)) | D25: =IF($J25="","",INDEX(_Helpers!$D$2:$D$151,$J25-2+1)) | E25: =IF($J25="","",INDEX(_Helpers!$B$2:$B$151,$J25-2+1)) | F25: =IF($J25="","",INDEX(_Helpers!$C$2:$C$151,$J25-2+1)) | G25: =IF($J25="","",INDEX(_Helpers!$L$2:$L$151,$J25-2+1)) | H25: =IF($J25="","",INDEX(_Helpers!$M$2:$M$151,$J25-2+1)) | I25: =IF($J25="","",INDEX(_Helpers!$P$2:$P$151,$J25-2+1)) | J25: =IFERROR(MATCH(IFERROR(LARGE(_Helpers!$AL$2:$AL$151,12),""),_Helpers!$AL$2:$AL$151,0)+1,"") | K25: =IF($J25="","",INDEX(_Helpers!$S$2:$S$151,$J25-2+1)) | L25: =IF($J25="","",INDEX(_Helpers!$AJ$2:$AJ$151,$J25-2+1))
B26: 13 | C26: =IF($J26="","",INDEX(_Helpers!$A$2:$A$151,$J26-2+1)) | D26: =IF($J26="","",INDEX(_Helpers!$D$2:$D$151,$J26-2+1)) | E26: =IF($J26="","",INDEX(_Helpers!$B$2:$B$151,$J26-2+1)) | F26: =IF($J26="","",INDEX(_Helpers!$C$2:$C$151,$J26-2+1)) | G26: =IF($J26="","",INDEX(_Helpers!$L$2:$L$151,$J26-2+1)) | H26: =IF($J26="","",INDEX(_Helpers!$M$2:$M$151,$J26-2+1)) | I26: =IF($J26="","",INDEX(_Helpers!$P$2:$P$151,$J26-2+1)) | J26: =IFERROR(MATCH(IFERROR(LARGE(_Helpers!$AL$2:$AL$151,13),""),_Helpers!$AL$2:$AL$151,0)+1,"") | K26: =IF($J26="","",INDEX(_Helpers!$S$2:$S$151,$J26-2+1)) | L26: =IF($J26="","",INDEX(_Helpers!$AJ$2:$AJ$151,$J26-2+1))
B27: 14 | C27: =IF($J27="","",INDEX(_Helpers!$A$2:$A$151,$J27-2+1)) | D27: =IF($J27="","",INDEX(_Helpers!$D$2:$D$151,$J27-2+1)) | E27: =IF($J27="","",INDEX(_Helpers!$B$2:$B$151,$J27-2+1)) | F27: =IF($J27="","",INDEX(_Helpers!$C$2:$C$151,$J27-2+1)) | G27: =IF($J27="","",INDEX(_Helpers!$L$2:$L$151,$J27-2+1)) | H27: =IF($J27="","",INDEX(_Helpers!$M$2:$M$151,$J27-2+1)) | I27: =IF($J27="","",INDEX(_Helpers!$P$2:$P$151,$J27-2+1)) | J27: =IFERROR(MATCH(IFERROR(LARGE(_Helpers!$AL$2:$AL$151,14),""),_Helpers!$AL$2:$AL$151,0)+1,"") | K27: =IF($J27="","",INDEX(_Helpers!$S$2:$S$151,$J27-2+1)) | L27: =IF($J27="","",INDEX(_Helpers!$AJ$2:$AJ$151,$J27-2+1))
B28: 15 | C28: =IF($J28="","",INDEX(_Helpers!$A$2:$A$151,$J28-2+1)) | D28: =IF($J28="","",INDEX(_Helpers!$D$2:$D$151,$J28-2+1)) | E28: =IF($J28="","",INDEX(_Helpers!$B$2:$B$151,$J28-2+1)) | F28: =IF($J28="","",INDEX(_Helpers!$C$2:$C$151,$J28-2+1)) | G28: =IF($J28="","",INDEX(_Helpers!$L$2:$L$151,$J28-2+1)) | H28: =IF($J28="","",INDEX(_Helpers!$M$2:$M$151,$J28-2+1)) | I28: =IF($J28="","",INDEX(_Helpers!$P$2:$P$151,$J28-2+1)) | J28: =IFERROR(MATCH(IFERROR(LARGE(_Helpers!$AL$2:$AL$151,15),""),_Helpers!$AL$2:$AL$151,0)+1,"") | K28: =IF($J28="","",INDEX(_Helpers!$S$2:$S$151,$J28-2+1)) | L28: =IF($J28="","",INDEX(_Helpers!$AJ$2:$AJ$151,$J28-2+1))
B29: 16 | C29: =IF($J29="","",INDEX(_Helpers!$A$2:$A$151,$J29-2+1)) | D29: =IF($J29="","",INDEX(_Helpers!$D$2:$D$151,$J29-2+1)) | E29: =IF($J29="","",INDEX(_Helpers!$B$2:$B$151,$J29-2+1)) | F29: =IF($J29="","",INDEX(_Helpers!$C$2:$C$151,$J29-2+1)) | G29: =IF($J29="","",INDEX(_Helpers!$L$2:$L$151,$J29-2+1)) | H29: =IF($J29="","",INDEX(_Helpers!$M$2:$M$151,$J29-2+1)) | I29: =IF($J29="","",INDEX(_Helpers!$P$2:$P$151,$J29-2+1)) | J29: =IFERROR(MATCH(IFERROR(LARGE(_Helpers!$AL$2:$AL$151,16),""),_Helpers!$AL$2:$AL$151,0)+1,"") | K29: =IF($J29="","",INDEX(_Helpers!$S$2:$S$151,$J29-2+1)) | L29: =IF($J29="","",INDEX(_Helpers!$AJ$2:$AJ$151,$J29-2+1))
B30: 17 | C30: =IF($J30="","",INDEX(_Helpers!$A$2:$A$151,$J30-2+1)) | D30: =IF($J30="","",INDEX(_Helpers!$D$2:$D$151,$J30-2+1)) | E30: =IF($J30="","",INDEX(_Helpers!$B$2:$B$151,$J30-2+1)) | F30: =IF($J30="","",INDEX(_Helpers!$C$2:$C$151,$J30-2+1)) | G30: =IF($J30="","",INDEX(_Helpers!$L$2:$L$151,$J30-2+1)) | H30: =IF($J30="","",INDEX(_Helpers!$M$2:$M$151,$J30-2+1)) | I30: =IF($J30="","",INDEX(_Helpers!$P$2:$P$151,$J30-2+1)) | J30: =IFERROR(MATCH(IFERROR(LARGE(_Helpers!$AL$2:$AL$151,17),""),_Helpers!$AL$2:$AL$151,0)+1,"") | K30: =IF($J30="","",INDEX(_Helpers!$S$2:$S$151,$J30-2+1)) | L30: =IF($J30="","",INDEX(_Helpers!$AJ$2:$AJ$151,$J30-2+1))
B31: 18 | C31: =IF($J31="","",INDEX(_Helpers!$A$2:$A$151,$J31-2+1)) | D31: =IF($J31="","",INDEX(_Helpers!$D$2:$D$151,$J31-2+1)) | E31: =IF($J31="","",INDEX(_Helpers!$B$2:$B$151,$J31-2+1)) | F31: =IF($J31="","",INDEX(_Helpers!$C$2:$C$151,$J31-2+1)) | G31: =IF($J31="","",INDEX(_Helpers!$L$2:$L$151,$J31-2+1)) | H31: =IF($J31="","",INDEX(_Helpers!$M$2:$M$151,$J31-2+1)) | I31: =IF($J31="","",INDEX(_Helpers!$P$2:$P$151,$J31-2+1)) | J31: =IFERROR(MATCH(IFERROR(LARGE(_Helpers!$AL$2:$AL$151,18),""),_Helpers!$AL$2:$AL$151,0)+1,"") | K31: =IF($J31="","",INDEX(_Helpers!$S$2:$S$151,$J31-2+1)) | L31: =IF($J31="","",INDEX(_Helpers!$AJ$2:$AJ$151,$J31-2+1))
B32: 19 | C32: =IF($J32="","",INDEX(_Helpers!$A$2:$A$151,$J32-2+1)) | D32: =IF($J32="","",INDEX(_Helpers!$D$2:$D$151,$J32-2+1)) | E32: =IF($J32="","",INDEX(_Helpers!$B$2:$B$151,$J32-2+1)) | F32: =IF($J32="","",INDEX(_Helpers!$C$2:$C$151,$J32-2+1)) | G32: =IF($J32="","",INDEX(_Helpers!$L$2:$L$151,$J32-2+1)) | H32: =IF($J32="","",INDEX(_Helpers!$M$2:$M$151,$J32-2+1)) | I32: =IF($J32="","",INDEX(_Helpers!$P$2:$P$151,$J32-2+1)) | J32: =IFERROR(MATCH(IFERROR(LARGE(_Helpers!$AL$2:$AL$151,19),""),_Helpers!$AL$2:$AL$151,0)+1,"") | K32: =IF($J32="","",INDEX(_Helpers!$S$2:$S$151,$J32-2+1)) | L32: =IF($J32="","",INDEX(_Helpers!$AJ$2:$AJ$151,$J32-2+1))
B33: 20 | C33: =IF($J33="","",INDEX(_Helpers!$A$2:$A$151,$J33-2+1)) | D33: =IF($J33="","",INDEX(_Helpers!$D$2:$D$151,$J33-2+1)) | E33: =IF($J33="","",INDEX(_Helpers!$B$2:$B$151,$J33-2+1)) | F33: =IF($J33="","",INDEX(_Helpers!$C$2:$C$151,$J33-2+1)) | G33: =IF($J33="","",INDEX(_Helpers!$L$2:$L$151,$J33-2+1)) | H33: =IF($J33="","",INDEX(_Helpers!$M$2:$M$151,$J33-2+1)) | I33: =IF($J33="","",INDEX(_Helpers!$P$2:$P$151,$J33-2+1)) | J33: =IFERROR(MATCH(IFERROR(LARGE(_Helpers!$AL$2:$AL$151,20),""),_Helpers!$AL$2:$AL$151,0)+1,"") | K33: =IF($J33="","",INDEX(_Helpers!$S$2:$S$151,$J33-2+1)) | L33: =IF($J33="","",INDEX(_Helpers!$AJ$2:$AJ$151,$J33-2+1))
B36: Totals reconciliation
B37: Figure | C37: Prior | D37: Current | E37: Difference
B38: Net Pay | C38: =SUM('NPV Comparison'!$E$15:$E$164) | D38: =SUM('NPV Comparison'!$F$15:$F$164) | E38: =D38-C38
B39: Total Gross | C39: =SUM('Payment Breakdown Prior'!$K$15:$K$164) | D39: =SUM('Payment Breakdown Current'!$K$15:$K$164) | E39: =D39-C39
B40: Employer NI | C40: =SUM('Payment Breakdown Prior'!$P$15:$P$164) | D40: =SUM('Payment Breakdown Current'!$P$15:$P$164) | E40: =D40-C40
B41: Employer Pension | C41: =SUM('Payment Breakdown Prior'!$Q$15:$Q$164) | D41: =SUM('Payment Breakdown Current'!$Q$15:$Q$164) | E41: =D41-C41
B42: Apprenticeship Levy | C42: =SUM('Payment Breakdown Prior'!$R$15:$R$164) | D42: =SUM('Payment Breakdown Current'!$R$15:$R$164) | E42: =D42-C42
B44: Note: agree Net Pay above to BACS. Agree Total Gross / Employer NI / Employer Pension / Apprenticeship Levy to the payroll submissions (FPS/EPS).
B47: Headcount reconciliation
B48: Prior records | D48: =COUNT('NPV Comparison'!$E$15:$E$164)
B49: + Starters | D49: =COUNTA('New Starters'!$D$14:$D$73)
B50: - Leavers | D50: =COUNTA('Leavers'!$D$12:$D$71)
B51: =Expected current records | D51: =D48+D49-D50
B52: Actual current records | D52: =COUNT('NPV Comparison'!$F$15:$F$164)
B53: Check | D53: =IF(D51=D52,"Reconciled","Check required")

Sheet Exceptions
A1: Exceptions - Net Pay Movements
A2: Zero-hours-only staff are excluded here - see the Zero Hours tab. Gold 'Notes' cells are the only cells to type into.
A3: Payroll Number | B3: Practice | C3: Prior Net | D3: Current Net | E3: Difference £ | F3: Difference % | G3: Starter? | H3: Leaver? | I3: Status | J3: Basic Salary % Change | K3: Main Movement (Element) | L3: Main Movement (£) | M3: Notes | O3: Helper: rank pointer
A4: =IF($O4="","",INDEX(_Helpers!$A$2:$A$151,$O4-2+1)) | B4: =IF($O4="","",INDEX(_Helpers!$D$2:$D$151,$O4-2+1)) | C4: =IF($O4="","",INDEX(_Helpers!$B$2:$B$151,$O4-2+1)) | D4: =IF($O4="","",INDEX(_Helpers!$C$2:$C$151,$O4-2+1)) | E4: =IF($O4="","",INDEX(_Helpers!$L$2:$L$151,$O4-2+1)) | F4: =IF($O4="","",INDEX(_Helpers!$M$2:$M$151,$O4-2+1)) | G4: =IF($O4="","",IF(INDEX(_Helpers!$G$2:$G$151,$O4-2+1)=1,"Starter","")) | H4: =IF($O4="","",IF(INDEX(_Helpers!$H$2:$H$151,$O4-2+1)=1,"Leaver","")) | I4: =IF($O4="","",INDEX(_Helpers!$P$2:$P$151,$O4-2+1)) | J4: =IF($O4="","",INDEX(_Helpers!$V$2:$V$151,$O4-2+1)) | K4: =IF($O4="","",INDEX(_Helpers!$AJ$2:$AJ$151,$O4-2+1)) | L4: =IF($O4="","",INDEX(_Helpers!$AK$2:$AK$151,$O4-2+1)) | O4: {=IFERROR(SMALL(IF(_Helpers!$F$2:$F$151=1,ROW(_Helpers!$F$2:$F$151)),ROWS($A$4:A4)),"")}
A5: =IF($O5="","",INDEX(_Helpers!$A$2:$A$151,$O5-2+1)) | B5: =IF($O5="","",INDEX(_Helpers!$D$2:$D$151,$O5-2+1)) | C5: =IF($O5="","",INDEX(_Helpers!$B$2:$B$151,$O5-2+1)) | D5: =IF($O5="","",INDEX(_Helpers!$C$2:$C$151,$O5-2+1)) | E5: =IF($O5="","",INDEX(_Helpers!$L$2:$L$151,$O5-2+1)) | F5: =IF($O5="","",INDEX(_Helpers!$M$2:$M$151,$O5-2+1)) | G5: =IF($O5="","",IF(INDEX(_Helpers!$G$2:$G$151,$O5-2+1)=1,"Starter","")) | H5: =IF($O5="","",IF(INDEX(_Helpers!$H$2:$H$151,$O5-2+1)=1,"Leaver","")) | I5: =IF($O5="","",INDEX(_Helpers!$P$2:$P$151,$O5-2+1)) | J5: =IF($O5="","",INDEX(_Helpers!$V$2:$V$151,$O5-2+1)) | K5: =IF($O5="","",INDEX(_Helpers!$AJ$2:$AJ$151,$O5-2+1)) | L5: =IF($O5="","",INDEX(_Helpers!$AK$2:$AK$151,$O5-2+1)) | O5: {=IFERROR(SMALL(IF(_Helpers!$F$2:$F$151=1,ROW(_Helpers!$F$2:$F$151)),ROWS($A$4:A5)),"")}
A6: =IF($O6="","",INDEX(_Helpers!$A$2:$A$151,$O6-2+1)) | B6: =IF($O6="","",INDEX(_Helpers!$D$2:$D$151,$O6-2+1)) | C6: =IF($O6="","",INDEX(_Helpers!$B$2:$B$151,$O6-2+1)) | D6: =IF($O6="","",INDEX(_Helpers!$C$2:$C$151,$O6-2+1)) | E6: =IF($O6="","",INDEX(_Helpers!$L$2:$L$151,$O6-2+1)) | F6: =IF($O6="","",INDEX(_Helpers!$M$2:$M$151,$O6-2+1)) | G6: =IF($O6="","",IF(INDEX(_Helpers!$G$2:$G$151,$O6-2+1)=1,"Starter","")) | H6: =IF($O6="","",IF(INDEX(_Helpers!$H$2:$H$151,$O6-2+1)=1,"Leaver","")) | I6: =IF($O6="","",INDEX(_Helpers!$P$2:$P$151,$O6-2+1)) | J6: =IF($O6="","",INDEX(_Helpers!$V$2:$V$151,$O6-2+1)) | K6: =IF($O6="","",INDEX(_Helpers!$AJ$2:$AJ$151,$O6-2+1)) | L6: =IF($O6="","",INDEX(_Helpers!$AK$2:$AK$151,$O6-2+1)) | O6: {=IFERROR(SMALL(IF(_Helpers!$F$2:$F$151=1,ROW(_Helpers!$F$2:$F$151)),ROWS($A$4:A6)),"")}
A7: =IF($O7="","",INDEX(_Helpers!$A$2:$A$151,$O7-2+1)) | B7: =IF($O7="","",INDEX(_Helpers!$D$2:$D$151,$O7-2+1)) | C7: =IF($O7="","",INDEX(_Helpers!$B$2:$B$151,$O7-2+1)) | D7: =IF($O7="","",INDEX(_Helpers!$C$2:$C$151,$O7-2+1)) | E7: =IF($O7="","",INDEX(_Helpers!$L$2:$L$151,$O7-2+1)) | F7: =IF($O7="","",INDEX(_Helpers!$M$2:$M$151,$O7-2+1)) | G7: =IF($O7="","",IF(INDEX(_Helpers!$G$2:$G$151,$O7-2+1)=1,"Starter","")) | H7: =IF($O7="","",IF(INDEX(_Helpers!$H$2:$H$151,$O7-2+1)=1,"Leaver","")) | I7: =IF($O7="","",INDEX(_Helpers!$P$2:$P$151,$O7-2+1)) | J7: =IF($O7="","",INDEX(_Helpers!$V$2:$V$151,$O7-2+1)) | K7: =IF($O7="","",INDEX(_Helpers!$AJ$2:$AJ$151,$O7-2+1)) | L7: =IF($O7="","",INDEX(_Helpers!$AK$2:$AK$151,$O7-2+1)) | O7: {=IFERROR(SMALL(IF(_Helpers!$F$2:$F$151=1,ROW(_Helpers!$F$2:$F$151)),ROWS($A$4:A7)),"")}
A8: =IF($O8="","",INDEX(_Helpers!$A$2:$A$151,$O8-2+1)) | B8: =IF($O8="","",INDEX(_Helpers!$D$2:$D$151,$O8-2+1)) | C8: =IF($O8="","",INDEX(_Helpers!$B$2:$B$151,$O8-2+1)) | D8: =IF($O8="","",INDEX(_Helpers!$C$2:$C$151,$O8-2+1)) | E8: =IF($O8="","",INDEX(_Helpers!$L$2:$L$151,$O8-2+1)) | F8: =IF($O8="","",INDEX(_Helpers!$M$2:$M$151,$O8-2+1)) | G8: =IF($O8="","",IF(INDEX(_Helpers!$G$2:$G$151,$O8-2+1)=1,"Starter","")) | H8: =IF($O8="","",IF(INDEX(_Helpers!$H$2:$H$151,$O8-2+1)=1,"Leaver","")) | I8: =IF($O8="","",INDEX(_Helpers!$P$2:$P$151,$O8-2+1)) | J8: =IF($O8="","",INDEX(_Helpers!$V$2:$V$151,$O8-2+1)) | K8: =IF($O8="","",INDEX(_Helpers!$AJ$2:$AJ$151,$O8-2+1)) | L8: =IF($O8="","",INDEX(_Helpers!$AK$2:$AK$151,$O8-2+1)) | O8: {=IFERROR(SMALL(IF(_Helpers!$F$2:$F$151=1,ROW(_Helpers!$F$2:$F$151)),ROWS($A$4:A8)),"")}
A9: =IF($O9="","",INDEX(_Helpers!$A$2:$A$151,$O9-2+1)) | B9: =IF($O9="","",INDEX(_Helpers!$D$2:$D$151,$O9-2+1)) | C9: =IF($O9="","",INDEX(_Helpers!$B$2:$B$151,$O9-2+1)) | D9: =IF($O9="","",INDEX(_Helpers!$C$2:$C$151,$O9-2+1)) | E9: =IF($O9="","",INDEX(_Helpers!$L$2:$L$151,$O9-2+1)) | F9: =IF($O9="","",INDEX(_Helpers!$M$2:$M$151,$O9-2+1)) | G9: =IF($O9="","",IF(INDEX(_Helpers!$G$2:$G$151,$O9-2+1)=1,"Starter","")) | H9: =IF($O9="","",IF(INDEX(_Helpers!$H$2:$H$151,$O9-2+1)=1,"Leaver","")) | I9: =IF($O9="","",INDEX(_Helpers!$P$2:$P$151,$O9-2+1)) | J9: =IF($O9="","",INDEX(_Helpers!$V$2:$V$151,$O9-2+1)) | K9: =IF($O9="","",INDEX(_Helpers!$AJ$2:$AJ$151,$O9-2+1)) | L9: =IF($O9="","",INDEX(_Helpers!$AK$2:$AK$151,$O9-2+1)) | O9: {=IFERROR(SMALL(IF(_Helpers!$F$2:$F$151=1,ROW(_Helpers!$F$2:$F$151)),ROWS($A$4:A9)),"")}
A10: =IF($O10="","",INDEX(_Helpers!$A$2:$A$151,$O10-2+1)) | B10: =IF($O10="","",INDEX(_Helpers!$D$2:$D$151,$O10-2+1)) | C10: =IF($O10="","",INDEX(_Helpers!$B$2:$B$151,$O10-2+1)) | D10: =IF($O10="","",INDEX(_Helpers!$C$2:$C$151,$O10-2+1)) | E10: =IF($O10="","",INDEX(_Helpers!$L$2:$L$151,$O10-2+1)) | F10: =IF($O10="","",INDEX(_Helpers!$M$2:$M$151,$O10-2+1)) | G10: =IF($O10="","",IF(INDEX(_Helpers!$G$2:$G$151,$O10-2+1)=1,"Starter","")) | H10: =IF($O10="","",IF(INDEX(_Helpers!$H$2:$H$151,$O10-2+1)=1,"Leaver","")) | I10: =IF($O10="","",INDEX(_Helpers!$P$2:$P$151,$O10-2+1)) | J10: =IF($O10="","",INDEX(_Helpers!$V$2:$V$151,$O10-2+1)) | K10: =IF($O10="","",INDEX(_Helpers!$AJ$2:$AJ$151,$O10-2+1)) | L10: =IF($O10="","",INDEX(_Helpers!$AK$2:$AK$151,$O10-2+1)) | O10: {=IFERROR(SMALL(IF(_Helpers!$F$2:$F$151=1,ROW(_Helpers!$F$2:$F$151)),ROWS($A$4:A10)),"")}
A11: =IF($O11="","",INDEX(_Helpers!$A$2:$A$151,$O11-2+1)) | B11: =IF($O11="","",INDEX(_Helpers!$D$2:$D$151,$O11-2+1)) | C11: =IF($O11="","",INDEX(_Helpers!$B$2:$B$151,$O11-2+1)) | D11: =IF($O11="","",INDEX(_Helpers!$C$2:$C$151,$O11-2+1)) | E11: =IF($O11="","",INDEX(_Helpers!$L$2:$L$151,$O11-2+1)) | F11: =IF($O11="","",INDEX(_Helpers!$M$2:$M$151,$O11-2+1)) | G11: =IF($O11="","",IF(INDEX(_Helpers!$G$2:$G$151,$O11-2+1)=1,"Starter","")) | H11: =IF($O11="","",IF(INDEX(_Helpers!$H$2:$H$151,$O11-2+1)=1,"Leaver","")) | I11: =IF($O11="","",INDEX(_Helpers!$P$2:$P$151,$O11-2+1)) | J11: =IF($O11="","",INDEX(_Helpers!$V$2:$V$151,$O11-2+1)) | K11: =IF($O11="","",INDEX(_Helpers!$AJ$2:$AJ$151,$O11-2+1)) | L11: =IF($O11="","",INDEX(_Helpers!$AK$2:$AK$151,$O11-2+1)) | O11: {=IFERROR(SMALL(IF(_Helpers!$F$2:$F$151=1,ROW(_Helpers!$F$2:$F$151)),ROWS($A$4:A11)),"")}
A12: =IF($O12="","",INDEX(_Helpers!$A$2:$A$151,$O12-2+1)) | B12: =IF($O12="","",INDEX(_Helpers!$D$2:$D$151,$O12-2+1)) | C12: =IF($O12="","",INDEX(_Helpers!$B$2:$B$151,$O12-2+1)) | D12: =IF($O12="","",INDEX(_Helpers!$C$2:$C$151,$O12-2+1)) | E12: =IF($O12="","",INDEX(_Helpers!$L$2:$L$151,$O12-2+1)) | F12: =IF($O12="","",INDEX(_Helpers!$M$2:$M$151,$O12-2+1)) | G12: =IF($O12="","",IF(INDEX(_Helpers!$G$2:$G$151,$O12-2+1)=1,"Starter","")) | H12: =IF($O12="","",IF(INDEX(_Helpers!$H$2:$H$151,$O12-2+1)=1,"Leaver","")) | I12: =IF($O12="","",INDEX(_Helpers!$P$2:$P$151,$O12-2+1)) | J12: =IF($O12="","",INDEX(_Helpers!$V$2:$V$151,$O12-2+1)) | K12: =IF($O12="","",INDEX(_Helpers!$AJ$2:$AJ$151,$O12-2+1)) | L12: =IF($O12="","",INDEX(_Helpers!$AK$2:$AK$151,$O12-2+1)) | O12: {=IFERROR(SMALL(IF(_Helpers!$F$2:$F$151=1,ROW(_Helpers!$F$2:$F$151)),ROWS($A$4:A12)),"")}
A13: =IF($O13="","",INDEX(_Helpers!$A$2:$A$151,$O13-2+1)) | B13: =IF($O13="","",INDEX(_Helpers!$D$2:$D$151,$O13-2+1)) | C13: =IF($O13="","",INDEX(_Helpers!$B$2:$B$151,$O13-2+1)) | D13: =IF($O13="","",INDEX(_Helpers!$C$2:$C$151,$O13-2+1)) | E13: =IF($O13="","",INDEX(_Helpers!$L$2:$L$151,$O13-2+1)) | F13: =IF($O13="","",INDEX(_Helpers!$M$2:$M$151,$O13-2+1)) | G13: =IF($O13="","",IF(INDEX(_Helpers!$G$2:$G$151,$O13-2+1)=1,"Starter","")) | H13: =IF($O13="","",IF(INDEX(_Helpers!$H$2:$H$151,$O13-2+1)=1,"Leaver","")) | I13: =IF($O13="","",INDEX(_Helpers!$P$2:$P$151,$O13-2+1)) | J13: =IF($O13="","",INDEX(_Helpers!$V$2:$V$151,$O13-2+1)) | K13: =IF($O13="","",INDEX(_Helpers!$AJ$2:$AJ$151,$O13-2+1)) | L13: =IF($O13="","",INDEX(_Helpers!$AK$2:$AK$151,$O13-2+1)) | O13: {=IFERROR(SMALL(IF(_Helpers!$F$2:$F$151=1,ROW(_Helpers!$F$2:$F$151)),ROWS($A$4:A13)),"")}
A14: =IF($O14="","",INDEX(_Helpers!$A$2:$A$151,$O14-2+1)) | B14: =IF($O14="","",INDEX(_Helpers!$D$2:$D$151,$O14-2+1)) | C14: =IF($O14="","",INDEX(_Helpers!$B$2:$B$151,$O14-2+1)) | D14: =IF($O14="","",INDEX(_Helpers!$C$2:$C$151,$O14-2+1)) | E14: =IF($O14="","",INDEX(_Helpers!$L$2:$L$151,$O14-2+1)) | F14: =IF($O14="","",INDEX(_Helpers!$M$2:$M$151,$O14-2+1)) | G14: =IF($O14="","",IF(INDEX(_Helpers!$G$2:$G$151,$O14-2+1)=1,"Starter","")) | H14: =IF($O14="","",IF(INDEX(_Helpers!$H$2:$H$151,$O14-2+1)=1,"Leaver","")) | I14: =IF($O14="","",INDEX(_Helpers!$P$2:$P$151,$O14-2+1)) | J14: =IF($O14="","",INDEX(_Helpers!$V$2:$V$151,$O14-2+1)) | K14: =IF($O14="","",INDEX(_Helpers!$AJ$2:$AJ$151,$O14-2+1)) | L14: =IF($O14="","",INDEX(_Helpers!$AK$2:$AK$151,$O14-2+1)) | O14: {=IFERROR(SMALL(IF(_Helpers!$F$2:$F$151=1,ROW(_Helpers!$F$2:$F$151)),ROWS($A$4:A14)),"")}
A15: =IF($O15="","",INDEX(_Helpers!$A$2:$A$151,$O15-2+1)) | B15: =IF($O15="","",INDEX(_Helpers!$D$2:$D$151,$O15-2+1)) | C15: =IF($O15="","",INDEX(_Helpers!$B$2:$B$151,$O15-2+1)) | D15: =IF($O15="","",INDEX(_Helpers!$C$2:$C$151,$O15-2+1)) | E15: =IF($O15="","",INDEX(_Helpers!$L$2:$L$151,$O15-2+1)) | F15: =IF($O15="","",INDEX(_Helpers!$M$2:$M$151,$O15-2+1)) | G15: =IF($O15="","",IF(INDEX(_Helpers!$G$2:$G$151,$O15-2+1)=1,"Starter","")) | H15: =IF($O15="","",IF(INDEX(_Helpers!$H$2:$H$151,$O15-2+1)=1,"Leaver","")) | I15: =IF($O15="","",INDEX(_Helpers!$P$2:$P$151,$O15-2+1)) | J15: =IF($O15="","",INDEX(_Helpers!$V$2:$V$151,$O15-2+1)) | K15: =IF($O15="","",INDEX(_Helpers!$AJ$2:$AJ$151,$O15-2+1)) | L15: =IF($O15="","",INDEX(_Helpers!$AK$2:$AK$151,$O15-2+1)) | O15: {=IFERROR(SMALL(IF(_Helpers!$F$2:$F$151=1,ROW(_Helpers!$F$2:$F$151)),ROWS($A$4:A15)),"")}
... A153: =IF($O153="","",INDEX(_Helpers!$A$2:$A$151,$O153-2+1)) | B153: =IF($O153="","",INDEX(_Helpers!$D$2:$D$151,$O153-2+1)) | C153: =IF($O153="","",INDEX(_Helpers!$B$2:$B$151,$O153-2+1)) | D153: =IF($O153="","",INDEX(_Helpers!$C$2:$C$151,$O153-2+1)) | E153: =IF($O153="","",INDEX(_Helpers!$L$2:$L$151,$O153-2+1)) | F153: =IF($O153="","",INDEX(_Helpers!$M$2:$M$151,$O153-2+1)) | G153: =IF($O153="","",IF(INDEX(_Helpers!$G$2:$G$151,$O153-2+1)=1,"Starter","")) | H153: =IF($O153="","",IF(INDEX(_Helpers!$H$2:$H$151,$O153-2+1)=1,"Leaver","")) | I153: =IF($O153="","",INDEX(_Helpers!$P$2:$P$151,$O153-2+1)) | J153: =IF($O153="","",INDEX(_Helpers!$V$2:$V$151,$O153-2+1)) | K153: =IF($O153="","",INDEX(_Helpers!$AJ$2:$AJ$151,$O153-2+1)) | L153: =IF($O153="","",INDEX(_Helpers!$AK$2:$AK$151,$O153-2+1)) | O153: {=IFERROR(SMALL(IF(_Helpers!$F$2:$F$151=1,ROW(_Helpers!$F$2:$F$151)),ROWS($A$4:A153)),"")}

Sheet Zero Hours
A1: Zero Hours Contracts - Net Pay Movements
A2: Staff whose ONLY contract basis on the Structure report is Zero Hours. Listed for visibility only.
A3: Payroll Number | B3: Practice | C3: Prior Net | D3: Current Net | E3: Difference £ | F3: Difference % | H3: Helper: rank pointer
A4: =IF($H4="","",INDEX(_Helpers!$A$2:$A$151,$H4-2+1)) | B4: =IF($H4="","",INDEX(_Helpers!$D$2:$D$151,$H4-2+1)) | C4: =IF($H4="","",INDEX(_Helpers!$B$2:$B$151,$H4-2+1)) | D4: =IF($H4="","",INDEX(_Helpers!$C$2:$C$151,$H4-2+1)) | E4: =IF($H4="","",INDEX(_Helpers!$L$2:$L$151,$H4-2+1)) | F4: =IF($H4="","",INDEX(_Helpers!$M$2:$M$151,$H4-2+1)) | H4: {=IFERROR(SMALL(IF(_Helpers!$E$2:$E$151=1,ROW(_Helpers!$E$2:$E$151)),ROWS($A$4:A4)),"")}
A5: =IF($H5="","",INDEX(_Helpers!$A$2:$A$151,$H5-2+1)) | B5: =IF($H5="","",INDEX(_Helpers!$D$2:$D$151,$H5-2+1)) | C5: =IF($H5="","",INDEX(_Helpers!$B$2:$B$151,$H5-2+1)) | D5: =IF($H5="","",INDEX(_Helpers!$C$2:$C$151,$H5-2+1)) | E5: =IF($H5="","",INDEX(_Helpers!$L$2:$L$151,$H5-2+1)) | F5: =IF($H5="","",INDEX(_Helpers!$M$2:$M$151,$H5-2+1)) | H5: {=IFERROR(SMALL(IF(_Helpers!$E$2:$E$151=1,ROW(_Helpers!$E$2:$E$151)),ROWS($A$4:A5)),"")}
A6: =IF($H6="","",INDEX(_Helpers!$A$2:$A$151,$H6-2+1)) | B6: =IF($H6="","",INDEX(_Helpers!$D$2:$D$151,$H6-2+1)) | C6: =IF($H6="","",INDEX(_Helpers!$B$2:$B$151,$H6-2+1)) | D6: =IF($H6="","",INDEX(_Helpers!$C$2:$C$151,$H6-2+1)) | E6: =IF($H6="","",INDEX(_Helpers!$L$2:$L$151,$H6-2+1)) | F6: =IF($H6="","",INDEX(_Helpers!$M$2:$M$151,$H6-2+1)) | H6: {=IFERROR(SMALL(IF(_Helpers!$E$2:$E$151=1,ROW(_Helpers!$E$2:$E$151)),ROWS($A$4:A6)),"")}
A7: =IF($H7="","",INDEX(_Helpers!$A$2:$A$151,$H7-2+1)) | B7: =IF($H7="","",INDEX(_Helpers!$D$2:$D$151,$H7-2+1)) | C7: =IF($H7="","",INDEX(_Helpers!$B$2:$B$151,$H7-2+1)) | D7: =IF($H7="","",INDEX(_Helpers!$C$2:$C$151,$H7-2+1)) | E7: =IF($H7="","",INDEX(_Helpers!$L$2:$L$151,$H7-2+1)) | F7: =IF($H7="","",INDEX(_Helpers!$M$2:$M$151,$H7-2+1)) | H7: {=IFERROR(SMALL(IF(_Helpers!$E$2:$E$151=1,ROW(_Helpers!$E$2:$E$151)),ROWS($A$4:A7)),"")}
A8: =IF($H8="","",INDEX(_Helpers!$A$2:$A$151,$H8-2+1)) | B8: =IF($H8="","",INDEX(_Helpers!$D$2:$D$151,$H8-2+1)) | C8: =IF($H8="","",INDEX(_Helpers!$B$2:$B$151,$H8-2+1)) | D8: =IF($H8="","",INDEX(_Helpers!$C$2:$C$151,$H8-2+1)) | E8: =IF($H8="","",INDEX(_Helpers!$L$2:$L$151,$H8-2+1)) | F8: =IF($H8="","",INDEX(_Helpers!$M$2:$M$151,$H8-2+1)) | H8: {=IFERROR(SMALL(IF(_Helpers!$E$2:$E$151=1,ROW(_Helpers!$E$2:$E$151)),ROWS($A$4:A8)),"")}
A9: =IF($H9="","",INDEX(_Helpers!$A$2:$A$151,$H9-2+1)) | B9: =IF($H9="","",INDEX(_Helpers!$D$2:$D$151,$H9-2+1)) | C9: =IF($H9="","",INDEX(_Helpers!$B$2:$B$151,$H9-2+1)) | D9: =IF($H9="","",INDEX(_Helpers!$C$2:$C$151,$H9-2+1)) | E9: =IF($H9="","",INDEX(_Helpers!$L$2:$L$151,$H9-2+1)) | F9: =IF($H9="","",INDEX(_Helpers!$M$2:$M$151,$H9-2+1)) | H9: {=IFERROR(SMALL(IF(_Helpers!$E$2:$E$151=1,ROW(_Helpers!$E$2:$E$151)),ROWS($A$4:A9)),"")}
A10: =IF($H10="","",INDEX(_Helpers!$A$2:$A$151,$H10-2+1)) | B10: =IF($H10="","",INDEX(_Helpers!$D$2:$D$151,$H10-2+1)) | C10: =IF($H10="","",INDEX(_Helpers!$B$2:$B$151,$H10-2+1)) | D10: =IF($H10="","",INDEX(_Helpers!$C$2:$C$151,$H10-2+1)) | E10: =IF($H10="","",INDEX(_Helpers!$L$2:$L$151,$H10-2+1)) | F10: =IF($H10="","",INDEX(_Helpers!$M$2:$M$151,$H10-2+1)) | H10: {=IFERROR(SMALL(IF(_Helpers!$E$2:$E$151=1,ROW(_Helpers!$E$2:$E$151)),ROWS($A$4:A10)),"")}
A11: =IF($H11="","",INDEX(_Helpers!$A$2:$A$151,$H11-2+1)) | B11: =IF($H11="","",INDEX(_Helpers!$D$2:$D$151,$H11-2+1)) | C11: =IF($H11="","",INDEX(_Helpers!$B$2:$B$151,$H11-2+1)) | D11: =IF($H11="","",INDEX(_Helpers!$C$2:$C$151,$H11-2+1)) | E11: =IF($H11="","",INDEX(_Helpers!$L$2:$L$151,$H11-2+1)) | F11: =IF($H11="","",INDEX(_Helpers!$M$2:$M$151,$H11-2+1)) | H11: {=IFERROR(SMALL(IF(_Helpers!$E$2:$E$151=1,ROW(_Helpers!$E$2:$E$151)),ROWS($A$4:A11)),"")}
A12: =IF($H12="","",INDEX(_Helpers!$A$2:$A$151,$H12-2+1)) | B12: =IF($H12="","",INDEX(_Helpers!$D$2:$D$151,$H12-2+1)) | C12: =IF($H12="","",INDEX(_Helpers!$B$2:$B$151,$H12-2+1)) | D12: =IF($H12="","",INDEX(_Helpers!$C$2:$C$151,$H12-2+1)) | E12: =IF($H12="","",INDEX(_Helpers!$L$2:$L$151,$H12-2+1)) | F12: =IF($H12="","",INDEX(_Helpers!$M$2:$M$151,$H12-2+1)) | H12: {=IFERROR(SMALL(IF(_Helpers!$E$2:$E$151=1,ROW(_Helpers!$E$2:$E$151)),ROWS($A$4:A12)),"")}
A13: =IF($H13="","",INDEX(_Helpers!$A$2:$A$151,$H13-2+1)) | B13: =IF($H13="","",INDEX(_Helpers!$D$2:$D$151,$H13-2+1)) | C13: =IF($H13="","",INDEX(_Helpers!$B$2:$B$151,$H13-2+1)) | D13: =IF($H13="","",INDEX(_Helpers!$C$2:$C$151,$H13-2+1)) | E13: =IF($H13="","",INDEX(_Helpers!$L$2:$L$151,$H13-2+1)) | F13: =IF($H13="","",INDEX(_Helpers!$M$2:$M$151,$H13-2+1)) | H13: {=IFERROR(SMALL(IF(_Helpers!$E$2:$E$151=1,ROW(_Helpers!$E$2:$E$151)),ROWS($A$4:A13)),"")}
A14: =IF($H14="","",INDEX(_Helpers!$A$2:$A$151,$H14-2+1)) | B14: =IF($H14="","",INDEX(_Helpers!$D$2:$D$151,$H14-2+1)) | C14: =IF($H14="","",INDEX(_Helpers!$B$2:$B$151,$H14-2+1)) | D14: =IF($H14="","",INDEX(_Helpers!$C$2:$C$151,$H14-2+1)) | E14: =IF($H14="","",INDEX(_Helpers!$L$2:$L$151,$H14-2+1)) | F14: =IF($H14="","",INDEX(_Helpers!$M$2:$M$151,$H14-2+1)) | H14: {=IFERROR(SMALL(IF(_Helpers!$E$2:$E$151=1,ROW(_Helpers!$E$2:$E$151)),ROWS($A$4:A14)),"")}
A15: =IF($H15="","",INDEX(_Helpers!$A$2:$A$151,$H15-2+1)) | B15: =IF($H15="","",INDEX(_Helpers!$D$2:$D$151,$H15-2+1)) | C15: =IF($H15="","",INDEX(_Helpers!$B$2:$B$151,$H15-2+1)) | D15: =IF($H15="","",INDEX(_Helpers!$C$2:$C$151,$H15-2+1)) | E15: =IF($H15="","",INDEX(_Helpers!$L$2:$L$151,$H15-2+1)) | F15: =IF($H15="","",INDEX(_Helpers!$M$2:$M$151,$H15-2+1)) | H15: {=IFERROR(SMALL(IF(_Helpers!$E$2:$E$151=1,ROW(_Helpers!$E$2:$E$151)),ROWS($A$4:A15)),"")}
... A153: =IF($H153="","",INDEX(_Helpers!$A$2:$A$151,$H153-2+1)) | B153: =IF($H153="","",INDEX(_Helpers!$D$2:$D$151,$H153-2+1)) | C153: =IF($H153="","",INDEX(_Helpers!$B$2:$B$151,$H153-2+1)) | D153: =IF($H153="","",INDEX(_Helpers!$C$2:$C$151,$H153-2+1)) | E153: =IF($H153="","",INDEX(_Helpers!$L$2:$L$151,$H153-2+1)) | F153: =IF($H153="","",INDEX(_Helpers!$M$2:$M$151,$H153-2+1)) | H153: {=IFERROR(SMALL(IF(_Helpers!$E$2:$E$151=1,ROW(_Helpers!$E$2:$E$151)),ROWS($A$4:A153)),"")}

Sheet Drilldown
A1: Drilldown - Inspect a Payroll Number
A3: Enter Payroll Number:
A5: Practice | C5: =IFERROR(INDEX(_Helpers!$D$2:$D$151,MATCH($C$3,_Helpers!$A$2:$A$151,0)),"Not found")
A6: Status | C6: =IFERROR(INDEX(_Helpers!$P$2:$P$151,MATCH($C$3,_Helpers!$A$2:$A$151,0)),"Not found")
A7: Starter? | C7: =IF(N(IFERROR(INDEX(_Helpers!$G$2:$G$151,MATCH($C$3,_Helpers!$A$2:$A$151,0)),"Not found"))=1,"Yes","No")
A8: Leaver? | C8: =IF(N(IFERROR(INDEX(_Helpers!$H$2:$H$151,MATCH($C$3,_Helpers!$A$2:$A$151,0)),"Not found"))=1,"Yes","No")
A9: Zero Hours contract? | C9: =IF(N(IFERROR(INDEX(_Helpers!$E$2:$E$151,MATCH($C$3,_Helpers!$A$2:$A$151,0)),"Not found"))=1,"Yes","No")
A10: Prior Net | C10: =IFERROR(INDEX(_Helpers!$B$2:$B$151,MATCH($C$3,_Helpers!$A$2:$A$151,0)),"Not found")
A11: Current Net | C11: =IFERROR(INDEX(_Helpers!$C$2:$C$151,MATCH($C$3,_Helpers!$A$2:$A$151,0)),"Not found")
A12: Difference £ | C12: =IFERROR(INDEX(_Helpers!$L$2:$L$151,MATCH($C$3,_Helpers!$A$2:$A$151,0)),"Not found")
A13: Difference % | C13: =IFERROR(INDEX(_Helpers!$M$2:$M$151,MATCH($C$3,_Helpers!$A$2:$A$151,0)),"Not found")
A15: Tolerance applied | C15: =IF(ISNUMBER(SEARCH("Head Office",C5)),'Control Sheet'!$C$6,'Control Sheet'!$C$5)
A17: All pay elements - both months compared
A18: Element | B18: Prior | C18: Current | D18: Difference | E18: Difference % | F18: CHECK
A19: Total Gross | B19: =IF($C$3="","",SUMIFS('Payment Breakdown Prior'!$K$15:$K$164,'Payment Breakdown Prior'!$AE$15:$AE$164,$C$3)) | C19: =IF($C$3="","",SUMIFS('Payment Breakdown Current'!$K$15:$K$164,'Payment Breakdown Current'!$AE$15:$AE$164,$C$3)) | D19: =IF($C$3="","",C19-B19) | E19: =IFERROR(D19/B19,"") | F19: =IF($C$3="","",IF(AND(ABS(D19)>='Control Sheet'!$C$7,OR(B19=0,AND(ISNUMBER(E19),ABS(E19)>$C$15))),"CHECK",""))
A20: Taxable Gross | B20: =IF($C$3="","",SUMIFS('Payment Breakdown Prior'!$L$15:$L$164,'Payment Breakdown Prior'!$AE$15:$AE$164,$C$3)) | C20: =IF($C$3="","",SUMIFS('Payment Breakdown Current'!$L$15:$L$164,'Payment Breakdown Current'!$AE$15:$AE$164,$C$3)) | D20: =IF($C$3="","",C20-B20) | E20: =IFERROR(D20/B20,"") | F20: =IF($C$3="","",IF(AND(ABS(D20)>='Control Sheet'!$C$7,OR(B20=0,AND(ISNUMBER(E20),ABS(E20)>$C$15))),"CHECK",""))
A21: Pensionable Pay | B21: =IF($C$3="","",SUMIFS('Payment Breakdown Prior'!$M$15:$M$164,'Payment Breakdown Prior'!$AE$15:$AE$164,$C$3)) | C21: =IF($C$3="","",SUMIFS('Payment Breakdown Current'!$M$15:$M$164,'Payment Breakdown Current'!$AE$15:$AE$164,$C$3)) | D21: =IF($C$3="","",C21-B21) | E21: =IFERROR(D21/B21,"") | F21: =IF($C$3="","",IF(AND(ABS(D21)>='Control Sheet'!$C$7,OR(B21=0,AND(ISNUMBER(E21),ABS(E21)>$C$15))),"CHECK",""))
A22: Hours Paid | B22: =IF($C$3="","",SUMIFS('Payment Breakdown Prior'!$N$15:$N$164,'Payment Breakdown Prior'!$AE$15:$AE$164,$C$3)) | C22: =IF($C$3="","",SUMIFS('Payment Breakdown Current'!$N$15:$N$164,'Payment Breakdown Current'!$AE$15:$AE$164,$C$3)) | D22: =IF($C$3="","",C22-B22) | E22: =IFERROR(D22/B22,"") | F22: =IF($C$3="","",IF(AND(ABS(D22)>='Control Sheet'!$C$7,OR(B22=0,AND(ISNUMBER(E22),ABS(E22)>$C$15))),"CHECK",""))
A23: Net Pay After Rounding | B23: =IF($C$3="","",SUMIFS('Payment Breakdown Prior'!$O$15:$O$164,'Payment Breakdown Prior'!$AE$15:$AE$164,$C$3)) | C23: =IF($C$3="","",SUMIFS('Payment Breakdown Current'!$O$15:$O$164,'Payment Breakdown Current'!$AE$15:$AE$164,$C$3)) | D23: =IF($C$3="","",C23-B23) | E23: =IFERROR(D23/B23,"") | F23: =IF($C$3="","",IF(AND(ABS(D23)>='Control Sheet'!$C$7,OR(B23=0,AND(ISNUMBER(E23),ABS(E23)>$C$15))),"CHECK",""))
A24: Employer NI | B24: =IF($C$3="","",SUMIFS('Payment Breakdown Prior'!$P$15:$P$164,'Payment Breakdown Prior'!$AE$15:$AE$164,$C$3)) | C24: =IF($C$3="","",SUMIFS('Payment Breakdown Current'!$P$15:$P$164,'Payment Breakdown Current'!$AE$15:$AE$164,$C$3)) | D24: =IF($C$3="","",C24-B24) | E24: =IFERROR(D24/B24,"") | F24: =IF($C$3="","",IF(AND(ABS(D24)>='Control Sheet'!$C$7,OR(B24=0,AND(ISNUMBER(E24),ABS(E24)>$C$15))),"CHECK",""))
A25: Employer Pension | B25: =IF($C$3="","",SUMIFS('Payment Breakdown Prior'!$Q$15:$Q$164,'Payment Breakdown Prior'!$AE$15:$AE$164,$C$3)) | C25: =IF($C$3="","",SUMIFS('Payment Breakdown Current'!$Q$15:$Q$164,'Payment Breakdown Current'!$AE$15:$AE$164,$C$3)) | D25: =IF($C$3="","",C25-B25) | E25: =IFERROR(D25/B25,"") | F25: =IF($C$3="","",IF(AND(ABS(D25)>='Control Sheet'!$C$7,OR(B25=0,AND(ISNUMBER(E25),ABS(E25)>$C$15))),"CHECK",""))
A26: Apprenticeship Levy | B26: =IF($C$3="","",SUMIFS('Payment Breakdown Prior'!$R$15:$R$164,'Payment Breakdown Prior'!$AE$15:$AE$164,$C$3)) | C26: =IF($C$3="","",SUMIFS('Payment Breakdown Current'!$R$15:$R$164,'Payment Breakdown Current'!$AE$15:$AE$164,$C$3)) | D26: =IF($C$3="","",C26-B26) | E26: =IFERROR(D26/B26,"") | F26: =IF($C$3="","",IF(AND(ABS(D26)>='Control Sheet'!$C$7,OR(B26=0,AND(ISNUMBER(E26),ABS(E26)>$C$15))),"CHECK",""))
A27: Basic Salary | B27: =IF($C$3="","",SUMIFS('Payment Breakdown Prior'!$S$15:$S$164,'Payment Breakdown Prior'!$AE$15:$AE$164,$C$3)) | C27: =IF($C$3="","",SUMIFS('Payment Breakdown Current'!$S$15:$S$164,'Payment Breakdown Current'!$AE$15:$AE$164,$C$3)) | D27: =IF($C$3="","",C27-B27) | E27: =IFERROR(D27/B27,"") | F27: =IF($C$3="","",IF(AND(ABS(D27)>='Control Sheet'!$C$7,OR(B27=0,AND(ISNUMBER(E27),ABS(E27)>$C$15))),"CHECK",""))
A28: Overtime | B28: =IF($C$3="","",SUMIFS('Payment Breakdown Prior'!$T$15:$T$164,'Payment Breakdown Prior'!$AE$15:$AE$164,$C$3)) | C28: =IF($C$3="","",SUMIFS('Payment Breakdown Current'!$T$15:$T$164,'Payment Breakdown Current'!$AE$15:$AE$164,$C$3)) | D28: =IF($C$3="","",C28-B28) | E28: =IFERROR(D28/B28,"") | F28: =IF($C$3="","",IF(AND(ABS(D28)>='Control Sheet'!$C$7,OR(B28=0,AND(ISNUMBER(E28),ABS(E28)>$C$15))),"CHECK",""))
A29: Bonus | B29: =IF($C$3="","",SUMIFS('Payment Breakdown Prior'!$U$15:$U$164,'Payment Breakdown Prior'!$AE$15:$AE$164,$C$3)) | C29: =IF($C$3="","",SUMIFS('Payment Breakdown Current'!$U$15:$U$164,'Payment Breakdown Current'!$AE$15:$AE$164,$C$3)) | D29: =IF($C$3="","",C29-B29) | E29: =IFERROR(D29/B29,"") | F29: =IF($C$3="","",IF(AND(ABS(D29)>='Control Sheet'!$C$7,OR(B29=0,AND(ISNUMBER(E29),ABS(E29)>$C$15))),"CHECK",""))
A30: Mileage Expenses | B30: =IF($C$3="","",SUMIFS('Payment Breakdown Prior'!$V$15:$V$164,'Payment Breakdown Prior'!$AE$15:$AE$164,$C$3)) | C30: =IF($C$3="","",SUMIFS('Payment Breakdown Current'!$V$15:$V$164,'Payment Breakdown Current'!$AE$15:$AE$164,$C$3)) | D30: =IF($C$3="","",C30-B30) | E30: =IFERROR(D30/B30,"") | F30: =IF($C$3="","",IF(AND(ABS(D30)>='Control Sheet'!$C$7,OR(B30=0,AND(ISNUMBER(E30),ABS(E30)>$C$15))),"CHECK",""))
A31: Other Expenses | B31: =IF($C$3="","",SUMIFS('Payment Breakdown Prior'!$W$15:$W$164,'Payment Breakdown Prior'!$AE$15:$AE$164,$C$3)) | C31: =IF($C$3="","",SUMIFS('Payment Breakdown Current'!$W$15:$W$164,'Payment Breakdown Current'!$AE$15:$AE$164,$C$3)) | D31: =IF($C$3="","",C31-B31) | E31: =IFERROR(D31/B31,"") | F31: =IF($C$3="","",IF(AND(ABS(D31)>='Control Sheet'!$C$7,OR(B31=0,AND(ISNUMBER(E31),ABS(E31)>$C$15))),"CHECK",""))
A32: SMP | B32: =IF($C$3="","",SUMIFS('Payment Breakdown Prior'!$X$15:$X$164,'Payment Breakdown Prior'!$AE$15:$AE$164,$C$3)) | C32: =IF($C$3="","",SUMIFS('Payment Breakdown Current'!$X$15:$X$164,'Payment Breakdown Current'!$AE$15:$AE$164,$C$3)) | D32: =IF($C$3="","",C32-B32) | E32: =IFERROR(D32/B32,"") | F32: =IF($C$3="","",IF(AND(ABS(D32)>='Control Sheet'!$C$7,OR(B32=0,AND(ISNUMBER(E32),ABS(E32)>$C$15))),"CHECK",""))
A33: SSP | B33: =IF($C$3="","",SUMIFS('Payment Breakdown Prior'!$Y$15:$Y$164,'Payment Breakdown Prior'!$AE$15:$AE$164,$C$3)) | C33: =IF($C$3="","",SUMIFS('Payment Breakdown Current'!$Y$15:$Y$164,'Payment Breakdown Current'!$AE$15:$AE$164,$C$3)) | D33: =IF($C$3="","",C33-B33) | E33: =IFERROR(D33/B33,"") | F33: =IF($C$3="","",IF(AND(ABS(D33)>='Control Sheet'!$C$7,OR(B33=0,AND(ISNUMBER(E33),ABS(E33)>$C$15))),"CHECK",""))
A34: Pension Deduction | B34: =IF($C$3="","",SUMIFS('Payment Breakdown Prior'!$Z$15:$Z$164,'Payment Breakdown Prior'!$AE$15:$AE$164,$C$3)) | C34: =IF($C$3="","",SUMIFS('Payment Breakdown Current'!$Z$15:$Z$164,'Payment Breakdown Current'!$AE$15:$AE$164,$C$3)) | D34: =IF($C$3="","",C34-B34) | E34: =IFERROR(D34/B34,"") | F34: =IF($C$3="","",IF(AND(ABS(D34)>='Control Sheet'!$C$7,OR(B34=0,AND(ISNUMBER(E34),ABS(E34)>$C$15))),"CHECK",""))
A35: Student Loan | B35: =IF($C$3="","",SUMIFS('Payment Breakdown Prior'!$AA$15:$AA$164,'Payment Breakdown Prior'!$AE$15:$AE$164,$C$3)) | C35: =IF($C$3="","",SUMIFS('Payment Breakdown Current'!$AA$15:$AA$164,'Payment Breakdown Current'!$AE$15:$AE$164,$C$3)) | D35: =IF($C$3="","",C35-B35) | E35: =IFERROR(D35/B35,"") | F35: =IF($C$3="","",IF(AND(ABS(D35)>='Control Sheet'!$C$7,OR(B35=0,AND(ISNUMBER(E35),ABS(E35)>$C$15))),"CHECK",""))
A36: Attachment of Earnings | B36: =IF($C$3="","",SUMIFS('Payment Breakdown Prior'!$AB$15:$AB$164,'Payment Breakdown Prior'!$AE$15:$AE$164,$C$3)) | C36: =IF($C$3="","",SUMIFS('Payment Breakdown Current'!$AB$15:$AB$164,'Payment Breakdown Current'!$AE$15:$AE$164,$C$3)) | D36: =IF($C$3="","",C36-B36) | E36: =IFERROR(D36/B36,"") | F36: =IF($C$3="","",IF(AND(ABS(D36)>='Control Sheet'!$C$7,OR(B36=0,AND(ISNUMBER(E36),ABS(E36)>$C$15))),"CHECK",""))
A37: On Call Allowance | B37: =IF($C$3="","",SUMIFS('Payment Breakdown Prior'!$AC$15:$AC$164,'Payment Breakdown Prior'!$AE$15:$AE$164,$C$3)) | C37: =IF($C$3="","",SUMIFS('Payment Breakdown Current'!$AC$15:$AC$164,'Payment Breakdown Current'!$AE$15:$AE$164,$C$3)) | D37: =IF($C$3="","",C37-B37) | E37: =IFERROR(D37/B37,"") | F37: =IF($C$3="","",IF(AND(ABS(D37)>='Control Sheet'!$C$7,OR(B37=0,AND(ISNUMBER(E37),ABS(E37)>$C$15))),"CHECK",""))
A38: Unsocial Hours Premium | B38: =IF($C$3="","",SUMIFS('Payment Breakdown Prior'!$AD$15:$AD$164,'Payment Breakdown Prior'!$AE$15:$AE$164,$C$3)) | C38: =IF($C$3="","",SUMIFS('Payment Breakdown Current'!$AD$15:$AD$164,'Payment Breakdown Current'!$AE$15:$AE$164,$C$3)) | D38: =IF($C$3="","",C38-B38) | E38: =IFERROR(D38/B38,"") | F38: =IF($C$3="","",IF(AND(ABS(D38)>='Control Sheet'!$C$7,OR(B38=0,AND(ISNUMBER(E38),ABS(E38)>$C$15))),"CHECK",""))

Sheet NPV Comparison
A1: NPV Comparison (Net Pay) - paste raw iTrent export below from row 14
A12: Paste the full export starting at A14 (headers) so data begins row 15. Do not insert or delete columns.
A14: Payroll Area | B14: Surname | C14: Forename | D14: Payroll Number | E14: Prior Net Pay | F14: Current Net Pay | G14: Difference | H14: Difference % | I14: Payment Date | J14: Frequency
A15: RIV | B15: Surname434 | C15: Forename434 | D15: P23434 | E15: 1840.81 | F15: 1625.82 | G15: =IF(AND(E15<>"",F15<>""),F15-E15,IF(F15<>"",F15,IF(E15<>"",-E15,""))) | H15: =IFERROR(G15/E15,"") | I15: July 2026 | J15: Monthly
A16: HAK | B16: Surname280 | C16: Forename280 | D16: P22280 | E16: 2462.89 | F16: 2400.62 | G16: =IF(AND(E16<>"",F16<>""),F16-E16,IF(F16<>"",F16,IF(E16<>"",-E16,""))) | H16: =IFERROR(G16/E16,"") | I16: July 2026 | J16: Monthly
A17: KIN | B17: Surname426 | C17: Forename426 | D17: P81426 | E17: 2410.24 | F17: 2578.93 | G17: =IF(AND(E17<>"",F17<>""),F17-E17,IF(F17<>"",F17,IF(E17<>"",-E17,""))) | H17: =IFERROR(G17/E17,"") | I17: July 2026 | J17: Monthly
A18: OAK | B18: Surname926 | C18: Forename926 | D18: P30926 | E18: 2856.97 | F18: 2400.16 | G18: =IF(AND(E18<>"",F18<>""),F18-E18,IF(F18<>"",F18,IF(E18<>"",-E18,""))) | H18: =IFERROR(G18/E18,"") | I18: July 2026 | J18: Monthly
A19: OAK | B19: Surname396 | C19: Forename396 | D19: P23396 | E19: 1787.56 | F19: 1940.17 | G19: =IF(AND(E19<>"",F19<>""),F19-E19,IF(F19<>"",F19,IF(E19<>"",-E19,""))) | H19: =IFERROR(G19/E19,"") | I19: July 2026 | J19: Monthly
A20: RIV | B20: Surname695 | C20: Forename695 | D20: P15695 | E20: 2925.49 | F20: 3023.81 | G20: =IF(AND(E20<>"",F20<>""),F20-E20,IF(F20<>"",F20,IF(E20<>"",-E20,""))) | H20: =IFERROR(G20/E20,"") | I20: July 2026 | J20: Monthly
A21: OAK | B21: Surname397 | C21: Forename397 | D21: P92397 | E21: 1541.84 | F21: 1438.52 | G21: =IF(AND(E21<>"",F21<>""),F21-E21,IF(F21<>"",F21,IF(E21<>"",-E21,""))) | H21: =IFERROR(G21/E21,"") | I21: July 2026 | J21: Monthly
A22: HAK | B22: Surname006 | C22: Forename006 | D22: P16006 | E22: 2439.23 | F22: 2466.18 | G22: =IF(AND(E22<>"",F22<>""),F22-E22,IF(F22<>"",F22,IF(E22<>"",-E22,""))) | H22: =IFERROR(G22/E22,"") | I22: July 2026 | J22: Monthly
A23: KIN | B23: Surname823 | C23: Forename823 | D23: P59823 | E23: 2939.57 | F23: 3288.62 | G23: =IF(AND(E23<>"",F23<>""),F23-E23,IF(F23<>"",F23,IF(E23<>"",-E23,""))) | H23: =IFERROR(G23/E23,"") | I23: July 2026 | J23: Monthly
A24: ELM | B24: Surname841 | C24: Forename841 | D24: P97841 | E24: 1692.78 | F24: 1613.4 | G24: =IF(AND(E24<>"",F24<>""),F24-E24,IF(F24<>"",F24,IF(E24<>"",-E24,""))) | H24: =IFERROR(G24/E24,"") | I24: July 2026 | J24: Monthly
A25: ELM | B25: Surname431 | C25: Forename431 | D25: P32431 | E25: 2566.46 | F25: 2657.21 | G25: =IF(AND(E25<>"",F25<>""),F25-E25,IF(F25<>"",F25,IF(E25<>"",-E25,""))) | H25: =IFERROR(G25/E25,"") | I25: July 2026 | J25: Monthly
A26: HAK | B26: Surname886 | C26: Forename886 | D26: P93886 | E26: 1694.12 | F26: 1683.1 | G26: =IF(AND(E26<>"",F26<>""),F26-E26,IF(F26<>"",F26,IF(E26<>"",-E26,""))) | H26: =IFERROR(G26/E26,"") | I26: July 2026 | J26: Monthly
... A54: KIN | B54: Surname050 | C54: Forename050 | D54: P34050 | E54: 1768.22 | F54: 2006.93 | G54: =IF(AND(E54<>"",F54<>""),F54-E54,IF(F54<>"",F54,IF(E54<>"",-E54,""))) | H54: =IFERROR(G54/E54,"") | I54: July 2026 | J54: Monthly
A55: HAK | B55: Surname630 | C55: Forename630 | D55: P16630 | F55: 1806.4 | G55: =IF(AND(E55<>"",F55<>""),F55-E55,IF(F55<>"",F55,IF(E55<>"",-E55,""))) | H55: =IFERROR(G55/E55,"") | I55: July 2026 | J55: Monthly
A56: HAK | B56: Surname224 | C56: Forename224 | D56: P22224 | F56: 1774.79 | G56: =IF(AND(E56<>"",F56<>""),F56-E56,IF(F56<>"",F56,IF(E56<>"",-E56,""))) | H56: =IFERROR(G56/E56,"") | I56: July 2026 | J56: Monthly
A57: KIN | B57: Surname092 | C57: Forename092 | D57: P73092 | F57: 2515.59 | G57: =IF(AND(E57<>"",F57<>""),F57-E57,IF(F57<>"",F57,IF(E57<>"",-E57,""))) | H57: =IFERROR(G57/E57,"") | I57: July 2026 | J57: Monthly
A58: KIN | B58: Surname579 | C58: Forename579 | D58: P31579 | F58: 921.57 | G58: =IF(AND(E58<>"",F58<>""),F58-E58,IF(F58<>"",F58,IF(E58<>"",-E58,""))) | H58: =IFERROR(G58/E58,"") | I58: July 2026 | J58: Monthly
A59: OAK | B59: Surname638 | C59: Forename638 | D59: P69638 | E59: 1691.72 | G59: =IF(AND(E59<>"",F59<>""),F59-E59,IF(F59<>"",F59,IF(E59<>"",-E59,""))) | H59: =IFERROR(G59/E59,"") | I59: July 2026 | J59: Monthly
A60: ELM | B60: Surname890 | C60: Forename890 | D60: P48890 | E60: 1570.28 | G60: =IF(AND(E60<>"",F60<>""),F60-E60,IF(F60<>"",F60,IF(E60<>"",-E60,""))) | H60: =IFERROR(G60/E60,"") | I60: July 2026 | J60: Monthly
A61: KIN | B61: Surname492 | C61: Forename492 | D61: P17492 | E61: 2222.77 | G61: =IF(AND(E61<>"",F61<>""),F61-E61,IF(F61<>"",F61,IF(E61<>"",-E61,""))) | H61: =IFERROR(G61/E61,"") | I61: July 2026 | J61: Monthly
A62: RIV | B62: Surname615 | C62: Forename615 | D62: P79615 | E62: 2411.33 | G62: =IF(AND(E62<>"",F62<>""),F62-E62,IF(F62<>"",F62,IF(E62<>"",-E62,""))) | H62: =IFERROR(G62/E62,"") | I62: July 2026 | J62: Monthly
A63: KIN | B63: Surname356 | C63: Forename356 | D63: P34356 | E63: 181.28 | F63: 210.61 | G63: =IF(AND(E63<>"",F63<>""),F63-E63,IF(F63<>"",F63,IF(E63<>"",-E63,""))) | H63: =IFERROR(G63/E63,"") | I63: July 2026 | J63: Monthly
A64: RIV | B64: Surname828 | C64: Forename828 | D64: P40828 | E64: 477.27 | F64: 674.3 | G64: =IF(AND(E64<>"",F64<>""),F64-E64,IF(F64<>"",F64,IF(E64<>"",-E64,""))) | H64: =IFERROR(G64/E64,"") | I64: July 2026 | J64: Monthly
A65: OAK | B65: Surname271 | C65: Forename271 | D65: P42271 | E65: 215.94 | F65: 374.74 | G65: =IF(AND(E65<>"",F65<>""),F65-E65,IF(F65<>"",F65,IF(E65<>"",-E65,""))) | H65: =IFERROR(G65/E65,"") | I65: July 2026 | J65: Monthly
A66: RIV | B66: Surname503 | C66: Forename503 | D66: P86503 | E66: 490.66 | F66: 504.81 | G66: =IF(AND(E66<>"",F66<>""),F66-E66,IF(F66<>"",F66,IF(E66<>"",-E66,""))) | H66: =IFERROR(G66/E66,"") | I66: July 2026 | J66: Monthly
A67: ELM | B67: Surname814 | C67: Forename814 | D67: P44814 | E67: 2335.78 | F67: 2314.39 | G67: =IF(AND(E67<>"",F67<>""),F67-E67,IF(F67<>"",F67,IF(E67<>"",-E67,""))) | H67: =IFERROR(G67/E67,"") | I67: July 2026 | J67: Monthly
A68: OAK | B68: Surname508 | C68: Forename508 | D68: P19508 | E68: 2165.78 | F68: 2319.06 | G68: =IF(AND(E68<>"",F68<>""),F68-E68,IF(F68<>"",F68,IF(E68<>"",-E68,""))) | H68: =IFERROR(G68/E68,"") | I68: July 2026 | J68: Monthly
A69: RIV | B69: Surname602 | C69: Forename602 | D69: P19602 | E69: 2596.88 | G69: =IF(AND(E69<>"",F69<>""),F69-E69,IF(F69<>"",F69,IF(E69<>"",-E69,""))) | H69: =IFERROR(G69/E69,"") | I69: July 2026 | J69: Monthly
A70: OAK | B70: Surname468 | C70: Forename468 | D70: P80468 | F70: 2596.88 | G70: =IF(AND(E70<>"",F70<>""),F70-E70,IF(F70<>"",F70,IF(E70<>"",-E70,""))) | H70: =IFERROR(G70/E70,"") | I70: July 2026 | J70: Monthly
A71: KIN | B71: Surname745 | C71: Forename745 | D71: P55745 | E71: 1905.97 | G71: =IF(AND(E71<>"",F71<>""),F71-E71,IF(F71<>"",F71,IF(E71<>"",-E71,""))) | H71: =IFERROR(G71/E71,"") | I71: July 2026 | J71: Monthly
A72: HAK | B72: Surname016 | C72: Forename016 | D72: P19016 | F72: 1905.97 | G72: =IF(AND(E72<>"",F72<>""),F72-E72,IF(F72<>"",F72,IF(E72<>"",-E72,""))) | H72: =IFERROR(G72/E72,"") | I72: July 2026 | J72: Monthly
A73: KIN | B73: Surname200 | C73: Forename200 | D73: P81200 | E73: 2150.55 | F73: 0 | G73: =IF(AND(E73<>"",F73<>""),F73-E73,IF(F73<>"",F73,IF(E73<>"",-E73,""))) | H73: =IFERROR(G73/E73,"") | I73: July 2026 | J73: Monthly
A74: ELM | B74: Surname538 | C74: Forename538 | D74: P97538 | E74: 2223.15 | F74: 0 | G74: =IF(AND(E74<>"",F74<>""),F74-E74,IF(F74<>"",F74,IF(E74<>"",-E74,""))) | H74: =IFERROR(G74/E74,"") | I74: July 2026 | J74: Monthly

Sheet Payment Breakdown Current
A1: Payment Breakdown - current month (July 2026) - paste from row 14
A12: Paste the full export starting at A14 (headers) so data begins row 15.
A14: Row | B14: Surname | C14: Forename | D14: Practice | E14: Department | F14: Cost Centre | G14: Payment Date | H14: Frequency | I14: Tax Code | J14: NI Category | K14: Total Gross | L14: Taxable Gross | M14: Pensionable Pay | N14: Hours Paid | O14: Net Pay After Rounding | P14: Employer NI | Q14: Employer Pension | R14: Apprenticeship Levy | S14: Basic Salary | T14: Overtime | U14: Bonus | V14: Mileage Expenses | W14: Other Expenses | X14: SMP | Y14: SSP | Z14: Pension Deduction | AA14: Student Loan | AB14: Attachment of Earnings | AC14: On Call Allowance | AD14: Unsocial Hours Premium | AE14: Reference No
A15: 1 | B15: Surname434 | C15: Forename434 | D15: Riverside Dental Practice | E15: Clinical | F15: CC-RIV | G15: July 2026 | H15: Monthly | I15: 1257L | J15: A | K15: 2520.02 | L15: 2469.62 | M15: 2394.02 | N15: 182.905 | O15: 1625.82 | P15: 347.76 | Q15: 126 | R15: 12.6 | S15: 2194.86 | T15: 0 | U15: 0 | V15: 0 | W15: 0 | X15: 0 | Y15: 0 | Z15: 0 | AA15: 0 | AB15: 0 | AC15: 0 | AD15: 0 | AE15: P23434
A16: 2 | B16: Surname280 | C16: Forename280 | D16: Hakim Group Head Office | E16: Support | F16: CC-HAK | G16: July 2026 | H16: Monthly | I16: 1257L | J16: A | K16: 3720.96 | L16: 3646.54 | M16: 3534.91 | N16: 270.07 | O16: 2400.62 | P16: 513.49 | Q16: 186.05 | R16: 18.6 | S16: 3240.84 | T16: 0 | U16: 0 | V16: 0 | W16: 0 | X16: 0 | Y16: 0 | Z16: 0 | AA16: 0 | AB16: 0 | AC16: 0 | AD16: 0 | AE16: P22280
A17: 3 | B17: Surname426 | C17: Forename426 | D17: Kings Road Dental Practice | E17: Clinical | F17: CC-KIN | G17: July 2026 | H17: Monthly | I17: 1257L | J17: A | K17: 3997.34 | L17: 3917.39 | M17: 3797.47 | N17: 290.13 | O17: 2578.93 | P17: 551.63 | Q17: 199.87 | R17: 19.99 | S17: 3481.56 | T17: 0 | U17: 0 | V17: 0 | W17: 0 | X17: 0 | Y17: 0 | Z17: 0 | AA17: 0 | AB17: 0 | AC17: 0 | AD17: 0 | AE17: P81426
A18: 4 | B18: Surname926 | C18: Forename926 | D18: Oakfield Dental Practice | E18: Clinical | F18: CC-OAK | G18: July 2026 | H18: Monthly | I18: 1257L | J18: A | K18: 3720.25 | L18: 3645.84 | M18: 3534.24 | N18: 270.01833 | O18: 2400.16 | P18: 513.39 | Q18: 186.01 | R18: 18.6 | S18: 3240.22 | T18: 0 | U18: 0 | V18: 0 | W18: 0 | X18: 0 | Y18: 0 | Z18: 0 | AA18: 0 | AB18: 0 | AC18: 0 | AD18: 0 | AE18: P30926
A19: 5 | B19: Surname396 | C19: Forename396 | D19: Oakfield Dental Practice | E19: Clinical | F19: CC-OAK | G19: July 2026 | H19: Monthly | I19: 1257L | J19: A | K19: 3007.26 | L19: 2947.11 | M19: 2856.9 | N19: 218.26917 | O19: 1940.17 | P19: 415 | Q19: 150.36 | R19: 15.04 | S19: 2619.23 | T19: 0 | U19: 0 | V19: 0 | W19: 0 | X19: 0 | Y19: 0 | Z19: 0 | AA19: 0 | AB19: 0 | AC19: 0 | AD19: 0 | AE19: P23396
A20: 6 | B20: Surname695 | C20: Forename695 | D20: Riverside Dental Practice | E20: Clinical | F20: CC-RIV | G20: July 2026 | H20: Monthly | I20: 1257L | J20: A | K20: 4686.91 | L20: 4593.17 | M20: 4452.56 | N20: 340.17833 | O20: 3023.81 | P20: 646.79 | Q20: 234.35 | R20: 23.43 | S20: 4082.14 | T20: 0 | U20: 0 | V20: 0 | W20: 0 | X20: 0 | Y20: 0 | Z20: 0 | AA20: 0 | AB20: 0 | AC20: 0 | AD20: 0 | AE20: P15695
A21: 7 | B21: Surname397 | C21: Forename397 | D21: Oakfield Dental Practice | E21: Support | F21: CC-OAK | G21: July 2026 | H21: Monthly | I21: 1257L | J21: A | K21: 2229.71 | L21: 2185.12 | M21: 2118.22 | N21: 161.83333 | O21: 1438.52 | P21: 307.7 | Q21: 111.49 | R21: 11.15 | S21: 1942 | T21: 0 | U21: 0 | V21: 0 | W21: 0 | X21: 0 | Y21: 0 | Z21: 0 | AA21: 0 | AB21: 0 | AC21: 0 | AD21: 0 | AE21: P92397
A22: 8 | B22: Surname006 | C22: Forename006 | D22: Hakim Group Head Office | E22: Support | F22: CC-HAK | G22: July 2026 | H22: Monthly | I22: 1257L | J22: A | K22: 3822.58 | L22: 3746.13 | M22: 3631.45 | N22: 277.445 | O22: 2466.18 | P22: 527.52 | Q22: 191.13 | R22: 19.11 | S22: 3329.34 | T22: 0 | U22: 0 | V22: 0 | W22: 0 | X22: 0 | Y22: 0 | Z22: 0 | AA22: 0 | AB22: 0 | AC22: 0 | AD22: 0 | AE22: P16006
A23: 9 | B23: Surname823 | C23: Forename823 | D23: Kings Road Dental Practice | E23: Support | F23: CC-KIN | G23: July 2026 | H23: Monthly | I23: 1257L | J23: A | K23: 5097.36 | L23: 4995.41 | M23: 4842.49 | N23: 369.97 | O23: 3288.62 | P23: 703.44 | Q23: 254.87 | R23: 25.49 | S23: 4439.64 | T23: 0 | U23: 0 | V23: 0 | W23: 0 | X23: 0 | Y23: 0 | Z23: 0 | AA23: 0 | AB23: 0 | AC23: 0 | AD23: 0 | AE23: P59823
A24: 10 | B24: Surname841 | C24: Forename841 | D24: Elm Park Dental Practice | E24: Support | F24: CC-ELM | G24: July 2026 | H24: Monthly | I24: 1257L | J24: A | K24: 2500.77 | L24: 2450.75 | M24: 2375.73 | N24: 181.5075 | O24: 1613.4 | P24: 345.11 | Q24: 125.04 | R24: 12.5 | S24: 2178.09 | T24: 0 | U24: 0 | V24: 0 | W24: 0 | X24: 0 | Y24: 0 | Z24: 0 | AA24: 0 | AB24: 0 | AC24: 0 | AD24: 0 | AE24: P97841
A25: 11 | B25: Surname431 | C25: Forename431 | D25: Elm Park Dental Practice | E25: Support | F25: CC-ELM | G25: July 2026 | H25: Monthly | I25: 1257L | J25: A | K25: 4118.68 | L25: 4036.31 | M25: 3912.75 | N25: 298.93583 | O25: 2657.21 | P25: 568.38 | Q25: 205.93 | R25: 20.59 | S25: 3587.23 | T25: 0 | U25: 0 | V25: 0 | W25: 0 | X25: 0 | Y25: 0 | Z25: 0 | AA25: 0 | AB25: 0 | AC25: 0 | AD25: 0 | AE25: P32431
A26: 12 | B26: Surname886 | C26: Forename886 | D26: Hakim Group Head Office | E26: Support | F26: CC-HAK | G26: July 2026 | H26: Monthly | I26: 1257L | J26: A | K26: 2608.8 | L26: 2556.62 | M26: 2478.36 | N26: 189.34833 | O26: 1683.1 | P26: 360.01 | Q26: 130.44 | R26: 13.04 | S26: 2272.18 | T26: 0 | U26: 0 | V26: 0 | W26: 0 | X26: 0 | Y26: 0 | Z26: 0 | AA26: 0 | AB26: 0 | AC26: 0 | AD26: 0 | AE26: P93886
... A68: 54 | B68: Surname538 | C68: Forename538 | D68: Elm Park Dental Practice | E68: Support | F68: CC-ELM | G68: July 2026 | H68: Monthly | I68: 1257L | J68: A | K68: 0 | L68: 0 | M68: 0 | N68: 0 | O68: 0 | P68: 0 | Q68: 0 | R68: 0 | S68: 0 | T68: 0 | U68: 0 | V68: 0 | W68: 0 | X68: 0 | Y68: 0 | Z68: 0 | AA68: 0 | AB68: 0 | AC68: 0 | AD68: 0 | AE68: P97538

Sheet Payment Breakdown Prior
A1: Payment Breakdown - prior month (June 2026) - paste from row 14
A12: If this export carries an EXTRA leading 'Reference No' column shifting everything right by one, delete that column before pasting - see Control Sheet warning.
A14: Row | B14: Surname | C14: Forename | D14: Practice | E14: Department | F14: Cost Centre | G14: Payment Date | H14: Frequency | I14: Tax Code | J14: NI Category | K14: Total Gross | L14: Taxable Gross | M14: Pensionable Pay | N14: Hours Paid | O14: Net Pay After Rounding | P14: Employer NI | Q14: Employer Pension | R14: Apprenticeship Levy | S14: Basic Salary | T14: Overtime | U14: Bonus | V14: Mileage Expenses | W14: Other Expenses | X14: SMP | Y14: SSP | Z14: Pension Deduction | AA14: Student Loan | AB14: Attachment of Earnings | AC14: On Call Allowance | AD14: Unsocial Hours Premium | AE14: Reference No
A15: 1 | B15: Surname434 | C15: Forename434 | D15: Riverside Dental Practice | E15: Clinical | F15: CC-RIV | G15: June 2026 | H15: Monthly | I15: 1257L | J15: A | K15: 2853.25 | L15: 2796.18 | M15: 2710.59 | N15: 207.09083 | O15: 1840.81 | P15: 393.75 | Q15: 142.66 | R15: 14.27 | S15: 2485.09 | T15: 0 | U15: 0 | V15: 0 | W15: 0 | X15: 0 | Y15: 0 | Z15: 0 | AA15: 0 | AB15: 0 | AC15: 0 | AD15: 0 | AE15: P23434
A16: 2 | B16: Surname280 | C16: Forename280 | D16: Hakim Group Head Office | E16: Support | F16: CC-HAK | G16: June 2026 | H16: Monthly | I16: 1257L | J16: A | K16: 3817.47 | L16: 3741.12 | M16: 3626.6 | N16: 277.075 | O16: 2462.89 | P16: 526.81 | Q16: 190.87 | R16: 19.09 | S16: 3324.9 | T16: 0 | U16: 0 | V16: 0 | W16: 0 | X16: 0 | Y16: 0 | Z16: 0 | AA16: 0 | AB16: 0 | AC16: 0 | AD16: 0 | AE16: P22280
A17: 3 | B17: Surname426 | C17: Forename426 | D17: Kings Road Dental Practice | E17: Clinical | F17: CC-KIN | G17: June 2026 | H17: Monthly | I17: 1257L | J17: A | K17: 3735.87 | L17: 3661.15 | M17: 3549.08 | N17: 271.1525 | O17: 2410.24 | P17: 515.55 | Q17: 186.79 | R17: 18.68 | S17: 3253.83 | T17: 0 | U17: 0 | V17: 0 | W17: 0 | X17: 0 | Y17: 0 | Z17: 0 | AA17: 0 | AB17: 0 | AC17: 0 | AD17: 0 | AE17: P81426
A18: 4 | B18: Surname926 | C18: Forename926 | D18: Oakfield Dental Practice | E18: Clinical | F18: CC-OAK | G18: June 2026 | H18: Monthly | I18: 1257L | J18: A | K18: 4428.31 | L18: 4339.74 | M18: 4206.89 | N18: 321.41 | O18: 2856.97 | P18: 611.11 | Q18: 221.42 | R18: 22.14 | S18: 3856.92 | T18: 0 | U18: 0 | V18: 0 | W18: 0 | X18: 0 | Y18: 0 | Z18: 0 | AA18: 0 | AB18: 0 | AC18: 0 | AD18: 0 | AE18: P30926
A19: 5 | B19: Surname396 | C19: Forename396 | D19: Oakfield Dental Practice | E19: Clinical | F19: CC-OAK | G19: June 2026 | H19: Monthly | I19: 1257L | J19: A | K19: 2770.73 | L19: 2715.32 | M19: 2632.19 | N19: 201.10083 | O19: 1787.56 | P19: 382.36 | Q19: 138.54 | R19: 13.85 | S19: 2413.21 | T19: 0 | U19: 0 | V19: 0 | W19: 0 | X19: 0 | Y19: 0 | Z19: 0 | AA19: 0 | AB19: 0 | AC19: 0 | AD19: 0 | AE19: P23396
A20: 6 | B20: Surname695 | C20: Forename695 | D20: Riverside Dental Practice | E20: Clinical | F20: CC-RIV | G20: June 2026 | H20: Monthly | I20: 1257L | J20: A | K20: 4534.51 | L20: 4443.82 | M20: 4307.78 | N20: 329.1175 | O20: 2925.49 | P20: 625.76 | Q20: 226.73 | R20: 22.67 | S20: 3949.41 | T20: 0 | U20: 0 | V20: 0 | W20: 0 | X20: 0 | Y20: 0 | Z20: 0 | AA20: 0 | AB20: 0 | AC20: 0 | AD20: 0 | AE20: P15695
A21: 7 | B21: Surname397 | C21: Forename397 | D21: Oakfield Dental Practice | E21: Support | F21: CC-OAK | G21: June 2026 | H21: Monthly | I21: 1257L | J21: A | K21: 2389.85 | L21: 2342.05 | M21: 2270.36 | N21: 173.45667 | O21: 1541.84 | P21: 329.8 | Q21: 119.49 | R21: 11.95 | S21: 2081.48 | T21: 0 | U21: 0 | V21: 0 | W21: 0 | X21: 0 | Y21: 0 | Z21: 0 | AA21: 0 | AB21: 0 | AC21: 0 | AD21: 0 | AE21: P92397
A22: 8 | B22: Surname006 | C22: Forename006 | D22: Hakim Group Head Office | E22: Support | F22: CC-HAK | G22: June 2026 | H22: Monthly | I22: 1257L | J22: A | K22: 3780.81 | L22: 3705.19 | M22: 3591.77 | N22: 274.41417 | O22: 2439.23 | P22: 521.75 | Q22: 189.04 | R22: 18.9 | S22: 3292.97 | T22: 0 | U22: 0 | V22: 0 | W22: 0 | X22: 0 | Y22: 0 | Z22: 0 | AA22: 0 | AB22: 0 | AC22: 0 | AD22: 0 | AE22: P16006
A23: 9 | B23: Surname823 | C23: Forename823 | D23: Kings Road Dental Practice | E23: Support | F23: CC-KIN | G23: June 2026 | H23: Monthly | I23: 1257L | J23: A | K23: 4556.34 | L23: 4465.21 | M23: 4328.52 | N23: 330.70167 | O23: 2939.57 | P23: 628.77 | Q23: 227.82 | R23: 22.78 | S23: 3968.42 | T23: 0 | U23: 0 | V23: 0 | W23: 0 | X23: 0 | Y23: 0 | Z23: 0 | AA23: 0 | AB23: 0 | AC23: 0 | AD23: 0 | AE23: P59823
A24: 10 | B24: Surname841 | C24: Forename841 | D24: Elm Park Dental Practice | E24: Support | F24: CC-ELM | G24: June 2026 | H24: Monthly | I24: 1257L | J24: A | K24: 2623.8 | L24: 2571.32 | M24: 2492.61 | N24: 190.4375 | O24: 1692.78 | P24: 362.08 | Q24: 131.19 | R24: 13.12 | S24: 2285.25 | T24: 0 | U24: 0 | V24: 0 | W24: 0 | X24: 0 | Y24: 0 | Z24: 0 | AA24: 0 | AB24: 0 | AC24: 0 | AD24: 0 | AE24: P97841
A25: 11 | B25: Surname431 | C25: Forename431 | D25: Elm Park Dental Practice | E25: Support | F25: CC-ELM | G25: June 2026 | H25: Monthly | I25: 1257L | J25: A | K25: 3978.02 | L25: 3898.46 | M25: 3779.12 | N25: 288.7275 | O25: 2566.46 | P25: 548.97 | Q25: 198.9 | R25: 19.89 | S25: 3464.73 | T25: 0 | U25: 0 | V25: 0 | W25: 0 | X25: 0 | Y25: 0 | Z25: 0 | AA25: 0 | AB25: 0 | AC25: 0 | AD25: 0 | AE25: P32431
A26: 12 | B26: Surname886 | C26: Forename886 | D26: Hakim Group Head Office | E26: Support | F26: CC-HAK | G26: June 2026 | H26: Monthly | I26: 1257L | J26: A | K26: 2625.89 | L26: 2573.37 | M26: 2494.6 | N26: 190.58917 | O26: 1694.12 | P26: 362.37 | Q26: 131.29 | R26: 13.13 | S26: 2287.07 | T26: 0 | U26: 0 | V26: 0 | W26: 0 | X26: 0 | Y26: 0 | Z26: 0 | AA26: 0 | AB26: 0 | AC26: 0 | AD26: 0 | AE26: P93886
... A68: 54 | B68: Surname538 | C68: Forename538 | D68: Elm Park Dental Practice | E68: Support | F68: CC-ELM | G68: June 2026 | H68: Monthly | I68: 1257L | J68: A | K68: 3334.73 | L68: 3268.04 | M68: 3167.99 | N68: 240.84167 | O68: 2223.15 | P68: 460.19 | Q68: 166.74 | R68: 16.67 | S68: 2890.1 | T68: 0 | U68: 0 | V68: 0 | W68: 0 | X68: 0 | Y68: 0 | Z68: 0 | AA68: 0 | AB68: 0 | AC68: 0 | AD68: 0 | AE68: P97538

Sheet New Starters
A1: New Starters - paste raw iTrent export below from row 13
A11: Paste the full export starting at A13 (headers) so data begins row 14.
A13: Row | B13: Title | C13: Surname | D13: Payroll Number | E13: Practice | F13: Position Name | G13: Start Date | H13: Category | I13: Basis | J13: Department | K13: Personal Reference
A14: 1 | B14: Mr/Mrs | C14: Surname630 | D14: P16630 | E14: Hakim Group Head Office | F14: Payroll Advisor | G14: July 2026 | H14: HGHQ | I14: Permanent | J14: N/A | K14: PR16630
A15: 2 | B15: Mr/Mrs | C15: Surname224 | D15: P22224 | E15: Hakim Group Head Office | F15: Payroll Advisor | G15: July 2026 | H15: HGHQ | I15: Permanent | J15: N/A | K15: PR22224
A16: 3 | B16: Mr/Mrs | C16: Surname092 | D16: P73092 | E16: Kings Road Dental Practice | F16: Orthodontist | G16: July 2026 | H16: Practice Clinical | I16: Permanent | J16: N/A | K16: PR73092
A17: 4 | B17: Mr/Mrs | C17: Surname579 | D17: P31579 | E17: Kings Road Dental Practice | F17: Practice Partner | G17: July 2026 | H17: Practice Partner | I17: Permanent | J17: N/A | K17: PR31579
A18: 5 | B18: Mr/Mrs | C18: Surname468 | D18: P80468 | E18: Oakfield Dental Practice | F18: Practice Administrator | G18: July 2026 | H18: Practice Support | I18: Permanent | J18: N/A | K18: PRTRF1000
A19: 6 | B19: Mr/Mrs | C19: Surname016 | D19: P19016 | E19: Hakim Group Head Office | F19: Finance Analyst | G19: July 2026 | H19: HGHQ | I19: Permanent | J19: N/A | K19: PRTRF1001

Sheet Leavers
A1: Leavers - paste raw iTrent export below from row 11
A9: Paste the full export starting at A11 (headers) so data begins row 12.
A11: Row | B11: Title | C11: Surname | D11: Payroll Number | E11: Practice | F11: Position Name | G11: Leave Date | H11: Category | I11: Basis | J11: Department | K11: Personal Reference
A12: 1 | B12: Mr/Mrs | C12: Surname638 | D12: P69638 | E12: Oakfield Dental Practice | F12: Orthodontist | G12: July 2026 | H12: Practice Clinical | I12: Permanent | J12: N/A | K12: PR69638
A13: 2 | B13: Mr/Mrs | C13: Surname890 | D13: P48890 | E13: Elm Park Dental Practice | F13: Orthodontist | G13: July 2026 | H13: Practice Clinical | I13: Permanent | J13: N/A | K13: PR48890
A14: 3 | B14: Mr/Mrs | C14: Surname492 | D14: P17492 | E14: Kings Road Dental Practice | F14: Regional Support Officer | G14: July 2026 | H14: Employee | I14: Permanent | J14: N/A | K14: PR17492
A15: 4 | B15: Mr/Mrs | C15: Surname615 | D15: P79615 | E15: Riverside Dental Practice | F15: Practice Administrator | G15: July 2026 | H15: Practice Support | I15: Permanent | J15: N/A | K15: PR79615
A16: 5 | B16: Mr/Mrs | C16: Surname602 | D16: P19602 | E16: Riverside Dental Practice | F16: Practice Administrator | G16: July 2026 | H16: Practice Support | I16: Permanent | J16: N/A | K16: PRTRF1000
A17: 6 | B17: Mr/Mrs | C17: Surname745 | D17: P55745 | E17: Kings Road Dental Practice | F17: Finance Analyst | G17: July 2026 | H17: HGHQ | I17: Permanent | J17: N/A | K17: PRTRF1001

Sheet Structure
A1: Structure Report - paste raw iTrent export below from row 12
A10: Paste the full export starting at A12 (headers) so data begins row 13. One row per assignment - staff with more than one contract (e.g. Zero Hours + Permanent) appear on multiple rows.
A12: Structure ID | B12: Title | C12: First Name | D12: Last Name | E12: Practice | F12: Department | G12: Cost Centre | H12: Start Date | I12: End Date | J12: Employment Status | K12: Contracted Hours | L12: Position Name | M12: Grade | N12: Basis | O12: FTE | P12: Payroll Reference | Q12: Line Manager | R12: Region | S12: Division | T12: Pay Group | U12: Tax Code | V12: NI Category | W12: Pension Scheme | X12: Pension Status | Y12: Address Line 1 | Z12: Address Line 2 | AA12: Town | AB12: Postcode | AC12: Email | AD12: Phone | AE12: Bank Name | AF12: Account Ref | AG12: Union Member | AH12: Notes | AI12: Category
A13: 1 | B13: Mr/Mrs | C13: Forename434 | D13: Surname434 | E13: Riverside Dental Practice | F13: Clinical | G13: CC-RIV | H13: 01/01/2022 | J13: Active | K13: 37.5 | L13: Dental Nurse | M13: Band 4 | N13: Permanent | O13: 1 | P13: P23434 | Q13: N/A | R13: N/A | S13: N/A | T13: N/A | U13: N/A | V13: N/A | W13: N/A | X13: N/A | Y13: N/A | Z13: N/A | AA13: N/A | AB13: N/A | AC13: N/A | AD13: N/A | AE13: N/A | AF13: N/A | AG13: N/A | AH13: N/A | AI13: Practice Clinical
A14: 2 | B14: Mr/Mrs | C14: Forename280 | D14: Surname280 | E14: Hakim Group Head Office | F14: Support | G14: CC-HAK | H14: 01/01/2022 | J14: Active | K14: 37.5 | L14: Payroll Advisor | M14: Band 4 | N14: Permanent | O14: 1 | P14: P22280 | Q14: N/A | R14: N/A | S14: N/A | T14: N/A | U14: N/A | V14: N/A | W14: N/A | X14: N/A | Y14: N/A | Z14: N/A | AA14: N/A | AB14: N/A | AC14: N/A | AD14: N/A | AE14: N/A | AF14: N/A | AG14: N/A | AH14: N/A | AI14: HGHQ
A15: 3 | B15: Mr/Mrs | C15: Forename426 | D15: Surname426 | E15: Kings Road Dental Practice | F15: Clinical | G15: CC-KIN | H15: 01/01/2022 | J15: Active | K15: 37.5 | L15: Dentist | M15: Band 4 | N15: Permanent | O15: 1 | P15: P81426 | Q15: N/A | R15: N/A | S15: N/A | T15: N/A | U15: N/A | V15: N/A | W15: N/A | X15: N/A | Y15: N/A | Z15: N/A | AA15: N/A | AB15: N/A | AC15: N/A | AD15: N/A | AE15: N/A | AF15: N/A | AG15: N/A | AH15: N/A | AI15: Practice Clinical
A16: 4 | B16: Mr/Mrs | C16: Forename926 | D16: Surname926 | E16: Oakfield Dental Practice | F16: Clinical | G16: CC-OAK | H16: 01/01/2022 | J16: Active | K16: 37.5 | L16: Dental Nurse | M16: Band 4 | N16: Permanent | O16: 1 | P16: P30926 | Q16: N/A | R16: N/A | S16: N/A | T16: N/A | U16: N/A | V16: N/A | W16: N/A | X16: N/A | Y16: N/A | Z16: N/A | AA16: N/A | AB16: N/A | AC16: N/A | AD16: N/A | AE16: N/A | AF16: N/A | AG16: N/A | AH16: N/A | AI16: Practice Clinical
A17: 5 | B17: Mr/Mrs | C17: Forename396 | D17: Surname396 | E17: Oakfield Dental Practice | F17: Clinical | G17: CC-OAK | H17: 01/01/2022 | J17: Active | K17: 37.5 | L17: Dental Hygienist | M17: Band 4 | N17: Permanent | O17: 1 | P17: P23396 | Q17: N/A | R17: N/A | S17: N/A | T17: N/A | U17: N/A | V17: N/A | W17: N/A | X17: N/A | Y17: N/A | Z17: N/A | AA17: N/A | AB17: N/A | AC17: N/A | AD17: N/A | AE17: N/A | AF17: N/A | AG17: N/A | AH17: N/A | AI17: Practice Clinical
A18: 6 | B18: Mr/Mrs | C18: Forename695 | D18: Surname695 | E18: Riverside Dental Practice | F18: Clinical | G18: CC-RIV | H18: 01/01/2022 | J18: Active | K18: 37.5 | L18: Dental Nurse | M18: Band 4 | N18: Permanent | O18: 1 | P18: P15695 | Q18: N/A | R18: N/A | S18: N/A | T18: N/A | U18: N/A | V18: N/A | W18: N/A | X18: N/A | Y18: N/A | Z18: N/A | AA18: N/A | AB18: N/A | AC18: N/A | AD18: N/A | AE18: N/A | AF18: N/A | AG18: N/A | AH18: N/A | AI18: Practice Clinical
A19: 7 | B19: Mr/Mrs | C19: Forename397 | D19: Surname397 | E19: Oakfield Dental Practice | F19: Support | G19: CC-OAK | H19: 01/01/2022 | J19: Active | K19: 37.5 | L19: Treatment Coordinator | M19: Band 4 | N19: Permanent | O19: 1 | P19: P92397 | Q19: N/A | R19: N/A | S19: N/A | T19: N/A | U19: N/A | V19: N/A | W19: N/A | X19: N/A | Y19: N/A | Z19: N/A | AA19: N/A | AB19: N/A | AC19: N/A | AD19: N/A | AE19: N/A | AF19: N/A | AG19: N/A | AH19: N/A | AI19: Practice Support
A20: 8 | B20: Mr/Mrs | C20: Forename006 | D20: Surname006 | E20: Hakim Group Head Office | F20: Support | G20: CC-HAK | H20: 01/01/2022 | J20: Active | K20: 37.5 | L20: Finance Analyst | M20: Band 4 | N20: Permanent | O20: 1 | P20: P16006 | Q20: N/A | R20: N/A | S20: N/A | T20: N/A | U20: N/A | V20: N/A | W20: N/A | X20: N/A | Y20: N/A | Z20: N/A | AA20: N/A | AB20: N/A | AC20: N/A | AD20: N/A | AE20: N/A | AF20: N/A | AG20: N/A | AH20: N/A | AI20: HGHQ
A21: 9 | B21: Mr/Mrs | C21: Forename823 | D21: Surname823 | E21: Kings Road Dental Practice | F21: Support | G21: CC-KIN | H21: 01/01/2022 | J21: Active | K21: 37.5 | L21: Practice Receptionist | M21: Band 4 | N21: Permanent | O21: 1 | P21: P59823 | Q21: N/A | R21: N/A | S21: N/A | T21: N/A | U21: N/A | V21: N/A | W21: N/A | X21: N/A | Y21: N/A | Z21: N/A | AA21: N/A | AB21: N/A | AC21: N/A | AD21: N/A | AE21: N/A | AF21: N/A | AG21: N/A | AH21: N/A | AI21: Practice Support
A22: 10 | B22: Mr/Mrs | C22: Forename841 | D22: Surname841 | E22: Elm Park Dental Practice | F22: Support | G22: CC-ELM | H22: 01/01/2022 | J22: Active | K22: 37.5 | L22: Treatment Coordinator | M22: Band 4 | N22: Permanent | O22: 1 | P22: P97841 | Q22: N/A | R22: N/A | S22: N/A | T22: N/A | U22: N/A | V22: N/A | W22: N/A | X22: N/A | Y22: N/A | Z22: N/A | AA22: N/A | AB22: N/A | AC22: N/A | AD22: N/A | AE22: N/A | AF22: N/A | AG22: N/A | AH22: N/A | AI22: Practice Support
A23: 11 | B23: Mr/Mrs | C23: Forename431 | D23: Surname431 | E23: Elm Park Dental Practice | F23: Support | G23: CC-ELM | H23: 01/01/2022 | J23: Active | K23: 37.5 | L23: Practice Administrator | M23: Band 4 | N23: Permanent | O23: 1 | P23: P32431 | Q23: N/A | R23: N/A | S23: N/A | T23: N/A | U23: N/A | V23: N/A | W23: N/A | X23: N/A | Y23: N/A | Z23: N/A | AA23: N/A | AB23: N/A | AC23: N/A | AD23: N/A | AE23: N/A | AF23: N/A | AG23: N/A | AH23: N/A | AI23: Practice Support
A24: 12 | B24: Mr/Mrs | C24: Forename886 | D24: Surname886 | E24: Hakim Group Head Office | F24: Support | G24: CC-HAK | H24: 01/01/2022 | J24: Active | K24: 37.5 | L24: HR Business Partner | M24: Band 4 | N24: Permanent | O24: 1 | P24: P93886 | Q24: N/A | R24: N/A | S24: N/A | T24: N/A | U24: N/A | V24: N/A | W24: N/A | X24: N/A | Y24: N/A | Z24: N/A | AA24: N/A | AB24: N/A | AC24: N/A | AD24: N/A | AE24: N/A | AF24: N/A | AG24: N/A | AH24: N/A | AI24: HGHQ
... A56: 44 | B56: Mr/Mrs | C56: Forename579 | D56: Surname579 | E56: Kings Road Dental Practice | F56: Support | G56: CC-KIN | H56: 01/01/2022 | J56: Active | K56: 37.5 | L56: Practice Partner | M56: Band 4 | N56: Permanent | O56: 1 | P56: P31579 | Q56: N/A | R56: N/A | S56: N/A | T56: N/A | U56: N/A | V56: N/A | W56: N/A | X56: N/A | Y56: N/A | Z56: N/A | AA56: N/A | AB56: N/A | AC56: N/A | AD56: N/A | AE56: N/A | AF56: N/A | AG56: N/A | AH56: N/A | AI56: Practice Partner
A57: 45 | B57: Mr/Mrs | C57: Forename638 | D57: Surname638 | E57: Oakfield Dental Practice | F57: Clinical | G57: CC-OAK | H57: 01/01/2022 | I57: July 2026 | J57: Leaver | K57: 37.5 | L57: Orthodontist | M57: Band 4 | N57: Permanent | O57: 1 | P57: P69638 | Q57: N/A | R57: N/A | S57: N/A | T57: N/A | U57: N/A | V57: N/A | W57: N/A | X57: N/A | Y57: N/A | Z57: N/A | AA57: N/A | AB57: N/A | AC57: N/A | AD57: N/A | AE57: N/A | AF57: N/A | AG57: N/A | AH57: N/A | AI57: Practice Clinical
A58: 46 | B58: Mr/Mrs | C58: Forename890 | D58: Surname890 | E58: Elm Park Dental Practice | F58: Clinical | G58: CC-ELM | H58: 01/01/2022 | I58: July 2026 | J58: Leaver | K58: 37.5 | L58: Orthodontist | M58: Band 4 | N58: Permanent | O58: 1 | P58: P48890 | Q58: N/A | R58: N/A | S58: N/A | T58: N/A | U58: N/A | V58: N/A | W58: N/A | X58: N/A | Y58: N/A | Z58: N/A | AA58: N/A | AB58: N/A | AC58: N/A | AD58: N/A | AE58: N/A | AF58: N/A | AG58: N/A | AH58: N/A | AI58: Practice Clinical
A59: 47 | B59: Mr/Mrs | C59: Forename492 | D59: Surname492 | E59: Kings Road Dental Practice | F59: Support | G59: CC-KIN | H59: 01/01/2022 | I59: July 2026 | J59: Leaver | K59: 37.5 | L59: Regional Support Officer | M59: Band 4 | N59: Permanent | O59: 1 | P59: P17492 | Q59: N/A | R59: N/A | S59: N/A | T59: N/A | U59: N/A | V59: N/A | W59: N/A | X59: N/A | Y59: N/A | Z59: N/A | AA59: N/A | AB59: N/A | AC59: N/A | AD59: N/A | AE59: N/A | AF59: N/A | AG59: N/A | AH59: N/A | AI59: Employee
A60: 48 | B60: Mr/Mrs | C60: Forename615 | D60: Surname615 | E60: Riverside Dental Practice | F60: Support | G60: CC-RIV | H60: 01/01/2022 | I60: July 2026 | J60: Leaver | K60: 37.5 | L60: Practice Administrator | M60: Band 4 | N60: Permanent | O60: 1 | P60: P79615 | Q60: N/A | R60: N/A | S60: N/A | T60: N/A | U60: N/A | V60: N/A | W60: N/A | X60: N/A | Y60: N/A | Z60: N/A | AA60: N/A | AB60: N/A | AC60: N/A | AD60: N/A | AE60: N/A | AF60: N/A | AG60: N/A | AH60: N/A | AI60: Practice Support
A61: 49 | B61: Mr/Mrs | C61: Forename356 | D61: Surname356 | E61: Kings Road Dental Practice | F61: Support | G61: CC-KIN | H61: 01/01/2022 | J61: Active | K61: 0 | L61: Bank Dental Nurse | M61: Band 4 | N61: Zero Hours | O61: 0 | P61: P34356 | Q61: N/A | R61: N/A | S61: N/A | T61: N/A | U61: N/A | V61: N/A | W61: N/A | X61: N/A | Y61: N/A | Z61: N/A | AA61: N/A | AB61: N/A | AC61: N/A | AD61: N/A | AE61: N/A | AF61: N/A | AG61: N/A | AH61: N/A | AI61: Practice Support
A62: 50 | B62: Mr/Mrs | C62: Forename828 | D62: Surname828 | E62: Riverside Dental Practice | F62: Support | G62: CC-RIV | H62: 01/01/2022 | J62: Active | K62: 0 | L62: Bank Dental Nurse | M62: Band 4 | N62: Zero Hours | O62: 0 | P62: P40828 | Q62: N/A | R62: N/A | S62: N/A | T62: N/A | U62: N/A | V62: N/A | W62: N/A | X62: N/A | Y62: N/A | Z62: N/A | AA62: N/A | AB62: N/A | AC62: N/A | AD62: N/A | AE62: N/A | AF62: N/A | AG62: N/A | AH62: N/A | AI62: Practice Support
A63: 51 | B63: Mr/Mrs | C63: Forename271 | D63: Surname271 | E63: Oakfield Dental Practice | F63: Support | G63: CC-OAK | H63: 01/01/2022 | J63: Active | K63: 0 | L63: Bank Dental Nurse | M63: Band 4 | N63: Zero Hours | O63: 0 | P63: P42271 | Q63: N/A | R63: N/A | S63: N/A | T63: N/A | U63: N/A | V63: N/A | W63: N/A | X63: N/A | Y63: N/A | Z63: N/A | AA63: N/A | AB63: N/A | AC63: N/A | AD63: N/A | AE63: N/A | AF63: N/A | AG63: N/A | AH63: N/A | AI63: Practice Support
A64: 52 | B64: Mr/Mrs | C64: Forename503 | D64: Surname503 | E64: Riverside Dental Practice | F64: Support | G64: CC-RIV | H64: 01/01/2022 | J64: Active | K64: 0 | L64: Bank Dental Nurse | M64: Band 4 | N64: Zero Hours | O64: 0 | P64: P86503 | Q64: N/A | R64: N/A | S64: N/A | T64: N/A | U64: N/A | V64: N/A | W64: N/A | X64: N/A | Y64: N/A | Z64: N/A | AA64: N/A | AB64: N/A | AC64: N/A | AD64: N/A | AE64: N/A | AF64: N/A | AG64: N/A | AH64: N/A | AI64: Practice Support
A65: 53 | B65: Mr/Mrs | C65: Forename814 | D65: Surname814 | E65: Elm Park Dental Practice | F65: Support | G65: CC-ELM | H65: 01/01/2022 | J65: Active | K65: 0 | L65: Regional Support Officer | M65: Band 4 | N65: Zero Hours | O65: 0 | P65: P44814 | Q65: N/A | R65: N/A | S65: N/A | T65: N/A | U65: N/A | V65: N/A | W65: N/A | X65: N/A | Y65: N/A | Z65: N/A | AA65: N/A | AB65: N/A | AC65: N/A | AD65: N/A | AE65: N/A | AF65: N/A | AG65: N/A | AH65: N/A | AI65: Employee
A66: 54 | B66: Mr/Mrs | C66: Forename814 | D66: Surname814 | E66: Elm Park Dental Practice | F66: Support | G66: CC-ELM | H66: 01/01/2022 | J66: Active | K66: 37.5 | L66: Regional Support Officer | M66: Band 4 | N66: Permanent | O66: 1 | P66: P44814 | Q66: N/A | R66: N/A | S66: N/A | T66: N/A | U66: N/A | V66: N/A | W66: N/A | X66: N/A | Y66: N/A | Z66: N/A | AA66: N/A | AB66: N/A | AC66: N/A | AD66: N/A | AE66: N/A | AF66: N/A | AG66: N/A | AH66: N/A | AI66: Employee
A67: 55 | B67: Mr/Mrs | C67: Forename508 | D67: Surname508 | E67: Oakfield Dental Practice | F67: Clinical | G67: CC-OAK | H67: 01/01/2022 | J67: Active | K67: 0 | L67: Dental Nurse | M67: Band 4 | N67: Zero Hours | O67: 0 | P67: P19508 | Q67: N/A | R67: N/A | S67: N/A | T67: N/A | U67: N/A | V67: N/A | W67: N/A | X67: N/A | Y67: N/A | Z67: N/A | AA67: N/A | AB67: N/A | AC67: N/A | AD67: N/A | AE67: N/A | AF67: N/A | AG67: N/A | AH67: N/A | AI67: Practice Clinical
A68: 56 | B68: Mr/Mrs | C68: Forename508 | D68: Surname508 | E68: Oakfield Dental Practice | F68: Clinical | G68: CC-OAK | H68: 01/01/2022 | J68: Active | K68: 37.5 | L68: Dental Nurse | M68: Band 4 | N68: Permanent | O68: 1 | P68: P19508 | Q68: N/A | R68: N/A | S68: N/A | T68: N/A | U68: N/A | V68: N/A | W68: N/A | X68: N/A | Y68: N/A | Z68: N/A | AA68: N/A | AB68: N/A | AC68: N/A | AD68: N/A | AE68: N/A | AF68: N/A | AG68: N/A | AH68: N/A | AI68: Practice Clinical
A69: 57 | B69: Mr/Mrs | C69: Forename602 | D69: Surname602 | E69: Riverside Dental Practice | F69: Support | G69: CC-RIV | H69: 01/01/2022 | I69: July 2026 | J69: Leaver | K69: 37.5 | L69: Practice Administrator | M69: Band 4 | N69: Permanent | O69: 1 | P69: P19602 | Q69: N/A | R69: N/A | S69: N/A | T69: N/A | U69: N/A | V69: N/A | W69: N/A | X69: N/A | Y69: N/A | Z69: N/A | AA69: N/A | AB69: N/A | AC69: N/A | AD69: N/A | AE69: N/A | AF69: N/A | AG69: N/A | AH69: N/A | AI69: Practice Support
A70: 58 | B70: Mr/Mrs | C70: Forename468 | D70: Surname468 | E70: Oakfield Dental Practice | F70: Support | G70: CC-OAK | H70: 01/01/2022 | J70: Active | K70: 37.5 | L70: Practice Administrator | M70: Band 4 | N70: Permanent | O70: 1 | P70: P80468 | Q70: N/A | R70: N/A | S70: N/A | T70: N/A | U70: N/A | V70: N/A | W70: N/A | X70: N/A | Y70: N/A | Z70: N/A | AA70: N/A | AB70: N/A | AC70: N/A | AD70: N/A | AE70: N/A | AF70: N/A | AG70: N/A | AH70: N/A | AI70: Practice Support
A71: 59 | B71: Mr/Mrs | C71: Forename745 | D71: Surname745 | E71: Kings Road Dental Practice | F71: Support | G71: CC-KIN | H71: 01/01/2022 | I71: July 2026 | J71: Leaver | K71: 37.5 | L71: Finance Analyst | M71: Band 4 | N71: Permanent | O71: 1 | P71: P55745 | Q71: N/A | R71: N/A | S71: N/A | T71: N/A | U71: N/A | V71: N/A | W71: N/A | X71: N/A | Y71: N/A | Z71: N/A | AA71: N/A | AB71: N/A | AC71: N/A | AD71: N/A | AE71: N/A | AF71: N/A | AG71: N/A | AH71: N/A | AI71: HGHQ
A72: 60 | B72: Mr/Mrs | C72: Forename016 | D72: Surname016 | E72: Hakim Group Head Office | F72: Support | G72: CC-HAK | H72: 01/01/2022 | J72: Active | K72: 37.5 | L72: Finance Analyst | M72: Band 4 | N72: Permanent | O72: 1 | P72: P19016 | Q72: N/A | R72: N/A | S72: N/A | T72: N/A | U72: N/A | V72: N/A | W72: N/A | X72: N/A | Y72: N/A | Z72: N/A | AA72: N/A | AB72: N/A | AC72: N/A | AD72: N/A | AE72: N/A | AF72: N/A | AG72: N/A | AH72: N/A | AI72: HGHQ
A73: 61 | B73: Mr/Mrs | C73: Forename200 | D73: Surname200 | E73: Kings Road Dental Practice | F73: Clinical | G73: CC-KIN | H73: 01/01/2022 | J73: Active | K73: 37.5 | L73: Dental Hygienist | M73: Band 4 | N73: Permanent | O73: 1 | P73: P81200 | Q73: N/A | R73: N/A | S73: N/A | T73: N/A | U73: N/A | V73: N/A | W73: N/A | X73: N/A | Y73: N/A | Z73: N/A | AA73: N/A | AB73: N/A | AC73: N/A | AD73: N/A | AE73: N/A | AF73: N/A | AG73: N/A | AH73: N/A | AI73: Practice Clinical
A74: 62 | B74: Mr/Mrs | C74: Forename538 | D74: Surname538 | E74: Elm Park Dental Practice | F74: Support | G74: CC-ELM | H74: 01/01/2022 | J74: Active | K74: 37.5 | L74: Practice Administrator | M74: Band 4 | N74: Permanent | O74: 1 | P74: P97538 | Q74: N/A | R74: N/A | S74: N/A | T74: N/A | U74: N/A | V74: N/A | W74: N/A | X74: N/A | Y74: N/A | Z74: N/A | AA74: N/A | AB74: N/A | AC74: N/A | AD74: N/A | AE74: N/A | AF74: N/A | AG74: N/A | AH74: N/A | AI74: Practice Support
