Workbook

Sheet Summary
A1: NMW and NLW uplift impact from 6 April 2027
A3: Employees in file | B3: =COUNT(Employees!F2:F501)
A4: Employees needing an uplift | B4: =COUNTIF(Employees!L2:L501,"Uplift needed")
A5: of which aged 21 and over | B5: =COUNTIFS(Employees!L2:L501,"Uplift needed",Employees!J2:J501,">=21")
A6: of which aged 18 to 20 | B6: =COUNTIFS(Employees!L2:L501,"Uplift needed",Employees!J2:J501,">=18",Employees!J2:J501,"<21")
A7: of which under 18 | B7: =COUNTIFS(Employees!L2:L501,"Uplift needed",Employees!J2:J501,"<18")
A8: Current annual pay bill (pro-rated) | B8: =SUM(Employees!D2:D501)
A9: Annual salary uplift | B9: =SUM(Employees!Q2:Q501)
A10: Employer NI increase | B10: =SUM(Employees!R2:R501)
A11: Employer pension increase | B11: =SUM(Employees!S2:S501)
A12: Total annual cost to company | B12: =SUM(Employees!T2:T501)
A13: Monthly cost to company | B13: =B12/12
A14: People who move age band during 2027/28 | B14: =COUNTIF(Employees!M2:M501,"Turns*")
A16: Notes
A17: Green columns A to I: your existing data. Yellow columns J to T: new formulas.
A18: All rates and thresholds sit on the Rates sheet. Change them there and every row updates.
A19: Cost is a full-year figure for April 2027. People who turn 18 or 21 later in the year are flagged, not costed.
A20: Uplift scales your own FTE and pro-rated salary by new rate divided by current rate.

Sheet Rates
A1: Setting | B1: Value | C1: Notes
A2: Effective date (first day of tax year) | B2: 46483 | C2: Age is worked out on this date
A3: Tax year end | B3: 46848 | C3: Used to flag people who move age band during the year
A4: NLW 21 and over (new) | B4: 13.2 | C4: Per Budget announcement. Confirm against GOV.UK
A5: NMW 18 to 20 (new) | B5: 11.27 | C5: Per Budget announcement. Confirm against GOV.UK
A6: NMW 16 to 17 (new) | B6: 8 | C6: PLACEHOLDER. Current rate shown. Update when confirmed
A7: Apprentice rate (new) | B7: 8 | C7: PLACEHOLDER. Current rate shown. Update when confirmed
A8: Employer NI rate | B8: 0.15 | C8: Current rate from April 2025. Confirm for 2027/28
A9: Employer NI secondary threshold (annual) | B9: 5000 | C9: Current threshold. Confirm for 2027/28
A10: Employer pension rate | B10: 0.03 | C10: PLACEHOLDER. Set to the Hakim Group employer rate
A11: Pension basis (Qualifying or Full) | B11: Qualifying | C11: Qualifying = band earnings only. Full = whole salary
A12: Pension lower limit (annual) | B12: 6240 | C12: Qualifying earnings lower limit. Confirm for 2027/28
A13: Pension upper limit (annual) | B13: 50270 | C13: Qualifying earnings upper limit. Confirm for 2027/28

Sheet Employees
A1: Reference No | B1: Calculated FTE | C1: FTE salary | D1: Pro-Rated Actual Scalepoint Val | E1: Hourly rate | F1: DOB | G1: Age | H1: NMW Check | I1: Apprentice (Y/N) | J1: Age at 06/04/2027 | K1: New minimum rate | L1: April 2027 check | M1: Changes age band in 2027/28 | N1: New hourly rate | O1: New FTE salary | P1: New pro-rated salary | Q1: Salary uplift | R1: Employer NI increase | S1: Employer pension increase | T1: Total cost to company
A2: 1 | B2: 0.52667 | C2: 24784.5 | D2: 13053.17 | E2: 12.71 | F2: 25015 | G2: =IF(F2="","",DATEDIF(F2,TODAY(),"Y")) | H2: =IF(E2="","",IF(E2>=12.71,"OK","Check")) | I2: N | J2: =IF($F2="","",DATEDIF($F2,Rates!$B$2,"Y")) | K2: =IF($F2="","",IF(UPPER($I2)="Y",Rates!$B$7,IF(J2>=21,Rates!$B$4,IF(J2>=18,Rates!$B$5,Rates!$B$6)))) | L2: =IF($F2="","",IF($E2<K2,"Uplift needed","OK")) | M2: =IF($F2="","",IF(AND(J2<21,DATEDIF($F2,Rates!$B$3,"Y")>=21),"Turns 21",IF(AND(J2<18,DATEDIF($F2,Rates!$B$3,"Y")>=18),"Turns 18",""))) | N2: =IF($F2="","",MAX($E2,K2)) | O2: =IF($F2="","",ROUND($C2*N2/$E2,2)) | P2: =IF($F2="","",ROUND($D2*N2/$E2,2)) | Q2: =IF($F2="","",ROUND(P2-$D2,2)) | R2: =IF($F2="","",ROUND(Rates!$B$8*(MAX(0,P2-Rates!$B$9)-MAX(0,$D2-Rates!$B$9)),2)) | S2: =IF($F2="","",ROUND(Rates!$B$10*IF(Rates!$B$11="Full",P2-$D2,MAX(0,MIN(P2,Rates!$B$13)-Rates!$B$12)-MAX(0,MIN($D2,Rates!$B$13)-Rates!$B$12)),2)) | T2: =IF($F2="","",ROUND(Q2+R2+S2,2))
A3: 2 | B3: 0.58 | C3: 24784.5 | D3: 14375.01 | E3: 12.71 | F3: 23447 | G3: =IF(F3="","",DATEDIF(F3,TODAY(),"Y")) | H3: =IF(E3="","",IF(E3>=12.71,"OK","Check")) | I3: N | J3: =IF($F3="","",DATEDIF($F3,Rates!$B$2,"Y")) | K3: =IF($F3="","",IF(UPPER($I3)="Y",Rates!$B$7,IF(J3>=21,Rates!$B$4,IF(J3>=18,Rates!$B$5,Rates!$B$6)))) | L3: =IF($F3="","",IF($E3<K3,"Uplift needed","OK")) | M3: =IF($F3="","",IF(AND(J3<21,DATEDIF($F3,Rates!$B$3,"Y")>=21),"Turns 21",IF(AND(J3<18,DATEDIF($F3,Rates!$B$3,"Y")>=18),"Turns 18",""))) | N3: =IF($F3="","",MAX($E3,K3)) | O3: =IF($F3="","",ROUND($C3*N3/$E3,2)) | P3: =IF($F3="","",ROUND($D3*N3/$E3,2)) | Q3: =IF($F3="","",ROUND(P3-$D3,2)) | R3: =IF($F3="","",ROUND(Rates!$B$8*(MAX(0,P3-Rates!$B$9)-MAX(0,$D3-Rates!$B$9)),2)) | S3: =IF($F3="","",ROUND(Rates!$B$10*IF(Rates!$B$11="Full",P3-$D3,MAX(0,MIN(P3,Rates!$B$13)-Rates!$B$12)-MAX(0,MIN($D3,Rates!$B$13)-Rates!$B$12)),2)) | T3: =IF($F3="","",ROUND(Q3+R3+S3,2))
J4: =IF($F4="","",DATEDIF($F4,Rates!$B$2,"Y")) | K4: =IF($F4="","",IF(UPPER($I4)="Y",Rates!$B$7,IF(J4>=21,Rates!$B$4,IF(J4>=18,Rates!$B$5,Rates!$B$6)))) | L4: =IF($F4="","",IF($E4<K4,"Uplift needed","OK")) | M4: =IF($F4="","",IF(AND(J4<21,DATEDIF($F4,Rates!$B$3,"Y")>=21),"Turns 21",IF(AND(J4<18,DATEDIF($F4,Rates!$B$3,"Y")>=18),"Turns 18",""))) | N4: =IF($F4="","",MAX($E4,K4)) | O4: =IF($F4="","",ROUND($C4*N4/$E4,2)) | P4: =IF($F4="","",ROUND($D4*N4/$E4,2)) | Q4: =IF($F4="","",ROUND(P4-$D4,2)) | R4: =IF($F4="","",ROUND(Rates!$B$8*(MAX(0,P4-Rates!$B$9)-MAX(0,$D4-Rates!$B$9)),2)) | S4: =IF($F4="","",ROUND(Rates!$B$10*IF(Rates!$B$11="Full",P4-$D4,MAX(0,MIN(P4,Rates!$B$13)-Rates!$B$12)-MAX(0,MIN($D4,Rates!$B$13)-Rates!$B$12)),2)) | T4: =IF($F4="","",ROUND(Q4+R4+S4,2))
J5: =IF($F5="","",DATEDIF($F5,Rates!$B$2,"Y")) | K5: =IF($F5="","",IF(UPPER($I5)="Y",Rates!$B$7,IF(J5>=21,Rates!$B$4,IF(J5>=18,Rates!$B$5,Rates!$B$6)))) | L5: =IF($F5="","",IF($E5<K5,"Uplift needed","OK")) | M5: =IF($F5="","",IF(AND(J5<21,DATEDIF($F5,Rates!$B$3,"Y")>=21),"Turns 21",IF(AND(J5<18,DATEDIF($F5,Rates!$B$3,"Y")>=18),"Turns 18",""))) | N5: =IF($F5="","",MAX($E5,K5)) | O5: =IF($F5="","",ROUND($C5*N5/$E5,2)) | P5: =IF($F5="","",ROUND($D5*N5/$E5,2)) | Q5: =IF($F5="","",ROUND(P5-$D5,2)) | R5: =IF($F5="","",ROUND(Rates!$B$8*(MAX(0,P5-Rates!$B$9)-MAX(0,$D5-Rates!$B$9)),2)) | S5: =IF($F5="","",ROUND(Rates!$B$10*IF(Rates!$B$11="Full",P5-$D5,MAX(0,MIN(P5,Rates!$B$13)-Rates!$B$12)-MAX(0,MIN($D5,Rates!$B$13)-Rates!$B$12)),2)) | T5: =IF($F5="","",ROUND(Q5+R5+S5,2))
J6: =IF($F6="","",DATEDIF($F6,Rates!$B$2,"Y")) | K6: =IF($F6="","",IF(UPPER($I6)="Y",Rates!$B$7,IF(J6>=21,Rates!$B$4,IF(J6>=18,Rates!$B$5,Rates!$B$6)))) | L6: =IF($F6="","",IF($E6<K6,"Uplift needed","OK")) | M6: =IF($F6="","",IF(AND(J6<21,DATEDIF($F6,Rates!$B$3,"Y")>=21),"Turns 21",IF(AND(J6<18,DATEDIF($F6,Rates!$B$3,"Y")>=18),"Turns 18",""))) | N6: =IF($F6="","",MAX($E6,K6)) | O6: =IF($F6="","",ROUND($C6*N6/$E6,2)) | P6: =IF($F6="","",ROUND($D6*N6/$E6,2)) | Q6: =IF($F6="","",ROUND(P6-$D6,2)) | R6: =IF($F6="","",ROUND(Rates!$B$8*(MAX(0,P6-Rates!$B$9)-MAX(0,$D6-Rates!$B$9)),2)) | S6: =IF($F6="","",ROUND(Rates!$B$10*IF(Rates!$B$11="Full",P6-$D6,MAX(0,MIN(P6,Rates!$B$13)-Rates!$B$12)-MAX(0,MIN($D6,Rates!$B$13)-Rates!$B$12)),2)) | T6: =IF($F6="","",ROUND(Q6+R6+S6,2))
J7: =IF($F7="","",DATEDIF($F7,Rates!$B$2,"Y")) | K7: =IF($F7="","",IF(UPPER($I7)="Y",Rates!$B$7,IF(J7>=21,Rates!$B$4,IF(J7>=18,Rates!$B$5,Rates!$B$6)))) | L7: =IF($F7="","",IF($E7<K7,"Uplift needed","OK")) | M7: =IF($F7="","",IF(AND(J7<21,DATEDIF($F7,Rates!$B$3,"Y")>=21),"Turns 21",IF(AND(J7<18,DATEDIF($F7,Rates!$B$3,"Y")>=18),"Turns 18",""))) | N7: =IF($F7="","",MAX($E7,K7)) | O7: =IF($F7="","",ROUND($C7*N7/$E7,2)) | P7: =IF($F7="","",ROUND($D7*N7/$E7,2)) | Q7: =IF($F7="","",ROUND(P7-$D7,2)) | R7: =IF($F7="","",ROUND(Rates!$B$8*(MAX(0,P7-Rates!$B$9)-MAX(0,$D7-Rates!$B$9)),2)) | S7: =IF($F7="","",ROUND(Rates!$B$10*IF(Rates!$B$11="Full",P7-$D7,MAX(0,MIN(P7,Rates!$B$13)-Rates!$B$12)-MAX(0,MIN($D7,Rates!$B$13)-Rates!$B$12)),2)) | T7: =IF($F7="","",ROUND(Q7+R7+S7,2))
J8: =IF($F8="","",DATEDIF($F8,Rates!$B$2,"Y")) | K8: =IF($F8="","",IF(UPPER($I8)="Y",Rates!$B$7,IF(J8>=21,Rates!$B$4,IF(J8>=18,Rates!$B$5,Rates!$B$6)))) | L8: =IF($F8="","",IF($E8<K8,"Uplift needed","OK")) | M8: =IF($F8="","",IF(AND(J8<21,DATEDIF($F8,Rates!$B$3,"Y")>=21),"Turns 21",IF(AND(J8<18,DATEDIF($F8,Rates!$B$3,"Y")>=18),"Turns 18",""))) | N8: =IF($F8="","",MAX($E8,K8)) | O8: =IF($F8="","",ROUND($C8*N8/$E8,2)) | P8: =IF($F8="","",ROUND($D8*N8/$E8,2)) | Q8: =IF($F8="","",ROUND(P8-$D8,2)) | R8: =IF($F8="","",ROUND(Rates!$B$8*(MAX(0,P8-Rates!$B$9)-MAX(0,$D8-Rates!$B$9)),2)) | S8: =IF($F8="","",ROUND(Rates!$B$10*IF(Rates!$B$11="Full",P8-$D8,MAX(0,MIN(P8,Rates!$B$13)-Rates!$B$12)-MAX(0,MIN($D8,Rates!$B$13)-Rates!$B$12)),2)) | T8: =IF($F8="","",ROUND(Q8+R8+S8,2))
J9: =IF($F9="","",DATEDIF($F9,Rates!$B$2,"Y")) | K9: =IF($F9="","",IF(UPPER($I9)="Y",Rates!$B$7,IF(J9>=21,Rates!$B$4,IF(J9>=18,Rates!$B$5,Rates!$B$6)))) | L9: =IF($F9="","",IF($E9<K9,"Uplift needed","OK")) | M9: =IF($F9="","",IF(AND(J9<21,DATEDIF($F9,Rates!$B$3,"Y")>=21),"Turns 21",IF(AND(J9<18,DATEDIF($F9,Rates!$B$3,"Y")>=18),"Turns 18",""))) | N9: =IF($F9="","",MAX($E9,K9)) | O9: =IF($F9="","",ROUND($C9*N9/$E9,2)) | P9: =IF($F9="","",ROUND($D9*N9/$E9,2)) | Q9: =IF($F9="","",ROUND(P9-$D9,2)) | R9: =IF($F9="","",ROUND(Rates!$B$8*(MAX(0,P9-Rates!$B$9)-MAX(0,$D9-Rates!$B$9)),2)) | S9: =IF($F9="","",ROUND(Rates!$B$10*IF(Rates!$B$11="Full",P9-$D9,MAX(0,MIN(P9,Rates!$B$13)-Rates!$B$12)-MAX(0,MIN($D9,Rates!$B$13)-Rates!$B$12)),2)) | T9: =IF($F9="","",ROUND(Q9+R9+S9,2))
J10: =IF($F10="","",DATEDIF($F10,Rates!$B$2,"Y")) | K10: =IF($F10="","",IF(UPPER($I10)="Y",Rates!$B$7,IF(J10>=21,Rates!$B$4,IF(J10>=18,Rates!$B$5,Rates!$B$6)))) | L10: =IF($F10="","",IF($E10<K10,"Uplift needed","OK")) | M10: =IF($F10="","",IF(AND(J10<21,DATEDIF($F10,Rates!$B$3,"Y")>=21),"Turns 21",IF(AND(J10<18,DATEDIF($F10,Rates!$B$3,"Y")>=18),"Turns 18",""))) | N10: =IF($F10="","",MAX($E10,K10)) | O10: =IF($F10="","",ROUND($C10*N10/$E10,2)) | P10: =IF($F10="","",ROUND($D10*N10/$E10,2)) | Q10: =IF($F10="","",ROUND(P10-$D10,2)) | R10: =IF($F10="","",ROUND(Rates!$B$8*(MAX(0,P10-Rates!$B$9)-MAX(0,$D10-Rates!$B$9)),2)) | S10: =IF($F10="","",ROUND(Rates!$B$10*IF(Rates!$B$11="Full",P10-$D10,MAX(0,MIN(P10,Rates!$B$13)-Rates!$B$12)-MAX(0,MIN($D10,Rates!$B$13)-Rates!$B$12)),2)) | T10: =IF($F10="","",ROUND(Q10+R10+S10,2))
J11: =IF($F11="","",DATEDIF($F11,Rates!$B$2,"Y")) | K11: =IF($F11="","",IF(UPPER($I11)="Y",Rates!$B$7,IF(J11>=21,Rates!$B$4,IF(J11>=18,Rates!$B$5,Rates!$B$6)))) | L11: =IF($F11="","",IF($E11<K11,"Uplift needed","OK")) | M11: =IF($F11="","",IF(AND(J11<21,DATEDIF($F11,Rates!$B$3,"Y")>=21),"Turns 21",IF(AND(J11<18,DATEDIF($F11,Rates!$B$3,"Y")>=18),"Turns 18",""))) | N11: =IF($F11="","",MAX($E11,K11)) | O11: =IF($F11="","",ROUND($C11*N11/$E11,2)) | P11: =IF($F11="","",ROUND($D11*N11/$E11,2)) | Q11: =IF($F11="","",ROUND(P11-$D11,2)) | R11: =IF($F11="","",ROUND(Rates!$B$8*(MAX(0,P11-Rates!$B$9)-MAX(0,$D11-Rates!$B$9)),2)) | S11: =IF($F11="","",ROUND(Rates!$B$10*IF(Rates!$B$11="Full",P11-$D11,MAX(0,MIN(P11,Rates!$B$13)-Rates!$B$12)-MAX(0,MIN($D11,Rates!$B$13)-Rates!$B$12)),2)) | T11: =IF($F11="","",ROUND(Q11+R11+S11,2))
J12: =IF($F12="","",DATEDIF($F12,Rates!$B$2,"Y")) | K12: =IF($F12="","",IF(UPPER($I12)="Y",Rates!$B$7,IF(J12>=21,Rates!$B$4,IF(J12>=18,Rates!$B$5,Rates!$B$6)))) | L12: =IF($F12="","",IF($E12<K12,"Uplift needed","OK")) | M12: =IF($F12="","",IF(AND(J12<21,DATEDIF($F12,Rates!$B$3,"Y")>=21),"Turns 21",IF(AND(J12<18,DATEDIF($F12,Rates!$B$3,"Y")>=18),"Turns 18",""))) | N12: =IF($F12="","",MAX($E12,K12)) | O12: =IF($F12="","",ROUND($C12*N12/$E12,2)) | P12: =IF($F12="","",ROUND($D12*N12/$E12,2)) | Q12: =IF($F12="","",ROUND(P12-$D12,2)) | R12: =IF($F12="","",ROUND(Rates!$B$8*(MAX(0,P12-Rates!$B$9)-MAX(0,$D12-Rates!$B$9)),2)) | S12: =IF($F12="","",ROUND(Rates!$B$10*IF(Rates!$B$11="Full",P12-$D12,MAX(0,MIN(P12,Rates!$B$13)-Rates!$B$12)-MAX(0,MIN($D12,Rates!$B$13)-Rates!$B$12)),2)) | T12: =IF($F12="","",ROUND(Q12+R12+S12,2))
J13: =IF($F13="","",DATEDIF($F13,Rates!$B$2,"Y")) | K13: =IF($F13="","",IF(UPPER($I13)="Y",Rates!$B$7,IF(J13>=21,Rates!$B$4,IF(J13>=18,Rates!$B$5,Rates!$B$6)))) | L13: =IF($F13="","",IF($E13<K13,"Uplift needed","OK")) | M13: =IF($F13="","",IF(AND(J13<21,DATEDIF($F13,Rates!$B$3,"Y")>=21),"Turns 21",IF(AND(J13<18,DATEDIF($F13,Rates!$B$3,"Y")>=18),"Turns 18",""))) | N13: =IF($F13="","",MAX($E13,K13)) | O13: =IF($F13="","",ROUND($C13*N13/$E13,2)) | P13: =IF($F13="","",ROUND($D13*N13/$E13,2)) | Q13: =IF($F13="","",ROUND(P13-$D13,2)) | R13: =IF($F13="","",ROUND(Rates!$B$8*(MAX(0,P13-Rates!$B$9)-MAX(0,$D13-Rates!$B$9)),2)) | S13: =IF($F13="","",ROUND(Rates!$B$10*IF(Rates!$B$11="Full",P13-$D13,MAX(0,MIN(P13,Rates!$B$13)-Rates!$B$12)-MAX(0,MIN($D13,Rates!$B$13)-Rates!$B$12)),2)) | T13: =IF($F13="","",ROUND(Q13+R13+S13,2))
J14: =IF($F14="","",DATEDIF($F14,Rates!$B$2,"Y")) | K14: =IF($F14="","",IF(UPPER($I14)="Y",Rates!$B$7,IF(J14>=21,Rates!$B$4,IF(J14>=18,Rates!$B$5,Rates!$B$6)))) | L14: =IF($F14="","",IF($E14<K14,"Uplift needed","OK")) | M14: =IF($F14="","",IF(AND(J14<21,DATEDIF($F14,Rates!$B$3,"Y")>=21),"Turns 21",IF(AND(J14<18,DATEDIF($F14,Rates!$B$3,"Y")>=18),"Turns 18",""))) | N14: =IF($F14="","",MAX($E14,K14)) | O14: =IF($F14="","",ROUND($C14*N14/$E14,2)) | P14: =IF($F14="","",ROUND($D14*N14/$E14,2)) | Q14: =IF($F14="","",ROUND(P14-$D14,2)) | R14: =IF($F14="","",ROUND(Rates!$B$8*(MAX(0,P14-Rates!$B$9)-MAX(0,$D14-Rates!$B$9)),2)) | S14: =IF($F14="","",ROUND(Rates!$B$10*IF(Rates!$B$11="Full",P14-$D14,MAX(0,MIN(P14,Rates!$B$13)-Rates!$B$12)-MAX(0,MIN($D14,Rates!$B$13)-Rates!$B$12)),2)) | T14: =IF($F14="","",ROUND(Q14+R14+S14,2))
J15: =IF($F15="","",DATEDIF($F15,Rates!$B$2,"Y")) | K15: =IF($F15="","",IF(UPPER($I15)="Y",Rates!$B$7,IF(J15>=21,Rates!$B$4,IF(J15>=18,Rates!$B$5,Rates!$B$6)))) | L15: =IF($F15="","",IF($E15<K15,"Uplift needed","OK")) | M15: =IF($F15="","",IF(AND(J15<21,DATEDIF($F15,Rates!$B$3,"Y")>=21),"Turns 21",IF(AND(J15<18,DATEDIF($F15,Rates!$B$3,"Y")>=18),"Turns 18",""))) | N15: =IF($F15="","",MAX($E15,K15)) | O15: =IF($F15="","",ROUND($C15*N15/$E15,2)) | P15: =IF($F15="","",ROUND($D15*N15/$E15,2)) | Q15: =IF($F15="","",ROUND(P15-$D15,2)) | R15: =IF($F15="","",ROUND(Rates!$B$8*(MAX(0,P15-Rates!$B$9)-MAX(0,$D15-Rates!$B$9)),2)) | S15: =IF($F15="","",ROUND(Rates!$B$10*IF(Rates!$B$11="Full",P15-$D15,MAX(0,MIN(P15,Rates!$B$13)-Rates!$B$12)-MAX(0,MIN($D15,Rates!$B$13)-Rates!$B$12)),2)) | T15: =IF($F15="","",ROUND(Q15+R15+S15,2))
... J501: =IF($F501="","",DATEDIF($F501,Rates!$B$2,"Y")) | K501: =IF($F501="","",IF(UPPER($I501)="Y",Rates!$B$7,IF(J501>=21,Rates!$B$4,IF(J501>=18,Rates!$B$5,Rates!$B$6)))) | L501: =IF($F501="","",IF($E501<K501,"Uplift needed","OK")) | M501: =IF($F501="","",IF(AND(J501<21,DATEDIF($F501,Rates!$B$3,"Y")>=21),"Turns 21",IF(AND(J501<18,DATEDIF($F501,Rates!$B$3,"Y")>=18),"Turns 18",""))) | N501: =IF($F501="","",MAX($E501,K501)) | O501: =IF($F501="","",ROUND($C501*N501/$E501,2)) | P501: =IF($F501="","",ROUND($D501*N501/$E501,2)) | Q501: =IF($F501="","",ROUND(P501-$D501,2)) | R501: =IF($F501="","",ROUND(Rates!$B$8*(MAX(0,P501-Rates!$B$9)-MAX(0,$D501-Rates!$B$9)),2)) | S501: =IF($F501="","",ROUND(Rates!$B$10*IF(Rates!$B$11="Full",P501-$D501,MAX(0,MIN(P501,Rates!$B$13)-Rates!$B$12)-MAX(0,MIN($D501,Rates!$B$13)-Rates!$B$12)),2)) | T501: =IF($F501="","",ROUND(Q501+R501+S501,2))
